Workbook

Sheet ÍNDICE_GENERAL
A1: PROGRAMA DE AUDITORÍA - CUENTAS POR COBRAR
A2: Basado en NIAs 505, 240, 330 - Confirmaciones Externas y Detección de Fraude en Cuentas por Cobrar
A4: Cliente: | B4: [NOMBRE DEL CLIENTE]
A5: Período auditado: | B5: 01/01/2024 - 31/12/2024
A6: Fecha de corte: | B6: 31/12/2024
A7: Auditor responsable: | B7: [NOMBRE DEL AUDITOR]
A9: REF | B9: PROCEDIMIENTO DE AUDITORÍA | C9: OBJETIVO NIA | D9: RIESGO | E9: ESTADO | F9: HALLAZGOS | G9: MATERIALIDAD | H9: RESPONSABLE | I9: FECHA
A10: PT B.1 | B10: Confirmación Positiva de Saldos | C10: NIA 505 - Confirmaciones Externas | D10: 5 | E10: 1 | F10: =PT_B.1_Confirmaciones!B25 -> 3 | G10: =PT_B.1_Confirmaciones!D26 -> 140800000 | H10: [Auditor] | I10: =TODAY() -> 45978
A11: PT B.2 | B11: Análisis de Antigüedad Detallado | C11: Evaluación de deterioro NIA 540 | D11: =PT_B.2_Antiguedad!I17 -> 0 | E11: =PT_B.2_Antiguedad!J17 -> 0 | F11: =PT_B.2_Antiguedad!B24 -> 0 | G11: =PT_B.2_Antiguedad!D25 -> 95430000 | H11: [Auditor] | I11: =TODAY() -> 45978
A12: PT B.3 | B12: Notas Crédito Post-Cierre | C12: Detección de manipulación | D12: =PT_B.3_NC_PostCierre!H16 -> RIESGO GLOBAL: | E12: =PT_B.3_NC_PostCierre!I16 -> CRÍTICO | F12: =PT_B.3_NC_PostCierre!B22 -> 4 | G12: =PT_B.3_NC_PostCierre!D23 -> 43200000 | H12: [Auditor] | I12: =TODAY() -> 45978
A13: PT B.4 | B13: Autorizaciones Cancelaciones | C13: Control de castigos irregulares | D13: =PT_B.4_Autorizaciones!H16 -> RIESGO GLOBAL: | E13: =PT_B.4_Autorizaciones!I16 -> CRÍTICO | F13: =PT_B.4_Autorizaciones!B21 -> 3 | G13: =PT_B.4_Autorizaciones!D22 -> 55500000 | H13: [Auditor] | I13: =TODAY() -> 45978
A14: PT B.5 | B14: Cut-Off Ventas y Devoluciones | C14: NIA 330 - Corte de operaciones | D14: =PT_B.5_CutOff!I16 -> 0 | E14: =PT_B.5_CutOff!J16 -> 0 | F14: =PT_B.5_CutOff!B23 -> 4 | G14: =PT_B.5_CutOff!D24 -> 50200005 | H14: [Auditor] | I14: =TODAY() -> 45978
A15: PT B.6 | B15: Partes Relacionadas | C15: NIA 550 - Revelación adecuada | D15: =PT_B.6_PartesRel!H16 -> RIESGO GLOBAL: | E15: =PT_B.6_PartesRel!I16 -> ALTO | F15: =PT_B.6_PartesRel!B21 -> 3 | G15: =PT_B.6_PartesRel!D22 -> 82000000 | H15: [Auditor] | I15: =TODAY() -> 45978
A16: PT B.7 | B16: Concentración por Cliente | C16: Evaluación de riesgo crediticio | D16: =PT_B.7_Concentracion!I16 -> 0 | E16: =PT_B.7_Concentracion!J16 -> 0 | F16: =PT_B.7_Concentracion!B23 -> Dependencia crítica | G16: =PT_B.7_Concentracion!D24 -> 280500000 | H16: [Auditor] | I16: =TODAY() -> 45978
A17: PT B.8 | B17: Colateral y Garantías | C17: Verificación de respaldos | D17: =PT_B.8_Colateral!H16 -> RIESGO GLOBAL: | E17: =PT_B.8_Colateral!I16 -> ALTO | F17: =PT_B.8_Colateral!B21 -> 5 | G17: =PT_B.8_Colateral!D22 -> 136500000 | H17: [Auditor] | I17: =TODAY() -> 45978
A18: PT B.9 | B18: Acuerdos Side-Letter | C18: Detección de condiciones ocultas | D18: =PT_B.9_SideLetter!H16 -> 0 | E18: =PT_B.9_SideLetter!I16 -> 0 | F18: =PT_B.9_SideLetter!B20 -> 33300000 | G18: =PT_B.9_SideLetter!D21 -> 111000000 | H18: [Auditor] | I18: =TODAY() -> 45978
A19: PT B.10 | B19: Ratios de Rotación | C19: Análisis de eficiencia | D19: =[1]PT_B!I17 -> #REF! | E19: =[1]PT_B!J17 -> #REF! | F19: =[1]PT_B!B23 -> #REF! | G19: =[1]PT_B!D24 -> #REF! | H19: [Auditor] | I19: =TODAY() -> 45978
A20: PT B.11 | B20: Facturas Duplicadas | C20: Control de secuencias | D20: =PT_B.11_Duplicadas!H16 -> RIESGO GLOBAL: | E20: =PT_B.11_Duplicadas!I16 -> CRÍTICO | F20: =PT_B.11_Duplicadas!B21 -> 3 | G20: =PT_B.11_Duplicadas!D22 -> 45500000 | H20: [Auditor] | I20: =TODAY() -> 45978
A21: PT B.12 | B21: Write-Offs Pre-Cierre | C21: Manipulación de resultados | D21: =PT_B.12_WriteOffs!H16 -> RIESGO GLOBAL: | E21: =PT_B.12_WriteOffs!I16 -> CRÍTICO | F21: =PT_B.12_WriteOffs!B21 -> 5 | G21: =PT_B.12_WriteOffs!D22 -> 24000000 | H21: [Auditor] | I21: =TODAY() -> 45978

Sheet PT_B.1_Confirmaciones
A1: PT B.1 - CONFIRMACIÓN POSITIVA DE SALDOS
A2: NIA 505 - Confirmaciones Externas | Objetivo: Obtener evidencia de auditoría directa de terceros
A4: Fecha de confirmación: | B4: 31/12/2024
A7: N° Cliente | B7: Nombre del Cliente | C7: Saldo Libros | D7: Conf. Enviada | E7: Conf. Recibida | F7: Saldo Confirmado | G7: Diferencia | H7: % Dif | I7: Riesgo | J7: Estado | K7: Acción Requerida
A8: CL-001 | B8: ACME CORPORATION S.A. | C8: 45800000 | D8: SÍ | E8: SÍ | F8: 100 | G8: =IF(E8="SÍ",C8-F8,C8) -> 45799900 | H8: =IF(C8=0,0,ABS(G8/C8)) -> 0.99999782 | I8: =IF(E8="NO","CRÍTICO",IF(H8>0.1,"ALTO",IF(H8>0.05,"MEDIO","BAJO"))) -> ALTO | J8: =IF(I8="CRÍTICO","🚨 SIN RESPUESTA",IF(I8="ALTO","🔴 DIFERENCIA",IF(I8="MEDIO","⚠ REVISAR","✓ CONFIRMADO"))) -> 🔴 DIFERENCIA | K8: =IF(E8="NO","Procedimientos alternativos",IF(H8>0.05,"Investigar diferencia","Ninguna")) -> Investigar diferencia
A9: CL-002 | B9: DISTRIBUIDORA BETA LTDA | C9: 28500000 | D9: SÍ | E9: SÍ | F9: 26200000 | G9: =IF(E9="SÍ",C9-F9,C9) -> 2300000 | H9: =IF(C9=0,0,ABS(G9/C9)) -> 0.080701754 | I9: =IF(E9="NO","CRÍTICO",IF(H9>0.1,"ALTO",IF(H9>0.05,"MEDIO","BAJO"))) -> MEDIO | J9: =IF(I9="CRÍTICO","🚨 SIN RESPUESTA",IF(I9="ALTO","🔴 DIFERENCIA",IF(I9="MEDIO","⚠ REVISAR","✓ CONFIRMADO"))) -> ⚠ REVISAR | K9: =IF(E9="NO","Procedimientos alternativos",IF(H9>0.05,"Investigar diferencia","Ninguna")) -> Investigar diferencia
A10: CL-003 | B10: COMERCIAL GAMMA S.A.S. | C10: 67200000 | D10: SÍ | E10: NO | G10: =IF(E10="SÍ",C10-F10,C10) -> 67200000 | H10: =IF(C10=0,0,ABS(G10/C10)) -> 1 | I10: =IF(E10="NO","CRÍTICO",IF(H10>0.1,"ALTO",IF(H10>0.05,"MEDIO","BAJO"))) -> CRÍTICO | J10: =IF(I10="CRÍTICO","🚨 SIN RESPUESTA",IF(I10="ALTO","🔴 DIFERENCIA",IF(I10="MEDIO","⚠ REVISAR","✓ CONFIRMADO"))) -> 🚨 SIN RESPUESTA | K10: =IF(E10="NO","Procedimientos alternativos",IF(H10>0.05,"Investigar diferencia","Ninguna")) -> Procedimientos alternativos
A11: CL-004 | B11: INDUSTRIAS DELTA S.A. | C11: 19800000 | D11: SÍ | E11: SÍ | F11: 19800000 | G11: =IF(E11="SÍ",C11-F11,C11) -> 0 | H11: =IF(C11=0,0,ABS(G11/C11)) -> 0 | I11: =IF(E11="NO","CRÍTICO",IF(H11>0.1,"ALTO",IF(H11>0.05,"MEDIO","BAJO"))) -> BAJO | J11: =IF(I11="CRÍTICO","🚨 SIN RESPUESTA",IF(I11="ALTO","🔴 DIFERENCIA",IF(I11="MEDIO","⚠ REVISAR","✓ CONFIRMADO"))) -> ✓ CONFIRMADO | K11: =IF(E11="NO","Procedimientos alternativos",IF(H11>0.05,"Investigar diferencia","Ninguna")) -> Ninguna
A12: CL-005 | B12: SERVICIOS EPSILON LTDA | C12: 52300000 | D12: SÍ | E12: SÍ | F12: 48900000 | G12: =IF(E12="SÍ",C12-F12,C12) -> 3400000 | H12: =IF(C12=0,0,ABS(G12/C12)) -> 0.06500956 | I12: =IF(E12="NO","CRÍTICO",IF(H12>0.1,"ALTO",IF(H12>0.05,"MEDIO","BAJO"))) -> MEDIO | J12: =IF(I12="CRÍTICO","🚨 SIN RESPUESTA",IF(I12="ALTO","🔴 DIFERENCIA",IF(I12="MEDIO","⚠ REVISAR","✓ CONFIRMADO"))) -> ⚠ REVISAR | K12: =IF(E12="NO","Procedimientos alternativos",IF(H12>0.05,"Investigar diferencia","Ninguna")) -> Investigar diferencia
A13: CL-006 | B13: SUMINISTROS ZETA S.A. | C13: 38700000 | D13: SÍ | E13: NO | G13: =IF(E13="SÍ",C13-F13,C13) -> 38700000 | H13: =IF(C13=0,0,ABS(G13/C13)) -> 1 | I13: =IF(E13="NO","CRÍTICO",IF(H13>0.1,"ALTO",IF(H13>0.05,"MEDIO","BAJO"))) -> CRÍTICO | J13: =IF(I13="CRÍTICO","🚨 SIN RESPUESTA",IF(I13="ALTO","🔴 DIFERENCIA",IF(I13="MEDIO","⚠ REVISAR","✓ CONFIRMADO"))) -> 🚨 SIN RESPUESTA | K13: =IF(E13="NO","Procedimientos alternativos",IF(H13>0.05,"Investigar diferencia","Ninguna")) -> Procedimientos alternativos
A14: CL-007 | B14: TECNOLOGÍA ETA S.A.S. | C14: 15400000 | D14: SÍ | E14: SÍ | F14: 15400000 | G14: =IF(E14="SÍ",C14-F14,C14) -> 0 | H14: =IF(C14=0,0,ABS(G14/C14)) -> 0 | I14: =IF(E14="NO","CRÍTICO",IF(H14>0.1,"ALTO",IF(H14>0.05,"MEDIO","BAJO"))) -> BAJO | J14: =IF(I14="CRÍTICO","🚨 SIN RESPUESTA",IF(I14="ALTO","🔴 DIFERENCIA",IF(I14="MEDIO","⚠ REVISAR","✓ CONFIRMADO"))) -> ✓ CONFIRMADO | K14: =IF(E14="NO","Procedimientos alternativos",IF(H14>0.05,"Investigar diferencia","Ninguna")) -> Ninguna
A15: CL-008 | B15: LOGÍSTICA THETA LTDA | C15: 89600000 | D15: SÍ | E15: SÍ | F15: 89600000 | G15: =IF(E15="SÍ",C15-F15,C15) -> 0 | H15: =IF(C15=0,0,ABS(G15/C15)) -> 0 | I15: =IF(E15="NO","CRÍTICO",IF(H15>0.1,"ALTO",IF(H15>0.05,"MEDIO","BAJO"))) -> BAJO | J15: =IF(I15="CRÍTICO","🚨 SIN RESPUESTA",IF(I15="ALTO","🔴 DIFERENCIA",IF(I15="MEDIO","⚠ REVISAR","✓ CONFIRMADO"))) -> ✓ CONFIRMADO | K15: =IF(E15="NO","Procedimientos alternativos",IF(H15>0.05,"Investigar diferencia","Ninguna")) -> Ninguna
A16: CL-009 | B16: CONSTRUCCIONES IOTA S.A. | C16: 34900000 | D16: SÍ | E16: NO | G16: =IF(E16="SÍ",C16-F16,C16) -> 34900000 | H16: =IF(C16=0,0,ABS(G16/C16)) -> 1 | I16: =IF(E16="NO","CRÍTICO",IF(H16>0.1,"ALTO",IF(H16>0.05,"MEDIO","BAJO"))) -> CRÍTICO | J16: =IF(I16="CRÍTICO","🚨 SIN RESPUESTA",IF(I16="ALTO","🔴 DIFERENCIA",IF(I16="MEDIO","⚠ REVISAR","✓ CONFIRMADO"))) -> 🚨 SIN RESPUESTA | K16: =IF(E16="NO","Procedimientos alternativos",IF(H16>0.05,"Investigar diferencia","Ninguna")) -> Procedimientos alternativos
A17: CL-010 | B17: ALIMENTOS KAPPA S.A.S. | C17: 21500000 | D17: SÍ | E17: SÍ | F17: 21500000 | G17: =IF(E17="SÍ",C17-F17,C17) -> 0 | H17: =IF(C17=0,0,ABS(G17/C17)) -> 0 | I17: =IF(E17="NO","CRÍTICO",IF(H17>0.1,"ALTO",IF(H17>0.05,"MEDIO","BAJO"))) -> BAJO | J17: =IF(I17="CRÍTICO","🚨 SIN RESPUESTA",IF(I17="ALTO","🔴 DIFERENCIA",IF(I17="MEDIO","⚠ REVISAR","✓ CONFIRMADO"))) -> ✓ CONFIRMADO | K17: =IF(E17="NO","Procedimientos alternativos",IF(H17>0.05,"Investigar diferencia","Ninguna")) -> Ninguna
A19: RESUMEN DE CONFIRMACIONES
A20: Total confirmaciones enviadas: | B20: =COUNTIF(D8:D17,"SÍ") -> 10 | I20: RIESGO GLOBAL: | J20: =IF(B22>3,"CRÍTICO",IF(B23>2,"ALTO",IF(B22>0,"MEDIO","BAJO"))) -> ALTO
A21: Confirmaciones recibidas: | B21: =COUNTIF(E8:E17,"SÍ") -> 7 | D21: Tasa de respuesta: | E21: =B21/B20 -> 0.7
A22: Sin respuesta: | B22: =COUNTIF(E8:E17,"NO") -> 3
A23: Con diferencias: | B23: =COUNTIFS(E8:E17,"SÍ",H8:H17,">0.05") -> 3
A24: Total diferencias detectadas: | B24: =SUMIF(E8:E17,"SÍ",G8:G17) -> 51499900
A25: Hallazgos críticos: | B25: =B22 -> 3 | C25: clientes sin respuesta + | D25: =B23 -> 3 | E25: con diferencias materiales
A26: Monto en riesgo: | B26: =SUMIF(E8:E17,"NO",C8:C17) -> 140800000 | D26: =B26 -> 140800000

Sheet PT_B.2_Antiguedad
A1: PT B.2 - ANÁLISIS DE ANTIGÜEDAD DE CARTERA
A2: NIA 540 - Estimaciones Contables | Objetivo: Evaluar deterioro y provisión de cartera
A4: Fecha de corte: | B4: 31/12/2024
A7: Cliente | B7: Saldo Total | C7: 0-30 días | D7: 31-60 días | E7: 61-90 días | F7: 91-180 días | G7: 181-360 días | H7: >360 días | I7: Días Prom | J7: Riesgo | K7: Provisión Sug.
A8: ACME CORPORATION | B8: =SUM(C8:H8) -> 45800000 | C8: 0 | D8: 12000000 | E8: 8500000 | F8: 5300000 | G8: 15000000 | H8: 5000000 | I8: =(C8*15+D8*45+E8*75+F8*135+G8*270+H8*450)/B8 -> 178.88646 | J8: =IF(I8>360,"CRÍTICO",IF(I8>180,"ALTO",IF(I8>90,"MEDIO","BAJO"))) -> MEDIO | K8: =(E8*0.1)+(F8*0.25)+(G8*0.5)+(H8*1) -> 14675000
A9: DISTRIBUIDORA BETA | B9: =SUM(C9:H9) -> 28500000 | C9: 15800000 | D9: 8700000 | E9: 3000000 | F9: 0 | G9: 0 | H9: 1000000 | I9: =(C9*15+D9*45+E9*75+F9*135+G9*270+H9*450)/B9 -> 45.736842 | J9: =IF(I9>360,"CRÍTICO",IF(I9>180,"ALTO",IF(I9>90,"MEDIO","BAJO"))) -> BAJO | K9: =(E9*0.1)+(F9*0.25)+(G9*0.5)+(H9*1) -> 1300000
A10: COMERCIAL GAMMA | B10: =SUM(C10:H10) -> 67200000 | C10: 0 | D10: 0 | E10: 0 | F10: 8200000 | G10: 25000000 | H10: 34000000 | I10: =(C10*15+D10*45+E10*75+F10*135+G10*270+H10*450)/B10 -> 344.59821 | J10: =IF(I10>360,"CRÍTICO",IF(I10>180,"ALTO",IF(I10>90,"MEDIO","BAJO"))) -> ALTO | K10: =(E10*0.1)+(F10*0.25)+(G10*0.5)+(H10*1) -> 48550000
A11: INDUSTRIAS DELTA | B11: =SUM(C11:H11) -> 19800000 | C11: 19800000 | D11: 0 | E11: 0 | F11: 0 | G11: 0 | H11: 0 | I11: =(C11*15+D11*45+E11*75+F11*135+G11*270+H11*450)/B11 -> 15 | J11: =IF(I11>360,"CRÍTICO",IF(I11>180,"ALTO",IF(I11>90,"MEDIO","BAJO"))) -> BAJO | K11: =(E11*0.1)+(F11*0.25)+(G11*0.5)+(H11*1) -> 0
A12: SERVICIOS EPSILON | B12: =SUM(C12:H12) -> 52300000 | C12: 8900000 | D12: 12400000 | E12: 18700000 | F12: 8300000 | G12: 4000000 | H12: 0 | I12: =(C12*15+D12*45+E12*75+F12*135+G12*270+H12*450)/B12 -> 82.112811 | J12: =IF(I12>360,"CRÍTICO",IF(I12>180,"ALTO",IF(I12>90,"MEDIO","BAJO"))) -> BAJO | K12: =(E12*0.1)+(F12*0.25)+(G12*0.5)+(H12*1) -> 5945000
A13: SUMINISTROS ZETA | B13: =SUM(C13:H13) -> 38700000 | C13: 0 | D13: 0 | E13: 2100000 | F13: 5600000 | G13: 18500000 | H13: 12500000 | I13: =(C13*15+D13*45+E13*75+F13*135+G13*270+H13*450)/B13 -> 298.02326 | J13: =IF(I13>360,"CRÍTICO",IF(I13>180,"ALTO",IF(I13>90,"MEDIO","BAJO"))) -> ALTO | K13: =(E13*0.1)+(F13*0.25)+(G13*0.5)+(H13*1) -> 23360000
A14: TECNOLOGÍA ETA | B14: =SUM(C14:H14) -> 15400000 | C14: 15400000 | D14: 0 | E14: 0 | F14: 0 | G14: 0 | H14: 0 | I14: =(C14*15+D14*45+E14*75+F14*135+G14*270+H14*450)/B14 -> 15 | J14: =IF(I14>360,"CRÍTICO",IF(I14>180,"ALTO",IF(I14>90,"MEDIO","BAJO"))) -> BAJO | K14: =(E14*0.1)+(F14*0.25)+(G14*0.5)+(H14*1) -> 0
A15: LOGÍSTICA THETA | B15: =SUM(C15:H15) -> 89600000 | C15: 45600000 | D15: 28000000 | E15: 16000000 | F15: 0 | G15: 0 | H15: 0 | I15: =(C15*15+D15*45+E15*75+F15*135+G15*270+H15*450)/B15 -> 35.089286 | J15: =IF(I15>360,"CRÍTICO",IF(I15>180,"ALTO",IF(I15>90,"MEDIO","BAJO"))) -> BAJO | K15: =(E15*0.1)+(F15*0.25)+(G15*0.5)+(H15*1) -> 1600000
A17: RESUMEN POR ANTIGÜEDAD
A18: Cartera corriente (0-90 días): | B18: =SUM(C8:E15) -> 214900000 | D18: =B18/SUM(B8:B15) -> 0.60145536 | I18: RIESGO GLOBAL: | J18: =IF(D21>0.2,"CRÍTICO",IF(D20>0.3,"ALTO",IF(D19>0.2,"MEDIO","BAJO"))) -> BAJO
A19: Cartera vencida (91-180 días): | B19: =SUM(F8:F15) -> 27400000 | D19: =B19/SUM(B8:B15) -> 0.076686258
A20: Cartera de difícil cobro (181-360): | B20: =SUM(G8:G15) -> 62500000 | D20: =B20/SUM(B8:B15) -> 0.17492303
A21: Cartera incobrable (>360 días): | B21: =SUM(H8:H15) -> 52500000 | D21: =B21/SUM(B8:B15) -> 0.14693535
A22: Total cartera: | B22: =SUM(B8:B15) -> 357300000
A23: Provisión sugerida total: | B23: =SUM(K8:K15) -> 95430000 | D23: =B23/B22 -> 0.26708648
A24: Clientes en riesgo crítico: | B24: =COUNTIF(J8:J15,"CRÍTICO") -> 0 | D24: Provisión sugerida: | E24: =B23 -> 95430000
A25: Días promedio de cartera: | B25: =SUMPRODUCT(B8:B15,I8:I15)/SUM(B8:B15) -> 145.96558 | D25: =B23 -> 95430000

Sheet PT_B.3_NC_PostCierre
A1: PT B.3 - NOTAS CRÉDITO EMITIDAS POST-CIERRE
A2: NIA 240 - Manipulación de Ventas | Objetivo: Detectar ventas ficticias o devoluciones ocultas
A4: Fecha de cierre: | B4: 31/12/2024
A7: N° NC | B7: Fecha NC | C7: Factura Original | D7: Fecha Factura | E7: Cliente | F7: Monto | G7: Días Post- Cierre | H7: Riesgo | I7: Estado | J7: Acción Requerida
A8: NC-00125 | B8: 03/01/2025 | C8: FV-8765 | D8: 28/12/2024 | E8: COMERCIAL GAMMA S.A. | F8: 8500000 | G8: =B8-$B$4 -> 3 | H8: =IF(AND(G8<=7,$B$4-D8<=3),"MUY ALTO",IF(G8<=5,"ALTO",IF(G8<=10,"MEDIO","BAJO"))) -> MUY ALTO | I8: =IF(H8="MUY ALTO","🚨 SOSPECHOSA",IF(H8="ALTO","🔴 REVISAR",IF(H8="MEDIO","⚠ VERIFICAR","✓ Normal"))) -> 🚨 SOSPECHOSA | J8: =IF(H8="MUY ALTO","Investigar venta original",IF(H8="ALTO","Verificar autorización","Revisar documentación")) -> Investigar venta original
A9: NC-00126 | B9: 05/01/2025 | C9: FV-8723 | D9: 30/12/2024 | E9: DISTRIBUIDORA BETA | F9: 4200000 | G9: =B9-$B$4 -> 5 | H9: =IF(AND(G9<=7,$B$4-D9<=3),"MUY ALTO",IF(G9<=5,"ALTO",IF(G9<=10,"MEDIO","BAJO"))) -> MUY ALTO | I9: =IF(H9="MUY ALTO","🚨 SOSPECHOSA",IF(H9="ALTO","🔴 REVISAR",IF(H9="MEDIO","⚠ VERIFICAR","✓ Normal"))) -> 🚨 SOSPECHOSA | J9: =IF(H9="MUY ALTO","Investigar venta original",IF(H9="ALTO","Verificar autorización","Revisar documentación")) -> Investigar venta original
A10: NC-00127 | B10: 02/01/2025 | C10: FV-8798 | D10: 31/12/2024 | E10: SERVICIOS EPSILON | F10: 12000000 | G10: =B10-$B$4 -> 2 | H10: =IF(AND(G10<=7,$B$4-D10<=3),"MUY ALTO",IF(G10<=5,"ALTO",IF(G10<=10,"MEDIO","BAJO"))) -> MUY ALTO | I10: =IF(H10="MUY ALTO","🚨 SOSPECHOSA",IF(H10="ALTO","🔴 REVISAR",IF(H10="MEDIO","⚠ VERIFICAR","✓ Normal"))) -> 🚨 SOSPECHOSA | J10: =IF(H10="MUY ALTO","Investigar venta original",IF(H10="ALTO","Verificar autorización","Revisar documentación")) -> Investigar venta original
A11: NC-00128 | B11: 08/01/2025 | C11: FV-8654 | D11: 29/12/2024 | E11: INDUSTRIAS DELTA | F11: 2800000 | G11: =B11-$B$4 -> 8 | H11: =IF(AND(G11<=7,$B$4-D11<=3),"MUY ALTO",IF(G11<=5,"ALTO",IF(G11<=10,"MEDIO","BAJO"))) -> MEDIO | I11: =IF(H11="MUY ALTO","🚨 SOSPECHOSA",IF(H11="ALTO","🔴 REVISAR",IF(H11="MEDIO","⚠ VERIFICAR","✓ Normal"))) -> ⚠ VERIFICAR | J11: =IF(H11="MUY ALTO","Investigar venta original",IF(H11="ALTO","Verificar autorización","Revisar documentación")) -> Revisar documentación
A12: NC-00129 | B12: 04/01/2025 | C12: FV-8812 | D12: 31/12/2024 | E12: ACME CORPORATION | F12: 18500000 | G12: =B12-$B$4 -> 4 | H12: =IF(AND(G12<=7,$B$4-D12<=3),"MUY ALTO",IF(G12<=5,"ALTO",IF(G12<=10,"MEDIO","BAJO"))) -> MUY ALTO | I12: =IF(H12="MUY ALTO","🚨 SOSPECHOSA",IF(H12="ALTO","🔴 REVISAR",IF(H12="MEDIO","⚠ VERIFICAR","✓ Normal"))) -> 🚨 SOSPECHOSA | J12: =IF(H12="MUY ALTO","Investigar venta original",IF(H12="ALTO","Verificar autorización","Revisar documentación")) -> Investigar venta original
A13: NC-00130 | B13: 10/01/2025 | C13: FV-8701 | D13: 27/12/2024 | E13: TECNOLOGÍA ETA | F13: 5300000 | G13: =B13-$B$4 -> 10 | H13: =IF(AND(G13<=7,$B$4-D13<=3),"MUY ALTO",IF(G13<=5,"ALTO",IF(G13<=10,"MEDIO","BAJO"))) -> MEDIO | I13: =IF(H13="MUY ALTO","🚨 SOSPECHOSA",IF(H13="ALTO","🔴 REVISAR",IF(H13="MEDIO","⚠ VERIFICAR","✓ Normal"))) -> ⚠ VERIFICAR | J13: =IF(H13="MUY ALTO","Investigar venta original",IF(H13="ALTO","Verificar autorización","Revisar documentación")) -> Revisar documentación
A15: ANÁLISIS DE RIESGO
A16: NCs emitidas primeros 5 días: | B16: =COUNTIF(G8:G13,"<=5") -> 4 | H16: RIESGO GLOBAL: | I16: =IF(B16>3,"CRÍTICO",IF(B17>0,"ALTO",IF(B16>1,"MEDIO","BAJO"))) -> CRÍTICO
A17: NCs con riesgo MUY ALTO: | B17: =COUNTIF(H8:H13,"MUY ALTO") -> 4
A18: Monto total NCs post-cierre: | B18: =SUM(F8:F13) -> 51300000
A19: Monto en riesgo MUY ALTO: | B19: =SUMIF(H8:H13,"MUY ALTO",F8:F13) -> 43200000
A22: Casos sospechosos: | B22: =COUNTIF(H8:H13,"MUY ALTO")+COUNTIF(H8:H13,"ALTO") -> 4 | C22: notas crédito requieren investigación
D23: =B19 -> 43200000

Sheet PT_B.4_Autorizaciones
A1: PT B.4 - VERIFICACIÓN DE AUTORIZACIONES DE CANCELACIONES/CASTIGOS
A2: NIA 240 - Control de Castigos | Objetivo: Detectar cancelaciones no autorizadas
A4: Período revisado: | B4: 01/01/2024 - 31/12/2024
A7: N° Castigo | B7: Fecha | C7: Cliente | D7: Monto | E7: Autorizado Por | F7: Nivel Requerido | G7: Cumple | H7: Riesgo | I7: Estado | J7: Acción Requerida
A8: CAST-001 | B8: 15/03/2024 | C8: CLIENTE MOROSO A | D8: 8500000 | E8: Gerente Cartera | F8: Gerente Cartera | G8: =IF(E8=F8,"SÍ","NO") -> SÍ | H8: =IF(G8="NO","CRÍTICO","BAJO") -> BAJO | I8: =IF(H8="CRÍTICO","⛔ NO AUTORIZADO","✓ CORRECTO") -> ✓ CORRECTO | J8: =IF(G8="NO","INVESTIGAR URGENTE","Ninguna") -> Ninguna
A9: CAST-002 | B9: 22/06/2024 | C9: DEUDOR INACTIVO B | D9: 15000000 | E9: Contador | F9: Gerente General | G9: =IF(E9=F9,"SÍ","NO") -> NO | H9: =IF(G9="NO","CRÍTICO","BAJO") -> CRÍTICO | I9: =IF(H9="CRÍTICO","⛔ NO AUTORIZADO","✓ CORRECTO") -> ⛔ NO AUTORIZADO | J9: =IF(G9="NO","INVESTIGAR URGENTE","Ninguna") -> INVESTIGAR URGENTE
A10: CAST-003 | B10: 10/08/2024 | C10: EMPRESA EN LIQUIDACIÓN C | D10: 3200000 | E10: Gerente Cartera | F10: Gerente Cartera | G10: =IF(E10=F10,"SÍ","NO") -> SÍ | H10: =IF(G10="NO","CRÍTICO","BAJO") -> BAJO | I10: =IF(H10="CRÍTICO","⛔ NO AUTORIZADO","✓ CORRECTO") -> ✓ CORRECTO | J10: =IF(G10="NO","INVESTIGAR URGENTE","Ninguna") -> Ninguna
A11: CAST-004 | B11: 05/10/2024 | C11: CLIENTE FALLIDO D | D11: 28000000 | E11: Gerente Cartera | F11: Junta Directiva | G11: =IF(E11=F11,"SÍ","NO") -> NO | H11: =IF(G11="NO","CRÍTICO","BAJO") -> CRÍTICO | I11: =IF(H11="CRÍTICO","⛔ NO AUTORIZADO","✓ CORRECTO") -> ⛔ NO AUTORIZADO | J11: =IF(G11="NO","INVESTIGAR URGENTE","Ninguna") -> INVESTIGAR URGENTE
A12: CAST-005 | B12: 18/11/2024 | C12: DEUDOR PRESCRITO E | D12: 5800000 | E12: Gerente General | F12: Gerente General | G12: =IF(E12=F12,"SÍ","NO") -> SÍ | H12: =IF(G12="NO","CRÍTICO","BAJO") -> BAJO | I12: =IF(H12="CRÍTICO","⛔ NO AUTORIZADO","✓ CORRECTO") -> ✓ CORRECTO | J12: =IF(G12="NO","INVESTIGAR URGENTE","Ninguna") -> Ninguna
A13: CAST-006 | B13: 28/12/2024 | C13: CLIENTE DESCONOCIDO F | D13: 12500000 | E13: Contador | F13: Gerente General | G13: =IF(E13=F13,"SÍ","NO") -> NO | H13: =IF(G13="NO","CRÍTICO","BAJO") -> CRÍTICO | I13: =IF(H13="CRÍTICO","⛔ NO AUTORIZADO","✓ CORRECTO") -> ⛔ NO AUTORIZADO | J13: =IF(G13="NO","INVESTIGAR URGENTE","Ninguna") -> INVESTIGAR URGENTE
A15: RESUMEN DE AUTORIZACIONES
A16: Total castigos revisados: | B16: =COUNTA(A8:A13) -> 6 | H16: RIESGO GLOBAL: | I16: =IF(B17>0,"CRÍTICO","BAJO") -> CRÍTICO
A17: Castigos NO autorizados correctamente: | B17: =COUNTIF(G8:G13,"NO") -> 3
A18: Monto total sin autorización: | B18: =SUMIF(G8:G13,"NO",D8:D13) -> 55500000
A21: Hallazgos críticos: | B21: =B17 -> 3 | C21: castigos sin autorización adecuada
D22: =B18 -> 55500000

Sheet PT_B.5_CutOff
A1: PT B.5 - ANÁLISIS DE CUT-OFF DE VENTAS Y DEVOLUCIONES
A2: NIA 330 - Corte de Operaciones | Objetivo: Verificar el reconocimiento correcto de ingresos por período
A4: Fecha de corte: | B4: 31/12/2024
A7: N° Factura | B7: Fecha Factura | C7: Fecha Despacho | D7: Cliente | E7: Monto | F7: Período Correcto | G7: Registro Contable | H7: Diferencia Días | I7: Riesgo | J7: Estado | K7: Acción
A8: FV-8945 | B8: 31/12/2024 | C8: 02/01/2025 | D8: CLIENTE A | E8: 5 | F8: 2025 | G8: 2024 | H8: 100 | I8: =IF(F8<>G8,"ALTO","BAJO") -> ALTO | J8: =IF(I8="ALTO","🔴 ERROR CUTOFF","✓ CORRECTO") -> 🔴 ERROR CUTOFF | K8: =IF(F8<>G8,"Ajustar período","Ninguna") -> Ajustar período
A9: FV-8932 | B9: 30/12/2024 | C9: 30/12/2024 | D9: CLIENTE B | E9: 8500000 | F9: 2024 | G9: 2024 | H9: =C9-B9 -> 0 | I9: =IF(F9<>G9,"ALTO","BAJO") -> BAJO | J9: =IF(I9="ALTO","🔴 ERROR CUTOFF","✓ CORRECTO") -> ✓ CORRECTO | K9: =IF(F9<>G9,"Ajustar período","Ninguna") -> Ninguna
A10: FV-8967 | B10: 31/12/2024 | C10: 04/01/2025 | D10: CLIENTE C | E10: 22000000 | F10: 2025 | G10: 2024 | H10: =C10-B10 -> 4 | I10: =IF(F10<>G10,"ALTO","BAJO") -> ALTO | J10: =IF(I10="ALTO","🔴 ERROR CUTOFF","✓ CORRECTO") -> 🔴 ERROR CUTOFF | K10: =IF(F10<>G10,"Ajustar período","Ninguna") -> Ajustar período
A11: FV-8912 | B11: 29/12/2024 | C11: 29/12/2024 | D11: CLIENTE D | E11: 5300000 | F11: 2024 | G11: 2024 | H11: =C11-B11 -> 0 | I11: =IF(F11<>G11,"ALTO","BAJO") -> BAJO | J11: =IF(I11="ALTO","🔴 ERROR CUTOFF","✓ CORRECTO") -> ✓ CORRECTO | K11: =IF(F11<>G11,"Ajustar período","Ninguna") -> Ninguna
A12: FV-8978 | B12: 31/12/2024 | C12: 31/12/2024 | D12: CLIENTE E | E12: 12800000 | F12: 2024 | G12: 2024 | H12: =C12-B12 -> 0 | I12: =IF(F12<>G12,"ALTO","BAJO") -> BAJO | J12: =IF(I12="ALTO","🔴 ERROR CUTOFF","✓ CORRECTO") -> ✓ CORRECTO | K12: =IF(F12<>G12,"Ajustar período","Ninguna") -> Ninguna
A13: FV-8889 | B13: 28/12/2024 | C13: 03/01/2025 | D13: CLIENTE F | E13: 9700000 | F13: 2025 | G13: 2024 | H13: =C13-B13 -> 6 | I13: =IF(F13<>G13,"ALTO","BAJO") -> ALTO | J13: =IF(I13="ALTO","🔴 ERROR CUTOFF","✓ CORRECTO") -> 🔴 ERROR CUTOFF | K13: =IF(F13<>G13,"Ajustar período","Ninguna") -> Ajustar período
A14: FV-8990 | B14: 31/12/2024 | C14: 05/01/2025 | D14: CLIENTE G | E14: 18500000 | F14: 2025 | G14: 2024 | H14: =C14-B14 -> 5 | I14: =IF(F14<>G14,"ALTO","BAJO") -> ALTO | J14: =IF(I14="ALTO","🔴 ERROR CUTOFF","✓ CORRECTO") -> 🔴 ERROR CUTOFF | K14: =IF(F14<>G14,"Ajustar período","Ninguna") -> Ajustar período
A16: EVALUACIÓN DE CUT-OFF
A17: Transacciones revisadas: | B17: =COUNTA(A8:A14) -> 7
A18: Errores de cut-off detectados: | B18: =COUNTIF(I8:I14,"ALTO") -> 4 | I18: RIESGO GLOBAL: | J18: =IF(B18>2,"ALTO",IF(B18>0,"MEDIO","BAJO")) -> ALTO
A19: Monto registrado incorrectamente: | B19: =SUMIF(I8:I14,"ALTO",E8:E14) -> 50200005
A20: Impacto en utilidad 2024: | B20: =-B19 -> -50200005
A23: Ajustes requeridos: | B23: =B18 -> 4 | C23: facturas en período incorrecto
D24: =B19 -> 50200005

Sheet PT_B.6_PartesRel
A1: PT B.6 - TRANSACCIONES CON PARTES RELACIONADAS NO REVELADAS
A2: NIA 550 - Partes Relacionadas | Objetivo: Identificar transacciones no reveladas adecuadamente
A4: Fecha de análisis: | B4: 31/12/2024
A7: Cliente/Deudor | B7: Saldo | C7: Relación Identificada | D7: Revelado en Notas EEFF | E7: Términos Comerciales | F7: Términos Normales | G7: Cumple | H7: Riesgo | I7: Estado | J7: Acción
A8: EMPRESA FAMILIAR S.A. | B8: 25000000 | C8: Accionista mayoritario | D8: NO | E8: Sin intereses | F8: Con intereses | G8: =IF(C8="Ninguna","N/A",IF(AND(D8="NO",C8<>"Ninguna"),"NO","SÍ")) -> NO | H8: =IF(G8="NO","ALTO","BAJO") -> ALTO | I8: =IF(H8="ALTO","🔴 NO REVELADO","✓ OK") -> 🔴 NO REVELADO | J8: =IF(G8="NO","Revelar en notas EEFF","Ninguna") -> Revelar en notas EEFF
A9: HERMANO DEL GERENTE LTDA | B9: 15000000 | C9: Familiar directivo | D9: NO | E9: 120 días plazo | F9: 60 días plazo | G9: =IF(C9="Ninguna","N/A",IF(AND(D9="NO",C9<>"Ninguna"),"NO","SÍ")) -> NO | H9: =IF(G9="NO","ALTO","BAJO") -> ALTO | I9: =IF(H9="ALTO","🔴 NO REVELADO","✓ OK") -> 🔴 NO REVELADO | J9: =IF(G9="NO","Revelar en notas EEFF","Ninguna") -> Revelar en notas EEFF
A10: PROVEEDOR NORMAL A | B10: 8500000 | C10: Ninguna | D10: N/A | E10: 60 días | F10: 60 días | G10: =IF(C10="Ninguna","N/A",IF(AND(D10="NO",C10<>"Ninguna"),"NO","SÍ")) -> N/A | H10: =IF(G10="NO","ALTO","BAJO") -> BAJO | I10: =IF(H10="ALTO","🔴 NO REVELADO","✓ OK") -> ✓ OK | J10: =IF(G10="NO","Revelar en notas EEFF","Ninguna") -> Ninguna
A11: SUBSIDIARIA NO REVELADA | B11: 42000000 | C11: Subsidiaria oculta | D11: NO | E11: Sin garantías | F11: Con garantías | G11: =IF(C11="Ninguna","N/A",IF(AND(D11="NO",C11<>"Ninguna"),"NO","SÍ")) -> NO | H11: =IF(G11="NO","ALTO","BAJO") -> ALTO | I11: =IF(H11="ALTO","🔴 NO REVELADO","✓ OK") -> 🔴 NO REVELADO | J11: =IF(G11="NO","Revelar en notas EEFF","Ninguna") -> Revelar en notas EEFF
A12: CLIENTE REGULAR B | B12: 12000000 | C12: Ninguna | D12: N/A | E12: 45 días | F12: 45 días | G12: =IF(C12="Ninguna","N/A",IF(AND(D12="NO",C12<>"Ninguna"),"NO","SÍ")) -> N/A | H12: =IF(G12="NO","ALTO","BAJO") -> BAJO | I12: =IF(H12="ALTO","🔴 NO REVELADO","✓ OK") -> ✓ OK | J12: =IF(G12="NO","Revelar en notas EEFF","Ninguna") -> Ninguna
A14: EVALUACIÓN DE REVELACIÓN
A15: Partes relacionadas identificadas: | B15: =COUNTIF(C8:C12,"<>Ninguna") -> 3
A16: Partes relacionadas NO reveladas: | B16: =COUNTIF(G8:G12,"NO") -> 3 | H16: RIESGO GLOBAL: | I16: =IF(B16>0,"ALTO","BAJO") -> ALTO
A17: Monto total no revelado: | B17: =SUMIF(G8:G12,"NO",B8:B12) -> 82000000
A21: Hallazgos: | B21: =B16 -> 3 | C21: transacciones con partes relacionadas sin revelar
D22: =B17 -> 82000000

Sheet PT_B.7_Concentracion
A1: PT B.7 - ANÁLISIS DE CONCENTRACIÓN DE VENTAS POR CLIENTE
A2: Evaluación de Riesgo de Negocio | Objetivo: Identificar dependencia excesiva de pocos clientes
A4: Total ventas del período: | B4: 850000000
A7: Cliente | B7: Ventas Año | C7: % Ventas Totales | D7: Saldo CxC | E7: % CxC Total | F7: Días Prom | G7: Riesgo Concentración | H7: Riesgo Crédito | I7: Riesgo Global | J7: Estado | K7: Acción
A8: MEGACLIENTE PRINCIPAL | B8: 255000000 | C8: =B8/$B$4 -> 0.3 | D8: 65000000 | E8: =D8/SUM($D$8:$D$15) -> 0.33713693 | F8: 85 | G8: =IF(C8>0.3,"MUY ALTO",IF(C8>0.15,"ALTO",IF(C8>0.1,"MEDIO","BAJO"))) -> ALTO | H8: =IF(F8>90,"ALTO",IF(F8>60,"MEDIO","BAJO")) -> MEDIO | I8: =IF(OR(G8="MUY ALTO",AND(G8="ALTO",H8="ALTO")),"MUY ALTO",IF(G8="ALTO","ALTO",IF(OR(G8="MEDIO",H8="MEDIO"),"MEDIO","BAJO"))) -> ALTO | J8: =IF(I8="MUY ALTO","🚨 CRÍTICO",IF(I8="ALTO","🔴 ALTO",IF(I8="MEDIO","⚠ MEDIO","✓ OK"))) -> 🔴 ALTO | K8: =IF(I8="MUY ALTO","Diversificar urgente",IF(I8="ALTO","Plan diversificación",IF(I8="MEDIO","Monitoreo estrecho","Seguimiento normal"))) -> Plan diversificación
A9: SEGUNDO CLIENTE IMPORTANTE | B9: 127500000 | C9: =B9/$B$4 -> 0.15 | D9: 32000000 | E9: =D9/SUM($D$8:$D$15) -> 0.1659751 | F9: 72 | G9: =IF(C9>0.3,"MUY ALTO",IF(C9>0.15,"ALTO",IF(C9>0.1,"MEDIO","BAJO"))) -> MEDIO | H9: =IF(F9>90,"ALTO",IF(F9>60,"MEDIO","BAJO")) -> MEDIO | I9: =IF(OR(G9="MUY ALTO",AND(G9="ALTO",H9="ALTO")),"MUY ALTO",IF(G9="ALTO","ALTO",IF(OR(G9="MEDIO",H9="MEDIO"),"MEDIO","BAJO"))) -> MEDIO | J9: =IF(I9="MUY ALTO","🚨 CRÍTICO",IF(I9="ALTO","🔴 ALTO",IF(I9="MEDIO","⚠ MEDIO","✓ OK"))) -> ⚠ MEDIO | K9: =IF(I9="MUY ALTO","Diversificar urgente",IF(I9="ALTO","Plan diversificación",IF(I9="MEDIO","Monitoreo estrecho","Seguimiento normal"))) -> Monitoreo estrecho
A10: TERCER CLIENTE | B10: 68000000 | C10: =B10/$B$4 -> 0.08 | D10: 18000000 | E10: =D10/SUM($D$8:$D$15) -> 0.093360996 | F10: 58 | G10: =IF(C10>0.3,"MUY ALTO",IF(C10>0.15,"ALTO",IF(C10>0.1,"MEDIO","BAJO"))) -> BAJO | H10: =IF(F10>90,"ALTO",IF(F10>60,"MEDIO","BAJO")) -> BAJO | I10: =IF(OR(G10="MUY ALTO",AND(G10="ALTO",H10="ALTO")),"MUY ALTO",IF(G10="ALTO","ALTO",IF(OR(G10="MEDIO",H10="MEDIO"),"MEDIO","BAJO"))) -> BAJO | J10: =IF(I10="MUY ALTO","🚨 CRÍTICO",IF(I10="ALTO","🔴 ALTO",IF(I10="MEDIO","⚠ MEDIO","✓ OK"))) -> ✓ OK | K10: =IF(I10="MUY ALTO","Diversificar urgente",IF(I10="ALTO","Plan diversificación",IF(I10="MEDIO","Monitoreo estrecho","Seguimiento normal"))) -> Seguimiento normal
A11: CLIENTE MEDIANO A | B11: 42500000 | C11: =B11/$B$4 -> 0.05 | D11: 12000000 | E11: =D11/SUM($D$8:$D$15) -> 0.062240664 | F11: 45 | G11: =IF(C11>0.3,"MUY ALTO",IF(C11>0.15,"ALTO",IF(C11>0.1,"MEDIO","BAJO"))) -> BAJO | H11: =IF(F11>90,"ALTO",IF(F11>60,"MEDIO","BAJO")) -> BAJO | I11: =IF(OR(G11="MUY ALTO",AND(G11="ALTO",H11="ALTO")),"MUY ALTO",IF(G11="ALTO","ALTO",IF(OR(G11="MEDIO",H11="MEDIO"),"MEDIO","BAJO"))) -> BAJO | J11: =IF(I11="MUY ALTO","🚨 CRÍTICO",IF(I11="ALTO","🔴 ALTO",IF(I11="MEDIO","⚠ MEDIO","✓ OK"))) -> ✓ OK | K11: =IF(I11="MUY ALTO","Diversificar urgente",IF(I11="ALTO","Plan diversificación",IF(I11="MEDIO","Monitoreo estrecho","Seguimiento normal"))) -> Seguimiento normal
A12: CLIENTE MEDIANO B | B12: 34000000 | C12: =B12/$B$4 -> 0.04 | D12: 9500000 | E12: =D12/SUM($D$8:$D$15) -> 0.049273859 | F12: 62 | G12: =IF(C12>0.3,"MUY ALTO",IF(C12>0.15,"ALTO",IF(C12>0.1,"MEDIO","BAJO"))) -> BAJO | H12: =IF(F12>90,"ALTO",IF(F12>60,"MEDIO","BAJO")) -> MEDIO | I12: =IF(OR(G12="MUY ALTO",AND(G12="ALTO",H12="ALTO")),"MUY ALTO",IF(G12="ALTO","ALTO",IF(OR(G12="MEDIO",H12="MEDIO"),"MEDIO","BAJO"))) -> MEDIO | J12: =IF(I12="MUY ALTO","🚨 CRÍTICO",IF(I12="ALTO","🔴 ALTO",IF(I12="MEDIO","⚠ MEDIO","✓ OK"))) -> ⚠ MEDIO | K12: =IF(I12="MUY ALTO","Diversificar urgente",IF(I12="ALTO","Plan diversificación",IF(I12="MEDIO","Monitoreo estrecho","Seguimiento normal"))) -> Monitoreo estrecho
A13: CLIENTE PEQUEÑO A | B13: 25500000 | C13: =B13/$B$4 -> 0.03 | D13: 6800000 | E13: =D13/SUM($D$8:$D$15) -> 0.03526971 | F13: 38 | G13: =IF(C13>0.3,"MUY ALTO",IF(C13>0.15,"ALTO",IF(C13>0.1,"MEDIO","BAJO"))) -> BAJO | H13: =IF(F13>90,"ALTO",IF(F13>60,"MEDIO","BAJO")) -> BAJO | I13: =IF(OR(G13="MUY ALTO",AND(G13="ALTO",H13="ALTO")),"MUY ALTO",IF(G13="ALTO","ALTO",IF(OR(G13="MEDIO",H13="MEDIO"),"MEDIO","BAJO"))) -> BAJO | J13: =IF(I13="MUY ALTO","🚨 CRÍTICO",IF(I13="ALTO","🔴 ALTO",IF(I13="MEDIO","⚠ MEDIO","✓ OK"))) -> ✓ OK | K13: =IF(I13="MUY ALTO","Diversificar urgente",IF(I13="ALTO","Plan diversificación",IF(I13="MEDIO","Monitoreo estrecho","Seguimiento normal"))) -> Seguimiento normal
A14: CLIENTE PEQUEÑO B | B14: 17000000 | C14: =B14/$B$4 -> 0.02 | D14: 4200000 | E14: =D14/SUM($D$8:$D$15) -> 0.021784232 | F14: 42 | G14: =IF(C14>0.3,"MUY ALTO",IF(C14>0.15,"ALTO",IF(C14>0.1,"MEDIO","BAJO"))) -> BAJO | H14: =IF(F14>90,"ALTO",IF(F14>60,"MEDIO","BAJO")) -> BAJO | I14: =IF(OR(G14="MUY ALTO",AND(G14="ALTO",H14="ALTO")),"MUY ALTO",IF(G14="ALTO","ALTO",IF(OR(G14="MEDIO",H14="MEDIO"),"MEDIO","BAJO"))) -> BAJO | J14: =IF(I14="MUY ALTO","🚨 CRÍTICO",IF(I14="ALTO","🔴 ALTO",IF(I14="MEDIO","⚠ MEDIO","✓ OK"))) -> ✓ OK | K14: =IF(I14="MUY ALTO","Diversificar urgente",IF(I14="ALTO","Plan diversificación",IF(I14="MEDIO","Monitoreo estrecho","Seguimiento normal"))) -> Seguimiento normal
A15: OTROS CLIENTES (150) | B15: 280500000 | C15: =B15/$B$4 -> 0.33 | D15: 45300000 | E15: =D15/SUM($D$8:$D$15) -> 0.23495851 | F15: 55 | G15: =IF(C15>0.3,"MUY ALTO",IF(C15>0.15,"ALTO",IF(C15>0.1,"MEDIO","BAJO"))) -> MUY ALTO | H15: =IF(F15>90,"ALTO",IF(F15>60,"MEDIO","BAJO")) -> BAJO | I15: =IF(OR(G15="MUY ALTO",AND(G15="ALTO",H15="ALTO")),"MUY ALTO",IF(G15="ALTO","ALTO",IF(OR(G15="MEDIO",H15="MEDIO"),"MEDIO","BAJO"))) -> MUY ALTO | J15: =IF(I15="MUY ALTO","🚨 CRÍTICO",IF(I15="ALTO","🔴 ALTO",IF(I15="MEDIO","⚠ MEDIO","✓ OK"))) -> 🚨 CRÍTICO | K15: =IF(I15="MUY ALTO","Diversificar urgente",IF(I15="ALTO","Plan diversificación",IF(I15="MEDIO","Monitoreo estrecho","Seguimiento normal"))) -> Diversificar urgente
A17: ANÁLISIS DE CONCENTRACIÓN
A18: Top 3 clientes representan: | B18: =SUM(C8:C10) -> 0.53 | I18: RIESGO GLOBAL: | J18: =IF(B18>0.6,"CRÍTICO",IF(B18>0.4,"ALTO",IF(B18>0.3,"MEDIO","BAJO"))) -> ALTO
A19: Clientes con riesgo MUY ALTO: | B19: =COUNTIF(I8:I15,"MUY ALTO") -> 1
A20: Ventas concentradas (riesgo alto): | B20: =SUMIF(I8:I15,"MUY ALTO",B8:B15) -> 280500000
A21: CxC en riesgo de concentración: | B21: =SUMIF(G8:G15,"MUY ALTO",D8:D15)+SUMIF(G8:G15,"ALTO",D8:D15) -> 110300000
A23: Nivel de dependencia: | B23: =IF(B18>0.5,"Dependencia crítica","Concentración moderada") -> Dependencia crítica
D24: =B20 -> 280500000

Sheet PT_B.8_Colateral
A1: PT B.8 - VERIFICACIÓN DE COLATERAL Y GARANTÍAS
A2: Evaluación de Respaldos | Objetivo: Verificar existencia y suficiencia de garantías
A4: Fecha de verificación: | B4: 31/12/2024
A7: Cliente | B7: Saldo CxC | C7: Tipo Garantía | D7: Valor Garantía | E7: % Cobertura | F7: Vigencia | G7: Vigente | H7: Riesgo | I7: Estado | J7: Acción
A8: MEGACLIENTE PRINCIPAL | B8: 65000000 | C8: Pagaré | D8: 70000000 | E8: =IF(D8=0,0,D8/B8) -> 1.0769231 | F8: 30/06/2025 | G8: =IF(F8="N/A","N/A",IF(F8>$B$4,"SÍ","NO")) -> NO | H8: =IF(C8="Ninguna","MUY ALTO",IF(G8="NO","ALTO",IF(E8<0.8,"MEDIO","BAJO"))) -> ALTO | I8: =IF(H8="MUY ALTO","🚨 SIN GARANTÍA",IF(H8="ALTO","🔴 VENCIDA",IF(H8="MEDIO","⚠ INSUFICIENTE","✓ OK"))) -> 🔴 VENCIDA | J8: =IF(C8="Ninguna","Exigir garantía",IF(G8="NO","Renovar urgente",IF(E8<0.8,"Ampliar cobertura","Ninguna"))) -> Renovar urgente
A9: SEGUNDO CLIENTE | B9: 32000000 | C9: Ninguna | D9: 0 | E9: =IF(D9=0,0,D9/B9) -> 0 | F9: N/A | G9: =IF(F9="N/A","N/A",IF(F9>$B$4,"SÍ","NO")) -> N/A | H9: =IF(C9="Ninguna","MUY ALTO",IF(G9="NO","ALTO",IF(E9<0.8,"MEDIO","BAJO"))) -> MUY ALTO | I9: =IF(H9="MUY ALTO","🚨 SIN GARANTÍA",IF(H9="ALTO","🔴 VENCIDA",IF(H9="MEDIO","⚠ INSUFICIENTE","✓ OK"))) -> 🚨 SIN GARANTÍA | J9: =IF(C9="Ninguna","Exigir garantía",IF(G9="NO","Renovar urgente",IF(E9<0.8,"Ampliar cobertura","Ninguna"))) -> Exigir garantía
A10: TERCER CLIENTE | B10: 18000000 | C10: Hipoteca | D10: 25000000 | E10: =IF(D10=0,0,D10/B10) -> 1.3888889 | F10: 15/12/2025 | G10: =IF(F10="N/A","N/A",IF(F10>$B$4,"SÍ","NO")) -> NO | H10: =IF(C10="Ninguna","MUY ALTO",IF(G10="NO","ALTO",IF(E10<0.8,"MEDIO","BAJO"))) -> ALTO | I10: =IF(H10="MUY ALTO","🚨 SIN GARANTÍA",IF(H10="ALTO","🔴 VENCIDA",IF(H10="MEDIO","⚠ INSUFICIENTE","✓ OK"))) -> 🔴 VENCIDA | J10: =IF(C10="Ninguna","Exigir garantía",IF(G10="NO","Renovar urgente",IF(E10<0.8,"Ampliar cobertura","Ninguna"))) -> Renovar urgente
A11: CLIENTE MEDIANO A | B11: 12000000 | C11: Carta crédito | D11: 8000000 | E11: =IF(D11=0,0,D11/B11) -> 0.66666667 | F11: 05/01/2024 | G11: =IF(F11="N/A","N/A",IF(F11>$B$4,"SÍ","NO")) -> NO | H11: =IF(C11="Ninguna","MUY ALTO",IF(G11="NO","ALTO",IF(E11<0.8,"MEDIO","BAJO"))) -> ALTO | I11: =IF(H11="MUY ALTO","🚨 SIN GARANTÍA",IF(H11="ALTO","🔴 VENCIDA",IF(H11="MEDIO","⚠ INSUFICIENTE","✓ OK"))) -> 🔴 VENCIDA | J11: =IF(C11="Ninguna","Exigir garantía",IF(G11="NO","Renovar urgente",IF(E11<0.8,"Ampliar cobertura","Ninguna"))) -> Renovar urgente
A12: CLIENTE MEDIANO B | B12: 9500000 | C12: Fianza | D12: 10000000 | E12: =IF(D12=0,0,D12/B12) -> 1.0526316 | F12: 20/08/2025 | G12: =IF(F12="N/A","N/A",IF(F12>$B$4,"SÍ","NO")) -> NO | H12: =IF(C12="Ninguna","MUY ALTO",IF(G12="NO","ALTO",IF(E12<0.8,"MEDIO","BAJO"))) -> ALTO | I12: =IF(H12="MUY ALTO","🚨 SIN GARANTÍA",IF(H12="ALTO","🔴 VENCIDA",IF(H12="MEDIO","⚠ INSUFICIENTE","✓ OK"))) -> 🔴 VENCIDA | J12: =IF(C12="Ninguna","Exigir garantía",IF(G12="NO","Renovar urgente",IF(E12<0.8,"Ampliar cobertura","Ninguna"))) -> Renovar urgente
A14: EVALUACIÓN DE GARANTÍAS
A15: Cartera sin garantía: | B15: =SUMIF(C8:C12,"Ninguna",B8:B12) -> 32000000
A16: Cartera con garantías vencidas: | B16: =SUMIF(G8:G12,"NO",B8:B12) -> 104500000 | H16: RIESGO GLOBAL: | I16: =IF(B15/SUM(B8:B12)>0.3,"MUY ALTO",IF(B16>0,"ALTO","BAJO")) -> ALTO
A17: Total cartera en riesgo: | B17: =B15+B16 -> 136500000
A21: Casos críticos: | B21: =COUNTIF(H8:H12,"MUY ALTO")+COUNTIF(H8:H12,"ALTO") -> 5 | C21: cuentas sin respaldo adecuado
D22: =B17 -> 136500000

Sheet PT_B.9_SideLetter
A1: PT B.9 - INDAGACIÓN ACUERDOS SIDE-LETTER
A2: NIA 240 - Condiciones Ocultas | Objetivo: Detectar acuerdos no revelados que afectan ventas
A4: Período revisado: | B4: 2024
A7: Cliente | B7: Factura | C7: Monto | D7: Condición Especial | E7: Revelado en Contrato | F7: Impacto Ingresos | G7: Cumple | H7: Riesgo | I7: Estado | J7: Acción
A8: CLIENTE ESPECIAL A | B8: FV-8523 | C8: 45000000 | D8: Devolución 100% si... | E8: NO | F8: Alto | G8: =IF(F8="Ninguno","SÍ",IF(E8="SÍ","SÍ","NO")) -> NO | H8: =IF(G8="NO","CRÍTICO","BAJO") -> CRÍTICO | I8: =IF(H8="CRÍTICO","⛔ SIDE-LETTER","✓ NORMAL") -> ⛔ SIDE-LETTER | J8: =IF(G8="NO","Ajustar reconocimiento ingreso","Ninguna") -> Ajustar reconocimiento ingreso
A9: DISTRIBUIDOR B | B9: FV-8645 | C9: 28000000 | D9: Derecho a devolver 30% | E9: NO | F9: Medio | G9: =IF(F9="Ninguno","SÍ",IF(E9="SÍ","SÍ","NO")) -> NO | H9: =IF(G9="NO","CRÍTICO","BAJO") -> CRÍTICO | I9: =IF(H9="CRÍTICO","⛔ SIDE-LETTER","✓ NORMAL") -> ⛔ SIDE-LETTER | J9: =IF(G9="NO","Ajustar reconocimiento ingreso","Ninguna") -> Ajustar reconocimiento ingreso
A10: CLIENTE REGULAR C | B10: FV-8712 | C10: 15000000 | D10: Condiciones normales | E10: SÍ | F10: Ninguno | G10: =IF(F10="Ninguno","SÍ",IF(E10="SÍ","SÍ","NO")) -> SÍ | H10: =IF(G10="NO","CRÍTICO","BAJO") -> BAJO | I10: =IF(H10="CRÍTICO","⛔ SIDE-LETTER","✓ NORMAL") -> ✓ NORMAL | J10: =IF(G10="NO","Ajustar reconocimiento ingreso","Ninguna") -> Ninguna
A11: CLIENTE BETA | B11: FV-8890 | C11: 38000000 | D11: Precio ajustable retroactivo | E11: NO | F11: Alto | G11: =IF(F11="Ninguno","SÍ",IF(E11="SÍ","SÍ","NO")) -> NO | H11: =IF(G11="NO","CRÍTICO","BAJO") -> CRÍTICO | I11: =IF(H11="CRÍTICO","⛔ SIDE-LETTER","✓ NORMAL") -> ⛔ SIDE-LETTER | J11: =IF(G11="NO","Ajustar reconocimiento ingreso","Ninguna") -> Ajustar reconocimiento ingreso
A13: EVALUACIÓN DE SIDE-LETTERS
A14: Acuerdos side-letter detectados: | B14: =COUNTIF(G8:G11,"NO") -> 3 | H14: RIESGO GLOBAL: | I14: =IF(B14>0,"CRÍTICO","BAJO") -> CRÍTICO
A15: Ingresos en riesgo de ajuste: | B15: =SUMIF(G8:G11,"NO",C8:C11) -> 111000000
A18: Hallazgos críticos: | B18: =B14 -> 3 | C18: acuerdos ocultos que afectan ingresos
A20: Ajuste estimado a ingresos: | B20: =B15*0.3 -> 33300000
D21: =B15 -> 111000000

Sheet PT_B.11_Duplicadas
A1: PT B.11 - FACTURAS DUPLICADAS Y NÚMEROS SECUENCIALES FALTANTES
A2: NIA 240 - Control de Secuencias | Objetivo: Detectar facturación fraudulenta o manipulación
A4: Período revisado: | B4: Diciembre 2024
A7: Tipo Hallazgo | B7: N° Factura | C7: Fecha | D7: Cliente | E7: Monto | F7: Duplicado de | G7: Secuencia Esperada | H7: Riesgo | I7: Estado | J7: Acción
A8: Duplicada | B8: FV-8523 | C8: 15/12/2024 | D8: CLIENTE A | E8: 8500000 | F8: FV-8523 | H8: =IF(A8="Duplicada","CRÍTICO",IF(A8="Salto","ALTO","BAJO")) -> CRÍTICO | I8: =IF(H8="CRÍTICO","⛔ DUPLICADA",IF(H8="ALTO","🔴 SALTO","✓ OK")) -> ⛔ DUPLICADA | J8: =IF(A8="Duplicada","Investigar fraude",IF(A8="Salto","Verificar anuladas","Ninguna")) -> Investigar fraude
A9: Salto | B9: FV-8527 | C9: 16/12/2024 | D9: CLIENTE B | E9: 12000000 | G9: FV-8524, 8525, 8526 | H9: =IF(A9="Duplicada","CRÍTICO",IF(A9="Salto","ALTO","BAJO")) -> ALTO | I9: =IF(H9="CRÍTICO","⛔ DUPLICADA",IF(H9="ALTO","🔴 SALTO","✓ OK")) -> 🔴 SALTO | J9: =IF(A9="Duplicada","Investigar fraude",IF(A9="Salto","Verificar anuladas","Ninguna")) -> Verificar anuladas
A10: Duplicada | B10: FV-8530 | C10: 18/12/2024 | D10: CLIENTE C | E10: 15000000 | F10: FV-8530 | H10: =IF(A10="Duplicada","CRÍTICO",IF(A10="Salto","ALTO","BAJO")) -> CRÍTICO | I10: =IF(H10="CRÍTICO","⛔ DUPLICADA",IF(H10="ALTO","🔴 SALTO","✓ OK")) -> ⛔ DUPLICADA | J10: =IF(A10="Duplicada","Investigar fraude",IF(A10="Salto","Verificar anuladas","Ninguna")) -> Investigar fraude
A11: Normal | B11: FV-8531 | C11: 18/12/2024 | D11: CLIENTE D | E11: 6200000 | H11: =IF(A11="Duplicada","CRÍTICO",IF(A11="Salto","ALTO","BAJO")) -> BAJO | I11: =IF(H11="CRÍTICO","⛔ DUPLICADA",IF(H11="ALTO","🔴 SALTO","✓ OK")) -> ✓ OK | J11: =IF(A11="Duplicada","Investigar fraude",IF(A11="Salto","Verificar anuladas","Ninguna")) -> Ninguna
A12: Salto | B12: FV-8540 | C12: 20/12/2024 | D12: CLIENTE E | E12: 9800000 | G12: FV-8532-8539 | H12: =IF(A12="Duplicada","CRÍTICO",IF(A12="Salto","ALTO","BAJO")) -> ALTO | I12: =IF(H12="CRÍTICO","⛔ DUPLICADA",IF(H12="ALTO","🔴 SALTO","✓ OK")) -> 🔴 SALTO | J12: =IF(A12="Duplicada","Investigar fraude",IF(A12="Salto","Verificar anuladas","Ninguna")) -> Verificar anuladas
A13: Duplicada | B13: FV-8545 | C13: 22/12/2024 | D13: CLIENTE F | E13: 22000000 | F13: FV-8545 | H13: =IF(A13="Duplicada","CRÍTICO",IF(A13="Salto","ALTO","BAJO")) -> CRÍTICO | I13: =IF(H13="CRÍTICO","⛔ DUPLICADA",IF(H13="ALTO","🔴 SALTO","✓ OK")) -> ⛔ DUPLICADA | J13: =IF(A13="Duplicada","Investigar fraude",IF(A13="Salto","Verificar anuladas","Ninguna")) -> Investigar fraude
A15: CONTROL DE SECUENCIAS Y DUPLICADOS
A16: Facturas duplicadas detectadas: | B16: =COUNTIF(A8:A13,"Duplicada") -> 3 | H16: RIESGO GLOBAL: | I16: =IF(B16>0,"CRÍTICO",IF(B17>1,"ALTO","BAJO")) -> CRÍTICO
A17: Saltos de secuencia detectados: | B17: =COUNTIF(A8:A13,"Salto") -> 2
A18: Monto en facturas duplicadas: | B18: =SUMIF(A8:A13,"Duplicada",E8:E13) -> 45500000
A21: Casos críticos: | B21: =B16 -> 3 | C21: facturas duplicadas requieren investigación
D22: =B18 -> 45500000

Sheet PT_B.12_WriteOffs
A1: PT B.12 - ANÁLISIS DE WRITE-OFFS INUSUALES PRE-CIERRE
A2: NIA 240 - Manipulación de Resultados | Objetivo: Detectar castigos estratégicos para mejorar indicadores
A4: Fecha de cierre: | B4: 31/12/2024
A7: N° Castigo | B7: Fecha | C7: Cliente | D7: Monto | E7: Días al Cierre | F7: Antigüedad Cartera | G7: Justificación | H7: Riesgo | I7: Estado | J7: Acción
A8: WO-045 | B8: 28/12/2024 | C8: CLIENTE MOROSO A | D8: 18500000 | E8: =$B$4-B8 -> 3 | F8: 245 | G8: Incobrabilidad | H8: =IF(AND(E8<=3,F8<180),"MUY ALTO",IF(E8<=5,"ALTO",IF(E8<=10,"MEDIO","BAJO"))) -> ALTO | I8: =IF(H8="MUY ALTO","🚨 SOSPECHOSO",IF(H8="ALTO","🔴 REVISAR",IF(H8="MEDIO","⚠ VERIFICAR","✓ NORMAL"))) -> 🔴 REVISAR | J8: =IF(H8="MUY ALTO","Investigar motivación",IF(H8="ALTO","Verificar justificación","Revisar documentación")) -> Verificar justificación
A9: WO-046 | B9: 30/12/2024 | C9: DEUDOR ACTIVO B | D9: 8200000 | E9: =$B$4-B9 -> 1 | F9: 125 | G9: Optimización cartera | H9: =IF(AND(E9<=3,F9<180),"MUY ALTO",IF(E9<=5,"ALTO",IF(E9<=10,"MEDIO","BAJO"))) -> MUY ALTO | I9: =IF(H9="MUY ALTO","🚨 SOSPECHOSO",IF(H9="ALTO","🔴 REVISAR",IF(H9="MEDIO","⚠ VERIFICAR","✓ NORMAL"))) -> 🚨 SOSPECHOSO | J9: =IF(H9="MUY ALTO","Investigar motivación",IF(H9="ALTO","Verificar justificación","Revisar documentación")) -> Investigar motivación
A10: WO-047 | B10: 31/12/2024 | C10: EMPRESA LIQUIDADA C | D10: 12000000 | E10: =$B$4-B10 -> 0 | F10: 520 | G10: Liquidación judicial | H10: =IF(AND(E10<=3,F10<180),"MUY ALTO",IF(E10<=5,"ALTO",IF(E10<=10,"MEDIO","BAJO"))) -> ALTO | I10: =IF(H10="MUY ALTO","🚨 SOSPECHOSO",IF(H10="ALTO","🔴 REVISAR",IF(H10="MEDIO","⚠ VERIFICAR","✓ NORMAL"))) -> 🔴 REVISAR | J10: =IF(H10="MUY ALTO","Investigar motivación",IF(H10="ALTO","Verificar justificación","Revisar documentación")) -> Verificar justificación
A11: WO-048 | B11: 30/12/2024 | C11: CLIENTE REGULAR D | D11: 15800000 | E11: =$B$4-B11 -> 1 | F11: 85 | G11: Mejora indicadores | H11: =IF(AND(E11<=3,F11<180),"MUY ALTO",IF(E11<=5,"ALTO",IF(E11<=10,"MEDIO","BAJO"))) -> MUY ALTO | I11: =IF(H11="MUY ALTO","🚨 SOSPECHOSO",IF(H11="ALTO","🔴 REVISAR",IF(H11="MEDIO","⚠ VERIFICAR","✓ NORMAL"))) -> 🚨 SOSPECHOSO | J11: =IF(H11="MUY ALTO","Investigar motivación",IF(H11="ALTO","Verificar justificación","Revisar documentación")) -> Investigar motivación
A12: WO-049 | B12: 31/12/2024 | C12: DEUDOR PRESCRITO E | D12: 9500000 | E12: =$B$4-B12 -> 0 | F12: 720 | G12: Prescripción | H12: =IF(AND(E12<=3,F12<180),"MUY ALTO",IF(E12<=5,"ALTO",IF(E12<=10,"MEDIO","BAJO"))) -> ALTO | I12: =IF(H12="MUY ALTO","🚨 SOSPECHOSO",IF(H12="ALTO","🔴 REVISAR",IF(H12="MEDIO","⚠ VERIFICAR","✓ NORMAL"))) -> 🔴 REVISAR | J12: =IF(H12="MUY ALTO","Investigar motivación",IF(H12="ALTO","Verificar justificación","Revisar documentación")) -> Verificar justificación
A14: ANÁLISIS DE WRITE-OFFS PRE-CIERRE
A15: Write-offs últimos 3 días: | B15: =COUNTIF(E8:E12,"<=3") -> 5
A16: Casos con riesgo MUY ALTO: | B16: =COUNTIF(H8:H12,"MUY ALTO") -> 2 | H16: RIESGO GLOBAL: | I16: =IF(B15>2,"CRÍTICO",IF(B16>0,"ALTO",IF(B15>0,"MEDIO","BAJO"))) -> CRÍTICO
A17: Monto total write-offs pre-cierre: | B17: =SUM(D8:D12) -> 64000000
A18: Monto sospechoso (MUY ALTO): | B18: =SUMIF(H8:H12,"MUY ALTO",D8:D12) -> 24000000
A21: Casos sospechosos: | B21: =COUNTIF(H8:H12,"MUY ALTO")+COUNTIF(H8:H12,"ALTO") -> 5 | C21: castigos requieren investigación
D22: =B18 -> 24000000
