Workbook

Sheet ÍNDICE_GENERAL
A1: PROGRAMA DE AUDITORÍA - INVENTARIOS
A2: Basado en NIAs 501, 240, 330 - Observación de Inventarios y Detección de Fraude
A4: Cliente: | B4: [NOMBRE DEL CLIENTE]
A5: Período auditado: | B5: 01/01/2024 - 31/12/2024
A6: Fecha de conteo físico: | B6: 31/12/2024
A7: Auditor responsable: | B7: [NOMBRE DEL AUDITOR]
A9: REF | B9: PROCEDIMIENTO | C9: OBJETIVO NIA | D9: RIESGO | E9: ESTADO | F9: HALLAZGOS | G9: MATERIALIDAD | H9: RESPONSABLE | I9: FECHA
A10: PT C.1 | B10: Observación Física Sorpresiva | C10: NIA 501 - Evidencia específica | D10: =PT_C.1_ObsFisica!I18 -> 0 | E10: =PT_C.1_ObsFisica!J18 -> 0 | F10: =PT_C.1_ObsFisica!B25 -> 5 | G10: =PT_C.1_ObsFisica!D26 -> 198600000 | H10: [Auditor] | I10: =TODAY() -> 45978
A11: PT C.2 | B11: Conteo Cíclico Alto Valor | C11: Verificación partidas materiales | D11: =PT_C.2_ConteoAltoValor!I17 -> RIESGO GLOBAL: | E11: =PT_C.2_ConteoAltoValor!J17 -> MEDIO | F11: =PT_C.2_ConteoAltoValor!B24 -> 1 | G11: =PT_C.2_ConteoAltoValor!D25 -> 15000000 | H11: [Auditor] | I11: =TODAY() -> 45978
A12: PT C.3 | B12: Movimientos Ubicaciones Remotas | C12: Detección de traslados ficticios | D12: =PT_C.3_UbicRemote!H16 -> RIESGO GLOBAL: | E12: =PT_C.3_UbicRemote!I16 -> CRÍTICO | F12: =PT_C.3_UbicRemote!B22 -> 3 | G12: =PT_C.3_UbicRemote!D23 -> 58500000 | H12: [Auditor] | I12: =TODAY() -> 45978
A13: PT C.4 | B13: Análisis de Obsolescencia | C13: Valuación correcta | D13: =PT_C.4_Obsolescencia!I17 -> RIESGO GLOBAL: | E13: =PT_C.4_Obsolescencia!J17 -> ALTO | F13: =PT_C.4_Obsolescencia!B24 -> 87205000 | G13: =PT_C.4_Obsolescencia!D25 -> 87205000 | H13: [Auditor] | I13: =TODAY() -> 45978
A14: PT C.5 | B14: Verificación de Propiedad | C14: Derechos sobre activos | D14: =PT_C.5_Propiedad!H16 -> RIESGO GLOBAL: | E14: =PT_C.5_Propiedad!I16 -> CRÍTICO | F14: =PT_C.5_Propiedad!B21 -> 1 | G14: =PT_C.5_Propiedad!D22 -> 45000000 | H14: [Auditor] | I14: =TODAY() -> 45978
A15: PT C.6 | B15: Cut-Off Compras/Ventas | C15: NIA 330 - Corte operaciones | D15: =PT_C.6_CutOff!I16 -> 2025 | E15: =PT_C.6_CutOff!J16 -> BAJO | F15: =PT_C.6_CutOff!B23 -> 2 | G15: =PT_C.6_CutOff!D24 -> 43500000 | H15: [Auditor] | I15: =TODAY() -> 45978
A16: PT C.7 | B16: Margen Bruto por Línea | C16: Detección de desviaciones | D16: =PT_C.7_MargenBruto!I17 -> RIESGO GLOBAL: | E16: =PT_C.7_MargenBruto!J17 -> BAJO | F16: =PT_C.7_MargenBruto!B24 -> 0 | G16: =PT_C.7_MargenBruto!D25 -> 0 | H16: [Auditor] | I16: =TODAY() -> 45978
A17: PT C.8 | B17: Inventario en Tránsito | C17: Existencia y valuación | D17: =PT_C.8_EnTransito!H16 -> RIESGO GLOBAL: | E17: =PT_C.8_EnTransito!I16 -> MEDIO | F17: =PT_C.8_EnTransito!B21 -> 2 | G17: =PT_C.8_EnTransito!D22 -> 63000000 | H17: [Auditor] | I17: =TODAY() -> 45978
A18: PT C.9 | B18: Ajustes Durante el Período | C18: Manipulación de registros | D18: =PT_C.9_Ajustes!H16 -> RIESGO GLOBAL: | E18: =PT_C.9_Ajustes!I16 -> CRÍTICO | F18: =PT_C.9_Ajustes!B22 -> 2 | G18: =PT_C.9_Ajustes!D23 -> 430750000 | H18: [Auditor] | I18: =TODAY() -> 45978
A19: PT C.10 | B19: Inventario Pignorado | C19: Restricciones no reveladas | D19: =PT_C.10_Pignorado!H16 -> RIESGO GLOBAL: | E19: =PT_C.10_Pignorado!I16 -> ALTO | F19: =PT_C.10_Pignorado!B20 -> 2 | G19: =PT_C.10_Pignorado!D21 -> 310000000 | H19: [Auditor] | I19: =TODAY() -> 45978
A20: PT C.11 | B20: Variaciones Entre Conteos | C20: Confiabilidad del conteo | D20: =PT_C.11_Variaciones!I17 -> RIESGO GLOBAL: | E20: =PT_C.11_Variaciones!J17 -> BAJO | F20: =PT_C.11_Variaciones!B24 -> 0 | G20: =PT_C.11_Variaciones!D25 -> 0 | H20: [Auditor] | I20: =TODAY() -> 45978
A21: PT C.12 | B21: Costos vs Mercado | C21: Prueba NRV | D21: =PT_C.12_CostosVsMercado!I17 -> RIESGO GLOBAL: | E21: =PT_C.12_CostosVsMercado!J17 -> ALTO | F21: =PT_C.12_CostosVsMercado!B24 -> 47800000 | G21: =PT_C.12_CostosVsMercado!D25 -> 47800000 | H21: [Auditor] | I21: =TODAY() -> 45978
A22: PT C.13 | B22: Productos Fantasma | C22: Integridad de registros | D22: =PT_C.13_Fantasma!H16 -> RIESGO GLOBAL: | E22: =PT_C.13_Fantasma!I16 -> CRÍTICO | F22: =PT_C.13_Fantasma!B21 -> 3 | G22: =PT_C.13_Fantasma!D22 -> 220000000 | H22: [Auditor] | I22: =TODAY() -> 45978

Sheet PT_C.1_ObsFisica
A1: PT C.1 - OBSERVACIÓN FÍSICA SORPRESIVA
A2: NIA 501 - Evidencia Específica | Objetivo: Verificar existencia y condición física del inventario
A4: Fecha de conteo sorpresivo: | B4: 31/12/2024
A7: Código Producto | B7: Descripción | C7: Ubicación | D7: Cant. Sistema | E7: Cant. Física | F7: Diferencia | G7: % Dif | H7: Valor Unit | I7: Valor Dif | J7: Riesgo | K7: Estado
A8: INV-001 | B8: Materia Prima A | C8: Bodega 1 | D8: 1500 | E8: 1500 | F8: =D8-E8 -> 0 | G8: =IF(D8=0,0,ABS(F8/D8)) -> 0 | H8: 125000 | I8: =ABS(F8)*H8 -> 0 | J8: =IF(G8>0.15,"CRÍTICO",IF(G8>0.1,"ALTO",IF(G8>0.05,"MEDIO","BAJO"))) -> BAJO | K8: =IF(J8="CRÍTICO","🚨 INVESTIGAR",IF(J8="ALTO","🔴 DIFERENCIA",IF(J8="MEDIO","⚠ REVISAR","✓ OK"))) -> ✓ OK
A9: INV-002 | B9: Producto Terminado B | C9: Bodega 2 | D9: 850 | E9: 780 | F9: =D9-E9 -> 70 | G9: =IF(D9=0,0,ABS(F9/D9)) -> 0.082352941 | H9: 580000 | I9: =ABS(F9)*H9 -> 40600000 | J9: =IF(G9>0.15,"CRÍTICO",IF(G9>0.1,"ALTO",IF(G9>0.05,"MEDIO","BAJO"))) -> MEDIO | K9: =IF(J9="CRÍTICO","🚨 INVESTIGAR",IF(J9="ALTO","🔴 DIFERENCIA",IF(J9="MEDIO","⚠ REVISAR","✓ OK"))) -> ⚠ REVISAR
A10: INV-003 | B10: Componente C | C10: Bodega 1 | D10: 3200 | E10: 3200 | F10: =D10-E10 -> 0 | G10: =IF(D10=0,0,ABS(F10/D10)) -> 0 | H10: 45000 | I10: =ABS(F10)*H10 -> 0 | J10: =IF(G10>0.15,"CRÍTICO",IF(G10>0.1,"ALTO",IF(G10>0.05,"MEDIO","BAJO"))) -> BAJO | K10: =IF(J10="CRÍTICO","🚨 INVESTIGAR",IF(J10="ALTO","🔴 DIFERENCIA",IF(J10="MEDIO","⚠ REVISAR","✓ OK"))) -> ✓ OK
A11: INV-004 | B11: Material Importado D | C11: Bodega 3 | D11: 450 | E11: 420 | F11: =D11-E11 -> 30 | G11: =IF(D11=0,0,ABS(F11/D11)) -> 0.066666667 | H11: 1200000 | I11: =ABS(F11)*H11 -> 36000000 | J11: =IF(G11>0.15,"CRÍTICO",IF(G11>0.1,"ALTO",IF(G11>0.05,"MEDIO","BAJO"))) -> MEDIO | K11: =IF(J11="CRÍTICO","🚨 INVESTIGAR",IF(J11="ALTO","🔴 DIFERENCIA",IF(J11="MEDIO","⚠ REVISAR","✓ OK"))) -> ⚠ REVISAR
A12: INV-005 | B12: Producto Alto Valor E | C12: Bodega 2 | D12: 180 | E12: 165 | F12: =D12-E12 -> 15 | G12: =IF(D12=0,0,ABS(F12/D12)) -> 0.083333333 | H12: 2800000 | I12: =ABS(F12)*H12 -> 42000000 | J12: =IF(G12>0.15,"CRÍTICO",IF(G12>0.1,"ALTO",IF(G12>0.05,"MEDIO","BAJO"))) -> MEDIO | K12: =IF(J12="CRÍTICO","🚨 INVESTIGAR",IF(J12="ALTO","🔴 DIFERENCIA",IF(J12="MEDIO","⚠ REVISAR","✓ OK"))) -> ⚠ REVISAR
A13: INV-006 | B13: Insumo F | C13: Bodega 1 | D13: 5600 | E13: 5600 | F13: =D13-E13 -> 0 | G13: =IF(D13=0,0,ABS(F13/D13)) -> 0 | H13: 28000 | I13: =ABS(F13)*H13 -> 0 | J13: =IF(G13>0.15,"CRÍTICO",IF(G13>0.1,"ALTO",IF(G13>0.05,"MEDIO","BAJO"))) -> BAJO | K13: =IF(J13="CRÍTICO","🚨 INVESTIGAR",IF(J13="ALTO","🔴 DIFERENCIA",IF(J13="MEDIO","⚠ REVISAR","✓ OK"))) -> ✓ OK
A14: INV-007 | B14: Producto G | C14: Bodega 4 | D14: 920 | E14: 850 | F14: =D14-E14 -> 70 | G14: =IF(D14=0,0,ABS(F14/D14)) -> 0.076086957 | H14: 350000 | I14: =ABS(F14)*H14 -> 24500000 | J14: =IF(G14>0.15,"CRÍTICO",IF(G14>0.1,"ALTO",IF(G14>0.05,"MEDIO","BAJO"))) -> MEDIO | K14: =IF(J14="CRÍTICO","🚨 INVESTIGAR",IF(J14="ALTO","🔴 DIFERENCIA",IF(J14="MEDIO","⚠ REVISAR","✓ OK"))) -> ⚠ REVISAR
A15: INV-008 | B15: Materia Prima H | C15: Bodega 3 | D15: 2100 | E15: 2100 | F15: =D15-E15 -> 0 | G15: =IF(D15=0,0,ABS(F15/D15)) -> 0 | H15: 95000 | I15: =ABS(F15)*H15 -> 0 | J15: =IF(G15>0.15,"CRÍTICO",IF(G15>0.1,"ALTO",IF(G15>0.05,"MEDIO","BAJO"))) -> BAJO | K15: =IF(J15="CRÍTICO","🚨 INVESTIGAR",IF(J15="ALTO","🔴 DIFERENCIA",IF(J15="MEDIO","⚠ REVISAR","✓ OK"))) -> ✓ OK
A16: INV-009 | B16: Componente Importado I | C16: Bodega 2 | D16: 340 | E16: 310 | F16: =D16-E16 -> 30 | G16: =IF(D16=0,0,ABS(F16/D16)) -> 0.088235294 | H16: 1850000 | I16: =ABS(F16)*H16 -> 55500000 | J16: =IF(G16>0.15,"CRÍTICO",IF(G16>0.1,"ALTO",IF(G16>0.05,"MEDIO","BAJO"))) -> MEDIO | K16: =IF(J16="CRÍTICO","🚨 INVESTIGAR",IF(J16="ALTO","🔴 DIFERENCIA",IF(J16="MEDIO","⚠ REVISAR","✓ OK"))) -> ⚠ REVISAR
A17: INV-010 | B17: Producto J | C17: Bodega 1 | D17: 1250 | E17: 1250 | F17: =D17-E17 -> 0 | G17: =IF(D17=0,0,ABS(F17/D17)) -> 0 | H17: 220000 | I17: =ABS(F17)*H17 -> 0 | J17: =IF(G17>0.15,"CRÍTICO",IF(G17>0.1,"ALTO",IF(G17>0.05,"MEDIO","BAJO"))) -> BAJO | K17: =IF(J17="CRÍTICO","🚨 INVESTIGAR",IF(J17="ALTO","🔴 DIFERENCIA",IF(J17="MEDIO","⚠ REVISAR","✓ OK"))) -> ✓ OK
A19: RESUMEN DE OBSERVACIÓN FÍSICA
A20: Partidas contadas: | B20: =COUNTA(A8:A17) -> 10 | I20: RIESGO GLOBAL: | J20: =IF(B23>2,"CRÍTICO",IF(B22>5,"ALTO",IF(B22>0,"MEDIO","BAJO"))) -> MEDIO
A21: Partidas sin diferencia: | B21: =COUNTIF(F8:F17,0) -> 5
A22: Partidas con diferencia: | B22: =COUNTIFS(F8:F17,"<>0") -> 5
A23: Diferencias críticas (>15%): | B23: =COUNTIF(J8:J17,"CRÍTICO") -> 0
A24: Valor total diferencias: | B24: =SUM(I8:I17) -> 198600000
A25: Hallazgos: | B25: =B22 -> 5 | C25: partidas con diferencias físicas vs sistema
D26: =B24 -> 198600000

Sheet PT_C.2_ConteoAltoValor
A1: PT C.2 - CONTEO CÍCLICO ADICIONAL - PARTIDAS ALTO VALOR
A2: Verificación Intensiva | Objetivo: Asegurar exactitud en partidas materiales
A4: Fecha de conteo adicional: | B4: 31/12/2024
A7: SKU | B7: Producto | C7: Valor Unitario | D7: Cant. Sistema | E7: Conteo 1 | F7: Conteo 2 | G7: Conteo 3 | H7: Promedio | I7: Diferencia | J7: Riesgo | K7: Estado
A8: SKU-001 | B8: Equipo Importado A | C8: 8500000 | D8: 45 | E8: 45 | F8: 45 | G8: 45 | H8: =ROUND(AVERAGE(E8:G8),0) -> 45 | I8: =D8-H8 -> 0 | J8: =IF(ABS(I8)>0,"ALTO","BAJO") -> BAJO | K8: =IF(J8="ALTO","🔴 DIFERENCIA","✓ EXACTO") -> ✓ EXACTO
A9: SKU-002 | B9: Maquinaria B | C9: 12000000 | D9: 12 | E9: 12 | F9: 11 | G9: 12 | H9: =ROUND(AVERAGE(E9:G9),0) -> 12 | I9: =D9-H9 -> 0 | J9: =IF(ABS(I9)>0,"ALTO","BAJO") -> BAJO | K9: =IF(J9="ALTO","🔴 DIFERENCIA","✓ EXACTO") -> ✓ EXACTO
A10: SKU-003 | B10: Componente Premium C | C10: 5800000 | D10: 78 | E10: 78 | F10: 78 | G10: 78 | H10: =ROUND(AVERAGE(E10:G10),0) -> 78 | I10: =D10-H10 -> 0 | J10: =IF(ABS(I10)>0,"ALTO","BAJO") -> BAJO | K10: =IF(J10="ALTO","🔴 DIFERENCIA","✓ EXACTO") -> ✓ EXACTO
A11: SKU-004 | B11: Producto Tecnológico D | C11: 15000000 | D11: 28 | E11: 28 | F11: 27 | G11: 26 | H11: =ROUND(AVERAGE(E11:G11),0) -> 27 | I11: =D11-H11 -> 1 | J11: =IF(ABS(I11)>0,"ALTO","BAJO") -> ALTO | K11: =IF(J11="ALTO","🔴 DIFERENCIA","✓ EXACTO") -> 🔴 DIFERENCIA
A12: SKU-005 | B12: Material Especial E | C12: 9200000 | D12: 52 | E12: 52 | F12: 52 | G12: 52 | H12: =ROUND(AVERAGE(E12:G12),0) -> 52 | I12: =D12-H12 -> 0 | J12: =IF(ABS(I12)>0,"ALTO","BAJO") -> BAJO | K12: =IF(J12="ALTO","🔴 DIFERENCIA","✓ EXACTO") -> ✓ EXACTO
A13: SKU-006 | B13: Equipo F | C13: 18500000 | D13: 8 | E13: 8 | F13: 7 | G13: 8 | H13: =ROUND(AVERAGE(E13:G13),0) -> 8 | I13: =D13-H13 -> 0 | J13: =IF(ABS(I13)>0,"ALTO","BAJO") -> BAJO | K13: =IF(J13="ALTO","🔴 DIFERENCIA","✓ EXACTO") -> ✓ EXACTO
A14: SKU-007 | B14: Componente Crítico G | C14: 6700000 | D14: 95 | E14: 95 | F14: 95 | G14: 95 | H14: =ROUND(AVERAGE(E14:G14),0) -> 95 | I14: =D14-H14 -> 0 | J14: =IF(ABS(I14)>0,"ALTO","BAJO") -> BAJO | K14: =IF(J14="ALTO","🔴 DIFERENCIA","✓ EXACTO") -> ✓ EXACTO
A16: EVALUACIÓN DE CONTEOS MÚLTIPLES
A17: Partidas alto valor revisadas: | B17: =COUNTA(A8:A14) -> 7 | I17: RIESGO GLOBAL: | J17: =IF(B19>2,"ALTO",IF(B19>0,"MEDIO","BAJO")) -> MEDIO
A18: Partidas exactas (3 conteos iguales): | B18: =COUNTIF(I8:I14,0) -> 6
A19: Partidas con diferencias: | B19: =COUNTIFS(I8:I14,"<>0") -> 1
A20: Valor total inventario alto valor: | B20: =SUMPRODUCT(C8:C14,D8:D14) -> 2661800000
A21: Valor en riesgo por diferencias: | B21: =SUMPRODUCT(C8:C14,ABS(I8:I14)) -> 15000000
A24: Partidas que requieren reconteo: | B24: =B19 -> 1
D25: =B21 -> 15000000

Sheet PT_C.3_UbicRemote
A1: PT C.3 - MOVIMIENTOS INUSUALES EN UBICACIONES REMOTAS
A2: Detección de Fraude | Objetivo: Identificar traslados ficticios para ocultar faltantes
A4: Período revisado: | B4: Diciembre 2024
A7: Fecha | B7: N° Traslado | C7: Desde | D7: Hacia | E7: Producto | F7: Cantidad | G7: Valor | H7: Recibido | I7: Riesgo | J7: Estado
A8: 28/12/2024 | B8: TRAS-001 | C8: Bodega Principal | D8: Bodega Remota A | E8: Producto X | F8: 250 | G8: 18500000 | H8: NO | I8: =IF(H8="NO","CRÍTICO","BAJO") -> CRÍTICO | J8: =IF(I8="CRÍTICO","⛔ NO CONFIRMADO","✓ CONFIRMADO") -> ⛔ NO CONFIRMADO
A9: 29/12/2024 | B9: TRAS-002 | C9: Bodega 2 | D9: Bodega Remota B | E9: Material Y | F9: 180 | G9: 12000000 | H9: SÍ | I9: =IF(H9="NO","CRÍTICO","BAJO") -> BAJO | J9: =IF(I9="CRÍTICO","⛔ NO CONFIRMADO","✓ CONFIRMADO") -> ✓ CONFIRMADO
A10: 30/12/2024 | B10: TRAS-003 | C10: Bodega Principal | D10: Bodega Remota A | E10: Componente Z | F10: 420 | G10: 25000000 | H10: NO | I10: =IF(H10="NO","CRÍTICO","BAJO") -> CRÍTICO | J10: =IF(I10="CRÍTICO","⛔ NO CONFIRMADO","✓ CONFIRMADO") -> ⛔ NO CONFIRMADO
A11: 31/12/2024 | B11: TRAS-004 | C11: Bodega 3 | D11: Bodega Remota C | E11: Producto W | F11: 150 | G11: 15000000 | H11: NO | I11: =IF(H11="NO","CRÍTICO","BAJO") -> CRÍTICO | J11: =IF(I11="CRÍTICO","⛔ NO CONFIRMADO","✓ CONFIRMADO") -> ⛔ NO CONFIRMADO
A12: 29/12/2024 | B12: TRAS-005 | C12: Bodega 2 | D12: Bodega 4 | E12: Material V | F12: 320 | G12: 8500000 | H12: SÍ | I12: =IF(H12="NO","CRÍTICO","BAJO") -> BAJO | J12: =IF(I12="CRÍTICO","⛔ NO CONFIRMADO","✓ CONFIRMADO") -> ✓ CONFIRMADO
A14: EVALUACIÓN DE TRASLADOS
A15: Traslados a ubicaciones remotas: | B15: =COUNTA(B8:B12) -> 5
A16: Traslados NO confirmados: | B16: =COUNTIF(H8:H12,"NO") -> 3 | H16: RIESGO GLOBAL: | I16: =IF(B16>2,"CRÍTICO",IF(B16>0,"ALTO","BAJO")) -> CRÍTICO
A17: Valor en tránsito no confirmado: | B17: =SUMIF(H8:H12,"NO",G8:G12) -> 58500000
A22: Traslados sospechosos: | B22: =B16 -> 3 | C22: movimientos sin confirmación de recepción
D23: =B17 -> 58500000

Sheet PT_C.4_Obsolescencia
A1: PT C.4 - ANÁLISIS DE OBSOLESCENCIA VS POLÍTICAS
A2: Valuación Correcta | Objetivo: Verificar adecuada provisión por obsolescencia
A4: Política de obsolescencia: | B4: 6 meses sin movimiento = 50%, 12 meses = 100%
A7: Código | B7: Producto | C7: Cant. | D7: Costo Unit | E7: Valor Total | F7: Días Sin Movimiento | G7: Provisión Política | H7: Provisión Real | I7: Diferencia | J7: Riesgo | K7: Estado
A8: OBS-001 | B8: Producto Descontinuado A | C8: 450 | D8: 85000 | E8: =C8*D8 -> 38250000 | F8: 220 | G8: =IF(F8>=360,E8,IF(F8>=180,E8*0.5,0)) -> 19125000 | H8: 0 | I8: =G8-H8 -> 19125000 | J8: =IF(I8>E8*0.3,"ALTO",IF(I8>0,"MEDIO","BAJO")) -> ALTO | K8: =IF(J8="ALTO","🔴 SUBPROVISIONADO",IF(J8="MEDIO","⚠ REVISAR","✓ OK")) -> 🔴 SUBPROVISIONADO
A9: OBS-002 | B9: Material Antiguo B | C9: 280 | D9: 125000 | E9: =C9*D9 -> 35000000 | F9: 90 | G9: =IF(F9>=360,E9,IF(F9>=180,E9*0.5,0)) -> 0 | H9: 15000000 | I9: =G9-H9 -> -15000000 | J9: =IF(I9>E9*0.3,"ALTO",IF(I9>0,"MEDIO","BAJO")) -> BAJO | K9: =IF(J9="ALTO","🔴 SUBPROVISIONADO",IF(J9="MEDIO","⚠ REVISAR","✓ OK")) -> ✓ OK
A10: OBS-003 | B10: Componente Obsoleto C | C10: 820 | D10: 45000 | E10: =C10*D10 -> 36900000 | F10: 420 | G10: =IF(F10>=360,E10,IF(F10>=180,E10*0.5,0)) -> 36900000 | H10: 0 | I10: =G10-H10 -> 36900000 | J10: =IF(I10>E10*0.3,"ALTO",IF(I10>0,"MEDIO","BAJO")) -> ALTO | K10: =IF(J10="ALTO","🔴 SUBPROVISIONADO",IF(J10="MEDIO","⚠ REVISAR","✓ OK")) -> 🔴 SUBPROVISIONADO
A11: OBS-004 | B11: Producto Regular D | C11: 1200 | D11: 95000 | E11: =C11*D11 -> 114000000 | F11: 45 | G11: =IF(F11>=360,E11,IF(F11>=180,E11*0.5,0)) -> 0 | H11: 0 | I11: =G11-H11 -> 0 | J11: =IF(I11>E11*0.3,"ALTO",IF(I11>0,"MEDIO","BAJO")) -> BAJO | K11: =IF(J11="ALTO","🔴 SUBPROVISIONADO",IF(J11="MEDIO","⚠ REVISAR","✓ OK")) -> ✓ OK
A12: OBS-005 | B12: Material Vencido E | C12: 150 | D12: 380000 | E12: =C12*D12 -> 57000000 | F12: 540 | G12: =IF(F12>=360,E12,IF(F12>=180,E12*0.5,0)) -> 57000000 | H12: 28500000 | I12: =G12-H12 -> 28500000 | J12: =IF(I12>E12*0.3,"ALTO",IF(I12>0,"MEDIO","BAJO")) -> ALTO | K12: =IF(J12="ALTO","🔴 SUBPROVISIONADO",IF(J12="MEDIO","⚠ REVISAR","✓ OK")) -> 🔴 SUBPROVISIONADO
A13: OBS-006 | B13: Componente Lento F | C13: 680 | D13: 52000 | E13: =C13*D13 -> 35360000 | F13: 210 | G13: =IF(F13>=360,E13,IF(F13>=180,E13*0.5,0)) -> 17680000 | H13: 0 | I13: =G13-H13 -> 17680000 | J13: =IF(I13>E13*0.3,"ALTO",IF(I13>0,"MEDIO","BAJO")) -> ALTO | K13: =IF(J13="ALTO","🔴 SUBPROVISIONADO",IF(J13="MEDIO","⚠ REVISAR","✓ OK")) -> 🔴 SUBPROVISIONADO
A15: EVALUACIÓN DE PROVISIONES
A16: Partidas obsoletas identificadas: | B16: =COUNTIF(F8:F13,">=180") -> 4
A17: Partidas subprovisionadas: | B17: =COUNTIF(I8:I13,">0") -> 4 | I17: RIESGO GLOBAL: | J17: =IF(B20/B18>0.5,"ALTO",IF(B20>0,"MEDIO","BAJO")) -> ALTO
A18: Provisión sugerida total: | B18: =SUM(G8:G13) -> 130705000
A19: Provisión actual: | B19: =SUM(H8:H13) -> 43500000
A20: Provisión adicional requerida: | B20: =B18-B19 -> 87205000
A24: Ajuste requerido: | B24: =B20 -> 87205000 | C24: provisión insuficiente según política
D25: =B20 -> 87205000

Sheet PT_C.5_Propiedad
A1: PT C.5 - VERIFICACIÓN DE PROPIEDAD - DOCUMENTOS CONSIGNACIÓN
A2: Derechos sobre Activos | Objetivo: Verificar propiedad del inventario registrado
A4: Fecha de verificación: | B4: 31/12/2024
A7: Producto | B7: Proveedor | C7: Cantidad | D7: Valor | E7: Tipo Acuerdo | F7: Documento Propiedad | G7: En Libros | H7: Riesgo | I7: Estado | J7: Acción
A8: Material A | B8: Proveedor 1 | C8: 450 | D8: 28500000 | E8: Propio | F8: Factura | G8: SÍ | H8: =IF(AND(E8="Consignación",G8="SÍ"),"CRÍTICO",IF(AND(E8="Propio",G8="NO"),"ALTO","BAJO")) -> BAJO | I8: =IF(H8="CRÍTICO","⛔ MAL REGISTRADO",IF(H8="ALTO","🔴 ERROR","✓ CORRECTO")) -> ✓ CORRECTO | J8: =IF(H8="CRÍTICO","Excluir de inventario",IF(H8="ALTO","Verificar factura","Ninguna")) -> Ninguna
A9: Producto B | B9: Proveedor 2 | C9: 280 | D9: 45000000 | E9: Consignación | F9: No disponible | G9: SÍ | H9: =IF(AND(E9="Consignación",G9="SÍ"),"CRÍTICO",IF(AND(E9="Propio",G9="NO"),"ALTO","BAJO")) -> CRÍTICO | I9: =IF(H9="CRÍTICO","⛔ MAL REGISTRADO",IF(H9="ALTO","🔴 ERROR","✓ CORRECTO")) -> ⛔ MAL REGISTRADO | J9: =IF(H9="CRÍTICO","Excluir de inventario",IF(H9="ALTO","Verificar factura","Ninguna")) -> Excluir de inventario
A10: Componente C | B10: Proveedor 3 | C10: 820 | D10: 18000000 | E10: Propio | F10: Factura | G10: SÍ | H10: =IF(AND(E10="Consignación",G10="SÍ"),"CRÍTICO",IF(AND(E10="Propio",G10="NO"),"ALTO","BAJO")) -> BAJO | I10: =IF(H10="CRÍTICO","⛔ MAL REGISTRADO",IF(H10="ALTO","🔴 ERROR","✓ CORRECTO")) -> ✓ CORRECTO | J10: =IF(H10="CRÍTICO","Excluir de inventario",IF(H10="ALTO","Verificar factura","Ninguna")) -> Ninguna
A11: Material D | B11: Proveedor 4 | C11: 350 | D11: 62000000 | E11: Consignación | F11: Contrato consig | G11: NO | H11: =IF(AND(E11="Consignación",G11="SÍ"),"CRÍTICO",IF(AND(E11="Propio",G11="NO"),"ALTO","BAJO")) -> BAJO | I11: =IF(H11="CRÍTICO","⛔ MAL REGISTRADO",IF(H11="ALTO","🔴 ERROR","✓ CORRECTO")) -> ✓ CORRECTO | J11: =IF(H11="CRÍTICO","Excluir de inventario",IF(H11="ALTO","Verificar factura","Ninguna")) -> Ninguna
A12: Producto E | B12: Proveedor 5 | C12: 180 | D12: 35000000 | E12: Propio | F12: Factura | G12: SÍ | H12: =IF(AND(E12="Consignación",G12="SÍ"),"CRÍTICO",IF(AND(E12="Propio",G12="NO"),"ALTO","BAJO")) -> BAJO | I12: =IF(H12="CRÍTICO","⛔ MAL REGISTRADO",IF(H12="ALTO","🔴 ERROR","✓ CORRECTO")) -> ✓ CORRECTO | J12: =IF(H12="CRÍTICO","Excluir de inventario",IF(H12="ALTO","Verificar factura","Ninguna")) -> Ninguna
A14: EVALUACIÓN DE PROPIEDAD
A15: Inventario en consignación mal registrado: | B15: =COUNTIFS(E8:E12,"Consignación",G8:G12,"SÍ") -> 1
A16: Valor mal clasificado: | B16: =SUMIFS(D8:D12,E8:E12,"Consignación",G8:G12,"SÍ") -> 45000000 | H16: RIESGO GLOBAL: | I16: =IF(B15>0,"CRÍTICO","BAJO") -> CRÍTICO
A21: Ajustes requeridos: | B21: =B15 -> 1 | C21: partidas sin propiedad en libros
D22: =B16 -> 45000000

Sheet PT_C.6_CutOff
A1: PT C.6 - CUT-OFF DE COMPRAS Y VENTAS (5 TRANSACCIONES PRE/POST)
A2: NIA 330 - Corte de Operaciones | Objetivo: Verificar registro correcto por período
A4: Fecha de corte: | B4: 31/12/2024
A7: Tipo | B7: N° Doc | C7: Fecha Doc | D7: Fecha Recepción | E7: Producto | F7: Cantidad | G7: Valor | H7: Período Correcto | I7: Período Registro | J7: Riesgo | K7: Estado
A8: Compra | B8: OC-897 | C8: 28/12/2024 | D8: 02/01/2025 | E8: Material A | F8: 450 | G8: 18500000 | H8: 2025 | I8: 2024 | J8: =IF(H8<>I8,"ALTO","BAJO") -> ALTO | K8: =IF(J8="ALTO","🔴 ERROR CUTOFF","✓ CORRECTO") -> 🔴 ERROR CUTOFF
A9: Compra | B9: OC-898 | C9: 29/12/2024 | D9: 29/12/2024 | E9: Producto B | F9: 280 | G9: 12000000 | H9: 2024 | I9: 2024 | J9: =IF(H9<>I9,"ALTO","BAJO") -> BAJO | K9: =IF(J9="ALTO","🔴 ERROR CUTOFF","✓ CORRECTO") -> ✓ CORRECTO
A10: Compra | B10: OC-899 | C10: 30/12/2024 | D10: 03/01/2025 | E10: Componente C | F10: 820 | G10: 25000000 | H10: 2025 | I10: 2024 | J10: =IF(H10<>I10,"ALTO","BAJO") -> ALTO | K10: =IF(J10="ALTO","🔴 ERROR CUTOFF","✓ CORRECTO") -> 🔴 ERROR CUTOFF
A11: Venta | B11: FV-1205 | C11: 31/12/2024 | D11: 31/12/2024 | E11: Producto D | F11: 350 | G11: 35000000 | H11: 2024 | I11: 2024 | J11: =IF(H11<>I11,"ALTO","BAJO") -> BAJO | K11: =IF(J11="ALTO","🔴 ERROR CUTOFF","✓ CORRECTO") -> ✓ CORRECTO
A12: Venta | B12: FV-1206 | C12: 31/12/2024 | D12: 04/01/2025 | E12: Material E | F12: 180 | G12: 22000000 | H12: 2024 | I12: 2024 | J12: =IF(H12<>I12,"ALTO","BAJO") -> BAJO | K12: =IF(J12="ALTO","🔴 ERROR CUTOFF","✓ CORRECTO") -> ✓ CORRECTO
A13: Compra | B13: OC-901 | C13: 02/01/2025 | D13: 02/01/2025 | E13: Producto F | F13: 520 | G13: 28000000 | H13: 2025 | I13: 2025 | J13: =IF(H13<>I13,"ALTO","BAJO") -> BAJO | K13: =IF(J13="ALTO","🔴 ERROR CUTOFF","✓ CORRECTO") -> ✓ CORRECTO
A14: Compra | B14: OC-902 | C14: 03/01/2025 | D14: 03/01/2025 | E14: Material G | F14: 380 | G14: 15000000 | H14: 2025 | I14: 2025 | J14: =IF(H14<>I14,"ALTO","BAJO") -> BAJO | K14: =IF(J14="ALTO","🔴 ERROR CUTOFF","✓ CORRECTO") -> ✓ CORRECTO
A15: Venta | B15: FV-1208 | C15: 02/01/2025 | D15: 02/01/2025 | E15: Componente H | F15: 240 | G15: 18500000 | H15: 2025 | I15: 2025 | J15: =IF(H15<>I15,"ALTO","BAJO") -> BAJO | K15: =IF(J15="ALTO","🔴 ERROR CUTOFF","✓ CORRECTO") -> ✓ CORRECTO
A16: Venta | B16: FV-1209 | C16: 03/01/2025 | D16: 03/01/2025 | E16: Producto I | F16: 420 | G16: 32000000 | H16: 2025 | I16: 2025 | J16: =IF(H16<>I16,"ALTO","BAJO") -> BAJO | K16: =IF(J16="ALTO","🔴 ERROR CUTOFF","✓ CORRECTO") -> ✓ CORRECTO
A17: Compra | B17: OC-905 | C17: 04/01/2025 | D17: 04/01/2025 | E17: Material J | F17: 680 | G17: 19500000 | H17: 2025 | I17: 2025 | J17: =IF(H17<>I17,"ALTO","BAJO") -> BAJO | K17: =IF(J17="ALTO","🔴 ERROR CUTOFF","✓ CORRECTO") -> ✓ CORRECTO
A19: EVALUACIÓN DE CUT-OFF
A20: Transacciones revisadas: | B20: =COUNTA(A8:A17) -> 10 | I20: RIESGO GLOBAL: | J20: =IF(B21>2,"ALTO",IF(B21>0,"MEDIO","BAJO")) -> MEDIO
A21: Errores de cut-off: | B21: =COUNTIF(J8:J17,"ALTO") -> 2
A22: Monto registrado en período incorrecto: | B22: =SUMIF(J8:J17,"ALTO",G8:G17) -> 43500000
A23: Ajustes de período requeridos: | B23: =B21 -> 2
D24: =B22 -> 43500000

Sheet PT_C.7_MargenBruto
A1: PT C.7 - ANÁLISIS DE MARGEN BRUTO POR LÍNEA DE PRODUCTO
A2: Detección de Desviaciones | Objetivo: Identificar manipulación de costos o precios
A4: Período: | B4: 2024
A7: Línea Producto | B7: Ventas | C7: Costo Ventas | D7: Margen Bruto $ | E7: Margen Bruto % | F7: Margen Esperado % | G7: Variación | H7: % Variación | I7: Riesgo | J7: Estado | K7: Acción
A8: Electrónicos | B8: 850000000 | C8: 510000000 | D8: =B8-C8 -> 340000000 | E8: =IF(B8=0,0,D8/B8) -> 0.4 | F8: 0.4 | G8: =E8-F8 -> 0 | H8: =IF(F8=0,0,G8/F8) -> 0 | I8: =IF(ABS(H8)>0.4,"CRÍTICO",IF(ABS(H8)>0.25,"ALTO",IF(ABS(H8)>0.1,"MEDIO","BAJO"))) -> BAJO | J8: =IF(I8="CRÍTICO","🚨 ANÓMALO",IF(I8="ALTO","🔴 DESVIACIÓN",IF(I8="MEDIO","⚠ REVISAR","✓ NORMAL"))) -> ✓ NORMAL | K8: =IF(I8="CRÍTICO","Investigar fraude",IF(I8="ALTO","Analizar causas","Monitoreo")) -> Monitoreo
A9: Línea Blanca | B9: 620000000 | C9: 496000000 | D9: =B9-C9 -> 124000000 | E9: =IF(B9=0,0,D9/B9) -> 0.2 | F9: 0.2 | G9: =E9-F9 -> 0 | H9: =IF(F9=0,0,G9/F9) -> 0 | I9: =IF(ABS(H9)>0.4,"CRÍTICO",IF(ABS(H9)>0.25,"ALTO",IF(ABS(H9)>0.1,"MEDIO","BAJO"))) -> BAJO | J9: =IF(I9="CRÍTICO","🚨 ANÓMALO",IF(I9="ALTO","🔴 DESVIACIÓN",IF(I9="MEDIO","⚠ REVISAR","✓ NORMAL"))) -> ✓ NORMAL | K9: =IF(I9="CRÍTICO","Investigar fraude",IF(I9="ALTO","Analizar causas","Monitoreo")) -> Monitoreo
A10: Computadores | B10: 1200000000 | C10: 720000000 | D10: =B10-C10 -> 480000000 | E10: =IF(B10=0,0,D10/B10) -> 0.4 | F10: 0.4 | G10: =E10-F10 -> 0 | H10: =IF(F10=0,0,G10/F10) -> 0 | I10: =IF(ABS(H10)>0.4,"CRÍTICO",IF(ABS(H10)>0.25,"ALTO",IF(ABS(H10)>0.1,"MEDIO","BAJO"))) -> BAJO | J10: =IF(I10="CRÍTICO","🚨 ANÓMALO",IF(I10="ALTO","🔴 DESVIACIÓN",IF(I10="MEDIO","⚠ REVISAR","✓ NORMAL"))) -> ✓ NORMAL | K10: =IF(I10="CRÍTICO","Investigar fraude",IF(I10="ALTO","Analizar causas","Monitoreo")) -> Monitoreo
A11: Accesorios | B11: 380000000 | C11: 342000000 | D11: =B11-C11 -> 38000000 | E11: =IF(B11=0,0,D11/B11) -> 0.1 | F11: 0.1 | G11: =E11-F11 -> 0 | H11: =IF(F11=0,0,G11/F11) -> 0 | I11: =IF(ABS(H11)>0.4,"CRÍTICO",IF(ABS(H11)>0.25,"ALTO",IF(ABS(H11)>0.1,"MEDIO","BAJO"))) -> BAJO | J11: =IF(I11="CRÍTICO","🚨 ANÓMALO",IF(I11="ALTO","🔴 DESVIACIÓN",IF(I11="MEDIO","⚠ REVISAR","✓ NORMAL"))) -> ✓ NORMAL | K11: =IF(I11="CRÍTICO","Investigar fraude",IF(I11="ALTO","Analizar causas","Monitoreo")) -> Monitoreo
A12: Componentes | B12: 550000000 | C12: 357500000 | D12: =B12-C12 -> 192500000 | E12: =IF(B12=0,0,D12/B12) -> 0.35 | F12: 0.35 | G12: =E12-F12 -> 0 | H12: =IF(F12=0,0,G12/F12) -> 0 | I12: =IF(ABS(H12)>0.4,"CRÍTICO",IF(ABS(H12)>0.25,"ALTO",IF(ABS(H12)>0.1,"MEDIO","BAJO"))) -> BAJO | J12: =IF(I12="CRÍTICO","🚨 ANÓMALO",IF(I12="ALTO","🔴 DESVIACIÓN",IF(I12="MEDIO","⚠ REVISAR","✓ NORMAL"))) -> ✓ NORMAL | K12: =IF(I12="CRÍTICO","Investigar fraude",IF(I12="ALTO","Analizar causas","Monitoreo")) -> Monitoreo
A13: Herramientas | B13: 420000000 | C13: 336000000 | D13: =B13-C13 -> 84000000 | E13: =IF(B13=0,0,D13/B13) -> 0.2 | F13: 0.2 | G13: =E13-F13 -> 0 | H13: =IF(F13=0,0,G13/F13) -> 0 | I13: =IF(ABS(H13)>0.4,"CRÍTICO",IF(ABS(H13)>0.25,"ALTO",IF(ABS(H13)>0.1,"MEDIO","BAJO"))) -> BAJO | J13: =IF(I13="CRÍTICO","🚨 ANÓMALO",IF(I13="ALTO","🔴 DESVIACIÓN",IF(I13="MEDIO","⚠ REVISAR","✓ NORMAL"))) -> ✓ NORMAL | K13: =IF(I13="CRÍTICO","Investigar fraude",IF(I13="ALTO","Analizar causas","Monitoreo")) -> Monitoreo
A15: ANÁLISIS DE RENTABILIDAD
A16: Margen promedio general: | B16: =SUM(D8:D13)/SUM(B8:B13) -> 0.3130597
A17: Líneas con desviación crítica: | B17: =COUNTIF(I8:I13,"CRÍTICO")+COUNTIF(I8:I13,"ALTO") -> 0 | I17: RIESGO GLOBAL: | J17: =IF(COUNTIF(I8:I13,"CRÍTICO")>0,"ALTO",IF(B17>2,"MEDIO","BAJO")) -> BAJO
A18: Impacto estimado en utilidad: | B18: =SUMPRODUCT((E8:E13-F8:F13),B8:B13) -> 0
A24: Líneas que requieren investigación: | B24: =B17 -> 0
D25: =ABS(B18) -> 0

Sheet PT_C.8_EnTransito
A1: PT C.8 - INVENTARIO EN TRÁNSITO
A2: Existencia y Valuación | Objetivo: Verificar inventario en tránsito y su registro
A4: Fecha de corte: | B4: 31/12/2024
A7: Orden Compra | B7: Proveedor | C7: Producto | D7: Valor | E7: Fecha Envío | F7: Fecha Est. Llegada | G7: Días en Tránsito | H7: Registrado | I7: Riesgo | J7: Estado
A8: OC-875 | B8: Importadora A | C8: Material X | D8: 45000000 | E8: 15/12/2024 | F8: 05/01/2025 | G8: =$B$4-E8 -> 16 | H8: SÍ | I8: =IF(H8="NO","ALTO","BAJO") -> BAJO | J8: =IF(I8="ALTO","🔴 NO REGISTRADO","✓ REGISTRADO") -> ✓ REGISTRADO
A9: OC-882 | B9: Proveedor B | C9: Componente Y | D9: 28000000 | E9: 20/12/2024 | F9: 02/01/2025 | G9: =$B$4-E9 -> 11 | H9: NO | I9: =IF(H9="NO","ALTO","BAJO") -> ALTO | J9: =IF(I9="ALTO","🔴 NO REGISTRADO","✓ REGISTRADO") -> 🔴 NO REGISTRADO
A10: OC-889 | B10: Importadora C | C10: Producto Z | D10: 82000000 | E10: 10/12/2024 | F10: 03/01/2025 | G10: =$B$4-E10 -> 21 | H10: SÍ | I10: =IF(H10="NO","ALTO","BAJO") -> BAJO | J10: =IF(I10="ALTO","🔴 NO REGISTRADO","✓ REGISTRADO") -> ✓ REGISTRADO
A11: OC-894 | B11: Proveedor D | C11: Material W | D11: 35000000 | E11: 28/12/2024 | F11: 08/01/2025 | G11: =$B$4-E11 -> 3 | H11: NO | I11: =IF(H11="NO","ALTO","BAJO") -> ALTO | J11: =IF(I11="ALTO","🔴 NO REGISTRADO","✓ REGISTRADO") -> 🔴 NO REGISTRADO
A12: OC-901 | B12: Importadora E | C12: Componente V | D12: 52000000 | E12: 22/12/2024 | F12: 06/01/2025 | G12: =$B$4-E12 -> 9 | H12: SÍ | I12: =IF(H12="NO","ALTO","BAJO") -> BAJO | J12: =IF(I12="ALTO","🔴 NO REGISTRADO","✓ REGISTRADO") -> ✓ REGISTRADO
A14: EVALUACIÓN INVENTARIO EN TRÁNSITO
A15: Total inventario en tránsito: | B15: =SUM(D8:D12) -> 242000000
A16: Inventario NO registrado: | B16: =SUMIF(H8:H12,"NO",D8:D12) -> 63000000 | H16: RIESGO GLOBAL: | I16: =IF(B16/B15>0.3,"ALTO",IF(B16>0,"MEDIO","BAJO")) -> MEDIO
A21: Partidas sin registrar: | B21: =COUNTIF(H8:H12,"NO") -> 2
D22: =B16 -> 63000000

Sheet PT_C.9_Ajustes
A1: PT C.9 - AJUSTES DE INVENTARIO DURANTE EL PERÍODO
A2: Manipulación de Registros | Objetivo: Detectar ajustes inusuales que oculten faltantes
A4: Período: | B4: 2024
A7: Fecha | B7: N° Ajuste | C7: Producto | D7: Cantidad | E7: Valor Unitario | F7: Valor Total | G7: Justificación | H7: Autorizado | I7: Riesgo | J7: Estado
A8: 15/03/2024 | B8: AJ-001 | C8: Producto A | D8: -120 | E8: 185000 | F8: =ABS(D8)*E8 -> 22200000 | G8: Robo reportado | H8: SÍ | I8: =IF(H8="NO","CRÍTICO","BAJO") -> BAJO | J8: =IF(I8="CRÍTICO","⛔ SIN AUTORIZAR","✓ AUTORIZADO") -> ✓ AUTORIZADO
A9: 28/06/2024 | B9: AJ-002 | C9: Material B | D9: -850 | E9: 95000 | F9: =ABS(D9)*E9 -> 80750000 | G9: Diferencia inventario | H9: NO | I9: =IF(H9="NO","CRÍTICO","BAJO") -> CRÍTICO | J9: =IF(I9="CRÍTICO","⛔ SIN AUTORIZAR","✓ AUTORIZADO") -> ⛔ SIN AUTORIZAR
A10: 10/09/2024 | B10: AJ-003 | C10: Componente C | D10: 420 | E10: 125000 | F10: =ABS(D10)*E10 -> 52500000 | G10: Error conteo anterior | H10: SÍ | I10: =IF(H10="NO","CRÍTICO","BAJO") -> BAJO | J10: =IF(I10="CRÍTICO","⛔ SIN AUTORIZAR","✓ AUTORIZADO") -> ✓ AUTORIZADO
A11: 18/11/2024 | B11: AJ-004 | C11: Producto D | D11: -1250 | E11: 280000 | F11: =ABS(D11)*E11 -> 350000000 | G11: Ajuste fin año | H11: NO | I11: =IF(H11="NO","CRÍTICO","BAJO") -> CRÍTICO | J11: =IF(I11="CRÍTICO","⛔ SIN AUTORIZAR","✓ AUTORIZADO") -> ⛔ SIN AUTORIZAR
A12: 30/12/2024 | B12: AJ-005 | C12: Material E | D12: -680 | E12: 450000 | F12: =ABS(D12)*E12 -> 306000000 | G12: Obsolescencia | H12: SÍ | I12: =IF(H12="NO","CRÍTICO","BAJO") -> BAJO | J12: =IF(I12="CRÍTICO","⛔ SIN AUTORIZAR","✓ AUTORIZADO") -> ✓ AUTORIZADO
A14: ANÁLISIS DE AJUSTES
A15: Total ajustes revisados: | B15: =COUNTA(B8:B12) -> 5
A16: Ajustes sin autorización: | B16: =COUNTIF(H8:H12,"NO") -> 2 | H16: RIESGO GLOBAL: | I16: =IF(B16>0,"CRÍTICO","BAJO") -> CRÍTICO
A17: Valor ajustes no autorizados: | B17: =SUMIF(H8:H12,"NO",F8:F12) -> 430750000
A22: Ajustes sospechosos: | B22: =B16 -> 2 | C22: ajustes sin autorización adecuada
D23: =B17 -> 430750000

Sheet PT_C.10_Pignorado
A1: PT C.10 - INDAGACIÓN INVENTARIO PIGNORADO
A2: Restricciones No Reveladas | Objetivo: Identificar inventario con restricciones de propiedad
A4: Fecha de verificación: | B4: 31/12/2024
A7: Producto | B7: Cantidad | C7: Valor | D7: Entidad Financiera | E7: Tipo Garantía | F7: Revelado EEFF | G7: Vigencia | H7: Riesgo | I7: Estado | J7: Acción
A8: Producto A | B8: 1500 | C8: 125000000 | D8: Banco A | E8: Prenda | F8: NO | G8: 30/06/2025 | H8: =IF(AND(E8<>"N/A",F8="NO"),"ALTO","BAJO") -> ALTO | I8: =IF(H8="ALTO","🔴 NO REVELADO","✓ OK") -> 🔴 NO REVELADO | J8: =IF(H8="ALTO","Revelar en notas EEFF","Ninguna") -> Revelar en notas EEFF
A9: Material B | B9: 850 | C9: 62000000 | D9: Banco B | E9: Prenda | F9: SÍ | G9: 15/12/2025 | H9: =IF(AND(E9<>"N/A",F9="NO"),"ALTO","BAJO") -> BAJO | I9: =IF(H9="ALTO","🔴 NO REVELADO","✓ OK") -> ✓ OK | J9: =IF(H9="ALTO","Revelar en notas EEFF","Ninguna") -> Ninguna
A10: Componente C | B10: 2400 | C10: 185000000 | D10: Banco C | E10: Garantía | F10: NO | G10: 20/08/2025 | H10: =IF(AND(E10<>"N/A",F10="NO"),"ALTO","BAJO") -> ALTO | I10: =IF(H10="ALTO","🔴 NO REVELADO","✓ OK") -> 🔴 NO REVELADO | J10: =IF(H10="ALTO","Revelar en notas EEFF","Ninguna") -> Revelar en notas EEFF
A11: Producto D | B11: 680 | C11: 48000000 | D11: Sin garantía | E11: N/A | F11: N/A | G11: N/A | H11: =IF(AND(E11<>"N/A",F11="NO"),"ALTO","BAJO") -> BAJO | I11: =IF(H11="ALTO","🔴 NO REVELADO","✓ OK") -> ✓ OK | J11: =IF(H11="ALTO","Revelar en notas EEFF","Ninguna") -> Ninguna
A13: EVALUACIÓN DE RESTRICCIONES
A14: Inventario pignorado identificado: | B14: =COUNTIF(E8:E11,"<>N/A")-COUNTIF(E8:E11,"Sin garantía") -> 3
A15: Inventario pignorado NO revelado: | B15: =COUNTIFS(E8:E11,"<>N/A",F8:F11,"NO") -> 2
A16: Valor no revelado: | B16: =SUMIFS(C8:C11,E8:E11,"<>N/A",F8:F11,"NO") -> 310000000 | H16: RIESGO GLOBAL: | I16: =IF(B15>0,"ALTO","BAJO") -> ALTO
A20: Restricciones sin revelar: | B20: =B15 -> 2
D21: =B16 -> 310000000

Sheet PT_C.11_Variaciones
A1: PT C.11 - VARIACIONES DE CANTIDAD ENTRE CONTEOS FÍSICOS
A2: Confiabilidad del Conteo | Objetivo: Evaluar consistencia en procesos de conteo
A4: Fechas de conteo: | B4: Conteo 1: 15/12/2024 | Conteo 2: 31/12/2024
A7: Producto | B7: Conteo 1 (15 Dic) | C7: Conteo 2 (31 Dic) | D7: Variación | E7: % Variación | F7: Movtos Esperados | G7: Movtos Reales | H7: Diferencia | I7: Riesgo | J7: Estado | K7: Acción
A8: Producto A | B8: 1500 | C8: 1420 | D8: =C8-B8 -> -80 | E8: =IF(B8=0,0,D8/B8) -> -0.053333333 | F8: -80 | G8: =D8 -> -80 | H8: =G8-F8 -> 0 | I8: =IF(ABS(H8)>B8*0.1,"ALTO",IF(ABS(H8)>B8*0.05,"MEDIO","BAJO")) -> BAJO | J8: =IF(I8="ALTO","🔴 DISCREPANCIA",IF(I8="MEDIO","⚠ REVISAR","✓ NORMAL")) -> ✓ NORMAL | K8: =IF(I8="ALTO","Recontar inmediato",IF(I8="MEDIO","Verificar movimientos","Ninguna")) -> Ninguna
A9: Material B | B9: 850 | C9: 920 | D9: =C9-B9 -> 70 | E9: =IF(B9=0,0,D9/B9) -> 0.082352941 | F9: 70 | G9: =D9 -> 70 | H9: =G9-F9 -> 0 | I9: =IF(ABS(H9)>B9*0.1,"ALTO",IF(ABS(H9)>B9*0.05,"MEDIO","BAJO")) -> BAJO | J9: =IF(I9="ALTO","🔴 DISCREPANCIA",IF(I9="MEDIO","⚠ REVISAR","✓ NORMAL")) -> ✓ NORMAL | K9: =IF(I9="ALTO","Recontar inmediato",IF(I9="MEDIO","Verificar movimientos","Ninguna")) -> Ninguna
A10: Componente C | B10: 3200 | C10: 2800 | D10: =C10-B10 -> -400 | E10: =IF(B10=0,0,D10/B10) -> -0.125 | F10: -400 | G10: =D10 -> -400 | H10: =G10-F10 -> 0 | I10: =IF(ABS(H10)>B10*0.1,"ALTO",IF(ABS(H10)>B10*0.05,"MEDIO","BAJO")) -> BAJO | J10: =IF(I10="ALTO","🔴 DISCREPANCIA",IF(I10="MEDIO","⚠ REVISAR","✓ NORMAL")) -> ✓ NORMAL | K10: =IF(I10="ALTO","Recontar inmediato",IF(I10="MEDIO","Verificar movimientos","Ninguna")) -> Ninguna
A11: Producto D | B11: 2100 | C11: 2050 | D11: =C11-B11 -> -50 | E11: =IF(B11=0,0,D11/B11) -> -0.023809524 | F11: -50 | G11: =D11 -> -50 | H11: =G11-F11 -> 0 | I11: =IF(ABS(H11)>B11*0.1,"ALTO",IF(ABS(H11)>B11*0.05,"MEDIO","BAJO")) -> BAJO | J11: =IF(I11="ALTO","🔴 DISCREPANCIA",IF(I11="MEDIO","⚠ REVISAR","✓ NORMAL")) -> ✓ NORMAL | K11: =IF(I11="ALTO","Recontar inmediato",IF(I11="MEDIO","Verificar movimientos","Ninguna")) -> Ninguna
A12: Material E | B12: 4500 | C12: 4850 | D12: =C12-B12 -> 350 | E12: =IF(B12=0,0,D12/B12) -> 0.077777778 | F12: 350 | G12: =D12 -> 350 | H12: =G12-F12 -> 0 | I12: =IF(ABS(H12)>B12*0.1,"ALTO",IF(ABS(H12)>B12*0.05,"MEDIO","BAJO")) -> BAJO | J12: =IF(I12="ALTO","🔴 DISCREPANCIA",IF(I12="MEDIO","⚠ REVISAR","✓ NORMAL")) -> ✓ NORMAL | K12: =IF(I12="ALTO","Recontar inmediato",IF(I12="MEDIO","Verificar movimientos","Ninguna")) -> Ninguna
A13: Componente F | B13: 1800 | C13: 1780 | D13: =C13-B13 -> -20 | E13: =IF(B13=0,0,D13/B13) -> -0.011111111 | F13: -20 | G13: =D13 -> -20 | H13: =G13-F13 -> 0 | I13: =IF(ABS(H13)>B13*0.1,"ALTO",IF(ABS(H13)>B13*0.05,"MEDIO","BAJO")) -> BAJO | J13: =IF(I13="ALTO","🔴 DISCREPANCIA",IF(I13="MEDIO","⚠ REVISAR","✓ NORMAL")) -> ✓ NORMAL | K13: =IF(I13="ALTO","Recontar inmediato",IF(I13="MEDIO","Verificar movimientos","Ninguna")) -> Ninguna
A15: EVALUACIÓN DE CONFIABILIDAD
A16: Partidas contadas dos veces: | B16: =COUNTA(A8:A13) -> 6
A17: Partidas con discrepancias altas: | B17: =COUNTIF(I8:I13,"ALTO") -> 0 | I17: RIESGO GLOBAL: | J17: =IF(B18<0.8,"ALTO",IF(B18<0.9,"MEDIO","BAJO")) -> BAJO
A18: % de confiabilidad del conteo: | B18: =(B16-B17)/B16 -> 1
A24: Partidas que requieren reconteo: | B24: =B17 -> 0
D25: =B17 -> 0

Sheet PT_C.12_CostosVsMercado
A1: PT C.12 - COSTOS UNITARIOS VS MERCADO (PRUEBA NRV)
A2: Prueba de Valor Neto Realizable | Objetivo: Verificar valuación al menor entre costo y mercado
A4: Fecha de valoración: | B4: 31/12/2024
A7: Producto | B7: Cantidad | C7: Costo Unitario | D7: Precio Mercado | E7: Costo Total | F7: VNR Total | G7: Provisión Requerida | H7: Provisión Actual | I7: Diferencia | J7: Riesgo | K7: Estado
A8: Producto A | B8: 850 | C8: 185000 | D8: 195000 | E8: =B8*C8 -> 157250000 | F8: =B8*D8 -> 165750000 | G8: =MAX(E8-F8,0) -> 0 | H8: 0 | I8: =G8-H8 -> 0 | J8: =IF(I8>E8*0.15,"ALTO",IF(I8>0,"MEDIO","BAJO")) -> BAJO | K8: =IF(J8="ALTO","🔴 SUBVALUADO",IF(J8="MEDIO","⚠ AJUSTAR","✓ OK")) -> ✓ OK
A9: Material B | B9: 1200 | C9: 125000 | D9: 95000 | E9: =B9*C9 -> 150000000 | F9: =B9*D9 -> 114000000 | G9: =MAX(E9-F9,0) -> 36000000 | H9: 18000000 | I9: =G9-H9 -> 18000000 | J9: =IF(I9>E9*0.15,"ALTO",IF(I9>0,"MEDIO","BAJO")) -> MEDIO | K9: =IF(J9="ALTO","🔴 SUBVALUADO",IF(J9="MEDIO","⚠ AJUSTAR","✓ OK")) -> ⚠ AJUSTAR
A10: Componente C | B10: 3500 | C10: 68000 | D10: 72000 | E10: =B10*C10 -> 238000000 | F10: =B10*D10 -> 252000000 | G10: =MAX(E10-F10,0) -> 0 | H10: 0 | I10: =G10-H10 -> 0 | J10: =IF(I10>E10*0.15,"ALTO",IF(I10>0,"MEDIO","BAJO")) -> BAJO | K10: =IF(J10="ALTO","🔴 SUBVALUADO",IF(J10="MEDIO","⚠ AJUSTAR","✓ OK")) -> ✓ OK
A11: Producto D | B11: 420 | C11: 380000 | D11: 320000 | E11: =B11*C11 -> 159600000 | F11: =B11*D11 -> 134400000 | G11: =MAX(E11-F11,0) -> 25200000 | H11: 8400000 | I11: =G11-H11 -> 16800000 | J11: =IF(I11>E11*0.15,"ALTO",IF(I11>0,"MEDIO","BAJO")) -> MEDIO | K11: =IF(J11="ALTO","🔴 SUBVALUADO",IF(J11="MEDIO","⚠ AJUSTAR","✓ OK")) -> ⚠ AJUSTAR
A12: Material E | B12: 2800 | C12: 95000 | D12: 110000 | E12: =B12*C12 -> 266000000 | F12: =B12*D12 -> 308000000 | G12: =MAX(E12-F12,0) -> 0 | H12: 0 | I12: =G12-H12 -> 0 | J12: =IF(I12>E12*0.15,"ALTO",IF(I12>0,"MEDIO","BAJO")) -> BAJO | K12: =IF(J12="ALTO","🔴 SUBVALUADO",IF(J12="MEDIO","⚠ AJUSTAR","✓ OK")) -> ✓ OK
A13: Componente F | B13: 650 | C13: 220000 | D13: 180000 | E13: =B13*C13 -> 143000000 | F13: =B13*D13 -> 117000000 | G13: =MAX(E13-F13,0) -> 26000000 | H13: 13000000 | I13: =G13-H13 -> 13000000 | J13: =IF(I13>E13*0.15,"ALTO",IF(I13>0,"MEDIO","BAJO")) -> MEDIO | K13: =IF(J13="ALTO","🔴 SUBVALUADO",IF(J13="MEDIO","⚠ AJUSTAR","✓ OK")) -> ⚠ AJUSTAR
A15: PRUEBA DE VALOR NETO REALIZABLE
A16: Partidas con costo > mercado: | B16: =COUNTIF(G8:G13,">0") -> 3
A17: Provisión total requerida: | B17: =SUM(G8:G13) -> 87200000 | I17: RIESGO GLOBAL: | J17: =IF(B19>B17*0.3,"ALTO",IF(B19>0,"MEDIO","BAJO")) -> ALTO
A18: Provisión actual: | B18: =SUM(H8:H13) -> 39400000
A19: Provisión adicional necesaria: | B19: =SUM(I8:I13) -> 47800000
A24: Ajuste de valuación requerido: | B24: =B19 -> 47800000
D25: =B19 -> 47800000

Sheet PT_C.13_Fantasma
A1: PT C.13 - PRODUCTOS FANTASMA O DUPLICADOS EN SISTEMA
A2: Integridad de Registros | Objetivo: Detectar productos ficticios o códigos duplicados
A4: Fecha de análisis: | B4: 31/12/2024
A7: Código | B7: Descripción | C7: Cantidad Sistema | D7: Ubicación Sistema | E7: Existe Físicamente | F7: Duplicado de | G7: Valor | H7: Riesgo | I7: Estado | J7: Acción
A8: PRD-001 | B8: Producto A | C8: 500 | D8: Bodega 1 | E8: SÍ | G8: 185000000 | H8: =IF(E8="NO","CRÍTICO",IF(F8<>"","ALTO","BAJO")) -> BAJO | I8: =IF(H8="CRÍTICO","⛔ FANTASMA",IF(H8="ALTO","🔴 DUPLICADO","✓ OK")) -> ✓ OK | J8: =IF(H8="CRÍTICO","Eliminar del sistema",IF(H8="ALTO","Consolidar códigos","Ninguna")) -> Ninguna
A9: PRD-002 | B9: Material B | C9: 850 | D9: Bodega 2 | E9: NO | G9: 95000000 | H9: =IF(E9="NO","CRÍTICO",IF(F9<>"","ALTO","BAJO")) -> CRÍTICO | I9: =IF(H9="CRÍTICO","⛔ FANTASMA",IF(H9="ALTO","🔴 DUPLICADO","✓ OK")) -> ⛔ FANTASMA | J9: =IF(H9="CRÍTICO","Eliminar del sistema",IF(H9="ALTO","Consolidar códigos","Ninguna")) -> Eliminar del sistema
A10: PRD-002A | B10: Material B | C10: 850 | D10: Bodega 2 | E10: SÍ | F10: PRD-002 | G10: 95000000 | H10: =IF(E10="NO","CRÍTICO",IF(F10<>"","ALTO","BAJO")) -> ALTO | I10: =IF(H10="CRÍTICO","⛔ FANTASMA",IF(H10="ALTO","🔴 DUPLICADO","✓ OK")) -> 🔴 DUPLICADO | J10: =IF(H10="CRÍTICO","Eliminar del sistema",IF(H10="ALTO","Consolidar códigos","Ninguna")) -> Consolidar códigos
A11: PRD-003 | B11: Componente C | C11: 3200 | D11: Bodega 1 | E11: SÍ | G11: 145000000 | H11: =IF(E11="NO","CRÍTICO",IF(F11<>"","ALTO","BAJO")) -> BAJO | I11: =IF(H11="CRÍTICO","⛔ FANTASMA",IF(H11="ALTO","🔴 DUPLICADO","✓ OK")) -> ✓ OK | J11: =IF(H11="CRÍTICO","Eliminar del sistema",IF(H11="ALTO","Consolidar códigos","Ninguna")) -> Ninguna
A12: PRD-004 | B12: Producto D | C12: 420 | D12: Bodega 3 | E12: NO | G12: 125000000 | H12: =IF(E12="NO","CRÍTICO",IF(F12<>"","ALTO","BAJO")) -> CRÍTICO | I12: =IF(H12="CRÍTICO","⛔ FANTASMA",IF(H12="ALTO","🔴 DUPLICADO","✓ OK")) -> ⛔ FANTASMA | J12: =IF(H12="CRÍTICO","Eliminar del sistema",IF(H12="ALTO","Consolidar códigos","Ninguna")) -> Eliminar del sistema
A13: PRD-005 | B13: Material E | C13: 2800 | D13: Bodega 2 | E13: SÍ | G13: 185000000 | H13: =IF(E13="NO","CRÍTICO",IF(F13<>"","ALTO","BAJO")) -> BAJO | I13: =IF(H13="CRÍTICO","⛔ FANTASMA",IF(H13="ALTO","🔴 DUPLICADO","✓ OK")) -> ✓ OK | J13: =IF(H13="CRÍTICO","Eliminar del sistema",IF(H13="ALTO","Consolidar códigos","Ninguna")) -> Ninguna
A15: INTEGRIDAD DEL SISTEMA
A16: Productos fantasma detectados: | B16: =COUNTIF(E8:E13,"NO") -> 2 | H16: RIESGO GLOBAL: | I16: =IF(B16>0,"CRÍTICO",IF(B17>0,"ALTO","BAJO")) -> CRÍTICO
A17: Productos duplicados: | B17: =COUNTIF(F8:F13,"<>") -> 1
A18: Valor total productos fantasma: | B18: =SUMIF(E8:E13,"NO",G8:G13) -> 220000000
A21: Registros a depurar: | B21: =B16+B17 -> 3
D22: =B18 -> 220000000
