Workbook

Sheet ÍNDICE_GENERAL
A1: PROGRAMA DE AUDITORÍA - PROPIEDAD, PLANTA Y EQUIPO
A2: Basado en NIAs 500, 501, 540 y NIC 16 - Evidencia de Auditoría y Detección de Fraude en Activos Fijos
A4: Cliente: | B4: [NOMBRE DEL CLIENTE]
A5: Período auditado: | B5: 01/01/2024 - 31/12/2024
A6: Fecha de corte: | B6: 31/12/2024
A7: Auditor responsable: | B7: [NOMBRE DEL AUDITOR]
A9: REF | B9: PROCEDIMIENTO | C9: OBJETIVO NIC/NIA | D9: RIESGO | E9: ESTADO | F9: HALLAZGOS | G9: MATERIALIDAD | H9: RESPONSABLE | I9: FECHA
A10: PT D.1 | B10: Inspección Física Activos Alto Valor | C10: NIA 500 - Evidencia física | D10: =PT_D.1_InspeccionFisica!I18 -> 0 | E10: =PT_D.1_InspeccionFisica!J18 -> 0 | F10: =PT_D.1_InspeccionFisica!B25 -> 2 | G10: =PT_D.1_InspeccionFisica!D26 -> 480000000 | H10: [Auditor] | I10: =TODAY() -> 45978
A11: PT D.2 | B11: Adiciones - Autorización y Soporte | C11: Control de capitalizaciones | D11: =PT_D.2_Adiciones!H16 -> RIESGO GLOBAL: | E11: =PT_D.2_Adiciones!I16 -> CRÍTICO | F11: =PT_D.2_Adiciones!B22 -> 1 | G11: =PT_D.2_Adiciones!D23 -> 94000000 | H11: [Auditor] | I11: =TODAY() -> 45978
A12: PT D.3 | B12: Retiros/Bajas Sin Autorización | C12: NIA 240 - Fraude | D12: =PT_D.3_Retiros!H16 -> RIESGO GLOBAL: | E12: =PT_D.3_Retiros!I16 -> CRÍTICO | F12: =PT_D.3_Retiros!B21 -> 4 | G12: =PT_D.3_Retiros!D22 -> 26000000 | H12: [Auditor] | I12: =TODAY() -> 45978
A13: PT D.4 | B13: Certificados Tradición y Libertad | C13: Propiedad legal inmuebles | D13: =PT_D.4_Certificados!H16 -> RIESGO GLOBAL: | E13: =PT_D.4_Certificados!I16 -> CRÍTICO | F13: =PT_D.4_Certificados!B20 -> 2 | G13: =PT_D.4_Certificados!D21 -> 1500000000 | H13: [Auditor] | I13: =TODAY() -> 45978
A14: PT D.5 | B14: Depreciación - Inconsistencias | C14: NIC 16 - Cálculo correcto | D14: =PT_D.5_Depreciacion!I17 -> RIESGO GLOBAL: | E14: =PT_D.5_Depreciacion!J17 -> BAJO | F14: =PT_D.5_Depreciacion!B24 -> 0 | G14: =PT_D.5_Depreciacion!D25 -> 0.33333333 | H14: [Auditor] | I14: =TODAY() -> 45978
A15: PT D.6 | B15: Reparaciones vs Gasto | C15: Capitalización indebida | D15: =PT_D.6_Reparaciones!H16 -> RIESGO GLOBAL: | E15: =PT_D.6_Reparaciones!I16 -> ALTO | F15: =PT_D.6_Reparaciones!B22 -> 4 | G15: =PT_D.6_Reparaciones!D23 -> 26200000 | H15: [Auditor] | I15: =TODAY() -> 45978
A16: PT D.7 | B16: Activos Totalmente Depreciados | C16: Vida útil razonable | D16: =PT_D.7_TotalDepreciados!H16 -> RIESGO GLOBAL: | E16: =PT_D.7_TotalDepreciados!I16 -> MEDIO | F16: =PT_D.7_TotalDepreciados!B21 -> 4 | G16: =PT_D.7_TotalDepreciados!D22 -> 623000000 | H16: [Auditor] | I16: =TODAY() -> 45978
A17: PT D.8 | B17: Revaluaciones y Razonabilidad | C17: NIC 16 - Valor razonable | D17: =PT_D.8_Revaluaciones!H16 -> RIESGO GLOBAL: | E17: =PT_D.8_Revaluaciones!I16 -> CRÍTICO | F17: =PT_D.8_Revaluaciones!B21 -> 2 | G17: =PT_D.8_Revaluaciones!D22 -> 965000000 | H17: [Auditor] | I17: =TODAY() -> 45978
A18: PT D.9 | B18: Activos Arrendados Como Propios | C18: NIIF 16 - Clasificación | D18: =PT_D.9_Arrendados!H16 -> RIESGO GLOBAL: | E18: =PT_D.9_Arrendados!I16 -> CRÍTICO | F18: =PT_D.9_Arrendados!B21 -> 2 | G18: =PT_D.9_Arrendados!D22 -> 125000000 | H18: [Auditor] | I18: =TODAY() -> 45978
A19: PT D.10 | B19: Políticas Depreciación vs Industria | C19: Razonabilidad políticas | D19: =PT_D.10_Politicas!I17 -> RIESGO GLOBAL: | E19: =PT_D.10_Politicas!J17 -> ALTO | F19: =PT_D.10_Politicas!B23 -> 3 | G19: =PT_D.10_Politicas!D24 -> Impacto: Posible sobreestimación del gasto | H19: [Auditor] | I19: =TODAY() -> 45978
A20: PT D.11 | B20: Ganancias/Pérdidas en Ventas | C20: Cálculo correcto | D20: =PT_D.11_Ventas!I17 -> RIESGO GLOBAL: | E20: =PT_D.11_Ventas!J17 -> BAJO | F20: =PT_D.11_Ventas!B23 -> 0 | G20: =PT_D.11_Ventas!D24 -> 0 | H20: [Auditor] | I20: =TODAY() -> 45978
A21: PT D.12 | B21: Activos Inexistentes o Ficticios | C21: NIA 240 - Existencia | D21: =PT_D.12_Ficticios!H16 -> RIESGO GLOBAL: | E21: =PT_D.12_Ficticios!I16 -> CRÍTICO | F21: =PT_D.12_Ficticios!B21 -> 2 | G21: =PT_D.12_Ficticios!D22 -> 905000000 | H21: [Auditor] | I21: =TODAY() -> 45978

Sheet PT_D.1_InspeccionFisica
A1: PT D.1 - INSPECCIÓN FÍSICA DE ACTIVOS ALTO VALOR
A2: NIA 500 - Evidencia de Auditoría | Objetivo: Verificar existencia física de activos materiales
A4: Fecha de inspección: | B4: 31/12/2024
A7: Código Activo | B7: Descripción | C7: Ubicación Registro | D7: Valor Libros | E7: Ubicado Físicamente | F7: Estado Físico | G7: Placa/Serie Coincide | H7: En Uso | I7: Riesgo | J7: Estado | K7: Acción
A8: AF-001 | B8: Vehículo Toyota 2022 | C8: Oficina Principal | D8: 125000000 | E8: SÍ | F8: Bueno | G8: SÍ | H8: SÍ | I8: =IF(E8="NO","CRÍTICO",IF(G8="NO","ALTO",IF(AND(F8="Malo",H8="NO"),"MEDIO","BAJO"))) -> BAJO | J8: =IF(I8="CRÍTICO","⛔ NO UBICADO",IF(I8="ALTO","🔴 VERIFICAR",IF(I8="MEDIO","⚠ DETERIORADO","✓ OK"))) -> ✓ OK | K8: =IF(E8="NO","Investigar pérdida",IF(G8="NO","Verificar identidad",IF(F8="Malo","Evaluar deterioro","Ninguna"))) -> Ninguna
A9: AF-002 | B9: Maquinaria CNC | C9: Planta Producción | D9: 385000000 | E9: NO | F9: N/A | G9: N/A | H9: N/A | I9: =IF(E9="NO","CRÍTICO",IF(G9="NO","ALTO",IF(AND(F9="Malo",H9="NO"),"MEDIO","BAJO"))) -> CRÍTICO | J9: =IF(I9="CRÍTICO","⛔ NO UBICADO",IF(I9="ALTO","🔴 VERIFICAR",IF(I9="MEDIO","⚠ DETERIORADO","✓ OK"))) -> ⛔ NO UBICADO | K9: =IF(E9="NO","Investigar pérdida",IF(G9="NO","Verificar identidad",IF(F9="Malo","Evaluar deterioro","Ninguna"))) -> Investigar pérdida
A10: AF-003 | B10: Edificio Sede Norte | C10: Calle 100 #15-20 | D10: 2800000000 | E10: SÍ | F10: Bueno | G10: N/A | H10: SÍ | I10: =IF(E10="NO","CRÍTICO",IF(G10="NO","ALTO",IF(AND(F10="Malo",H10="NO"),"MEDIO","BAJO"))) -> BAJO | J10: =IF(I10="CRÍTICO","⛔ NO UBICADO",IF(I10="ALTO","🔴 VERIFICAR",IF(I10="MEDIO","⚠ DETERIORADO","✓ OK"))) -> ✓ OK | K10: =IF(E10="NO","Investigar pérdida",IF(G10="NO","Verificar identidad",IF(F10="Malo","Evaluar deterioro","Ninguna"))) -> Ninguna
A11: AF-004 | B11: Computadores (50) | C11: Oficinas | D11: 185000000 | E11: SÍ | F11: Regular | G11: SÍ | H11: SÍ | I11: =IF(E11="NO","CRÍTICO",IF(G11="NO","ALTO",IF(AND(F11="Malo",H11="NO"),"MEDIO","BAJO"))) -> BAJO | J11: =IF(I11="CRÍTICO","⛔ NO UBICADO",IF(I11="ALTO","🔴 VERIFICAR",IF(I11="MEDIO","⚠ DETERIORADO","✓ OK"))) -> ✓ OK | K11: =IF(E11="NO","Investigar pérdida",IF(G11="NO","Verificar identidad",IF(F11="Malo","Evaluar deterioro","Ninguna"))) -> Ninguna
A12: AF-005 | B12: Equipo Laboratorio | C12: Bodega 2 | D12: 520000000 | E12: SÍ | F12: Malo | G12: SÍ | H12: NO | I12: =IF(E12="NO","CRÍTICO",IF(G12="NO","ALTO",IF(AND(F12="Malo",H12="NO"),"MEDIO","BAJO"))) -> MEDIO | J12: =IF(I12="CRÍTICO","⛔ NO UBICADO",IF(I12="ALTO","🔴 VERIFICAR",IF(I12="MEDIO","⚠ DETERIORADO","✓ OK"))) -> ⚠ DETERIORADO | K12: =IF(E12="NO","Investigar pérdida",IF(G12="NO","Verificar identidad",IF(F12="Malo","Evaluar deterioro","Ninguna"))) -> Evaluar deterioro
A13: AF-006 | B13: Montacargas | C13: Bodega Principal | D13: 95000000 | E13: NO | F13: N/A | G13: N/A | H13: N/A | I13: =IF(E13="NO","CRÍTICO",IF(G13="NO","ALTO",IF(AND(F13="Malo",H13="NO"),"MEDIO","BAJO"))) -> CRÍTICO | J13: =IF(I13="CRÍTICO","⛔ NO UBICADO",IF(I13="ALTO","🔴 VERIFICAR",IF(I13="MEDIO","⚠ DETERIORADO","✓ OK"))) -> ⛔ NO UBICADO | K13: =IF(E13="NO","Investigar pérdida",IF(G13="NO","Verificar identidad",IF(F13="Malo","Evaluar deterioro","Ninguna"))) -> Investigar pérdida
A14: AF-007 | B14: Mobiliario Oficina | C14: Piso 3 | D14: 45000000 | E14: SÍ | F14: Bueno | G14: N/A | H14: SÍ | I14: =IF(E14="NO","CRÍTICO",IF(G14="NO","ALTO",IF(AND(F14="Malo",H14="NO"),"MEDIO","BAJO"))) -> BAJO | J14: =IF(I14="CRÍTICO","⛔ NO UBICADO",IF(I14="ALTO","🔴 VERIFICAR",IF(I14="MEDIO","⚠ DETERIORADO","✓ OK"))) -> ✓ OK | K14: =IF(E14="NO","Investigar pérdida",IF(G14="NO","Verificar identidad",IF(F14="Malo","Evaluar deterioro","Ninguna"))) -> Ninguna
A15: AF-008 | B15: Servidor Principal | C15: Datacenter | D15: 280000000 | E15: SÍ | F15: Bueno | G15: SÍ | H15: SÍ | I15: =IF(E15="NO","CRÍTICO",IF(G15="NO","ALTO",IF(AND(F15="Malo",H15="NO"),"MEDIO","BAJO"))) -> BAJO | J15: =IF(I15="CRÍTICO","⛔ NO UBICADO",IF(I15="ALTO","🔴 VERIFICAR",IF(I15="MEDIO","⚠ DETERIORADO","✓ OK"))) -> ✓ OK | K15: =IF(E15="NO","Investigar pérdida",IF(G15="NO","Verificar identidad",IF(F15="Malo","Evaluar deterioro","Ninguna"))) -> Ninguna
A16: AF-009 | B16: Equipo Médico | C16: Consultorio | D16: 425000000 | E16: SÍ | F16: Bueno | G16: NO | H16: SÍ | I16: =IF(E16="NO","CRÍTICO",IF(G16="NO","ALTO",IF(AND(F16="Malo",H16="NO"),"MEDIO","BAJO"))) -> ALTO | J16: =IF(I16="CRÍTICO","⛔ NO UBICADO",IF(I16="ALTO","🔴 VERIFICAR",IF(I16="MEDIO","⚠ DETERIORADO","✓ OK"))) -> 🔴 VERIFICAR | K16: =IF(E16="NO","Investigar pérdida",IF(G16="NO","Verificar identidad",IF(F16="Malo","Evaluar deterioro","Ninguna"))) -> Verificar identidad
A17: AF-010 | B17: Camión Carga | C17: Parqueadero | D17: 185000000 | E17: SÍ | F17: Regular | G17: SÍ | H17: SÍ | I17: =IF(E17="NO","CRÍTICO",IF(G17="NO","ALTO",IF(AND(F17="Malo",H17="NO"),"MEDIO","BAJO"))) -> BAJO | J17: =IF(I17="CRÍTICO","⛔ NO UBICADO",IF(I17="ALTO","🔴 VERIFICAR",IF(I17="MEDIO","⚠ DETERIORADO","✓ OK"))) -> ✓ OK | K17: =IF(E17="NO","Investigar pérdida",IF(G17="NO","Verificar identidad",IF(F17="Malo","Evaluar deterioro","Ninguna"))) -> Ninguna
A19: RESUMEN DE INSPECCIÓN FÍSICA
A20: Activos inspeccionados: | B20: =COUNTA(A8:A17) -> 10 | I20: RIESGO GLOBAL: | J20: =IF(B22>2,"CRÍTICO",IF(B22>0,"ALTO",IF(B24>0,"MEDIO","BAJO"))) -> ALTO
A21: Activos ubicados físicamente: | B21: =COUNTIF(E8:E17,"SÍ") -> 8
A22: Activos NO ubicados: | B22: =COUNTIF(E8:E17,"NO") -> 2
A23: Valor activos no ubicados: | B23: =SUMIF(E8:E17,"NO",D8:D17) -> 480000000
A24: Activos con placa/serie no coincide: | B24: =COUNTIF(G8:G17,"NO") -> 1
A25: Hallazgos críticos: | B25: =B22 -> 2 | C25: activos no ubicados físicamente
D26: =B23 -> 480000000

Sheet PT_D.2_Adiciones
A1: PT D.2 - ADICIONES - AUTORIZACIÓN Y DOCUMENTACIÓN SOPORTE
A2: Control de Capitalizaciones | Objetivo: Verificar que adiciones cumplan criterios NIC 16
A4: Período: | B4: 2024
A7: Fecha | B7: Descripción | C7: Valor | D7: Factura/ Soporte | E7: Autorizado | F7: Cumple Criterio | G7: Nivel Autor. Requerido | H7: Riesgo | I7: Estado | J7: Acción
A8: 15/03/2024 | B8: Vehículo nuevo | C8: 125000000 | D8: SÍ | E8: Gerente General | F8: SÍ | G8: Gerente General | H8: =IF(D8="NO","CRÍTICO",IF(E8<>G8,"ALTO",IF(F8="NO","MEDIO","BAJO"))) -> BAJO | I8: =IF(H8="CRÍTICO","⛔ SIN SOPORTE",IF(H8="ALTO","🔴 MAL AUTORIZADA",IF(H8="MEDIO","⚠ NO CUMPLE","✓ CORRECTA"))) -> ✓ CORRECTA | J8: =IF(D8="NO","Obtener soporte",IF(E8<>G8,"Obtener autorización","Verificar criterio")) -> Verificar criterio
A9: 22/05/2024 | B9: Reparación edificio | C9: 8500000 | D9: SÍ | E9: Contador | F9: NO | G9: Gerente General | H9: =IF(D9="NO","CRÍTICO",IF(E9<>G9,"ALTO",IF(F9="NO","MEDIO","BAJO"))) -> ALTO | I9: =IF(H9="CRÍTICO","⛔ SIN SOPORTE",IF(H9="ALTO","🔴 MAL AUTORIZADA",IF(H9="MEDIO","⚠ NO CUMPLE","✓ CORRECTA"))) -> 🔴 MAL AUTORIZADA | J9: =IF(D9="NO","Obtener soporte",IF(E9<>G9,"Obtener autorización","Verificar criterio")) -> Obtener autorización
A10: 10/07/2024 | B10: Maquinaria producción | C10: 385000000 | D10: SÍ | E10: Junta Directiva | F10: SÍ | G10: Junta Directiva | H10: =IF(D10="NO","CRÍTICO",IF(E10<>G10,"ALTO",IF(F10="NO","MEDIO","BAJO"))) -> BAJO | I10: =IF(H10="CRÍTICO","⛔ SIN SOPORTE",IF(H10="ALTO","🔴 MAL AUTORIZADA",IF(H10="MEDIO","⚠ NO CUMPLE","✓ CORRECTA"))) -> ✓ CORRECTA | J10: =IF(D10="NO","Obtener soporte",IF(E10<>G10,"Obtener autorización","Verificar criterio")) -> Verificar criterio
A11: 18/09/2024 | B11: Computadores | C11: 45000000 | D11: SÍ | E11: Gerente TI | F11: SÍ | G11: Gerente General | H11: =IF(D11="NO","CRÍTICO",IF(E11<>G11,"ALTO",IF(F11="NO","MEDIO","BAJO"))) -> ALTO | I11: =IF(H11="CRÍTICO","⛔ SIN SOPORTE",IF(H11="ALTO","🔴 MAL AUTORIZADA",IF(H11="MEDIO","⚠ NO CUMPLE","✓ CORRECTA"))) -> 🔴 MAL AUTORIZADA | J11: =IF(D11="NO","Obtener soporte",IF(E11<>G11,"Obtener autorización","Verificar criterio")) -> Obtener autorización
A12: 05/11/2024 | B12: Mejoras arrendamiento | C12: 28000000 | D12: NO | E12: Contador | F12: SÍ | G12: Gerente General | H12: =IF(D12="NO","CRÍTICO",IF(E12<>G12,"ALTO",IF(F12="NO","MEDIO","BAJO"))) -> CRÍTICO | I12: =IF(H12="CRÍTICO","⛔ SIN SOPORTE",IF(H12="ALTO","🔴 MAL AUTORIZADA",IF(H12="MEDIO","⚠ NO CUMPLE","✓ CORRECTA"))) -> ⛔ SIN SOPORTE | J12: =IF(D12="NO","Obtener soporte",IF(E12<>G12,"Obtener autorización","Verificar criterio")) -> Obtener soporte
A13: 20/12/2024 | B13: Equipo oficina | C13: 12500000 | D13: SÍ | E13: Gerente Operaciones | F13: SÍ | G13: Gerente General | H13: =IF(D13="NO","CRÍTICO",IF(E13<>G13,"ALTO",IF(F13="NO","MEDIO","BAJO"))) -> ALTO | I13: =IF(H13="CRÍTICO","⛔ SIN SOPORTE",IF(H13="ALTO","🔴 MAL AUTORIZADA",IF(H13="MEDIO","⚠ NO CUMPLE","✓ CORRECTA"))) -> 🔴 MAL AUTORIZADA | J13: =IF(D13="NO","Obtener soporte",IF(E13<>G13,"Obtener autorización","Verificar criterio")) -> Obtener autorización
A15: EVALUACIÓN DE ADICIONES
A16: Total adiciones revisadas: | B16: =COUNTA(A8:A13) -> 6 | H16: RIESGO GLOBAL: | I16: =IF(B17>0,"CRÍTICO",IF(B18>0,"ALTO","BAJO")) -> CRÍTICO
A17: Adiciones sin soporte: | B17: =COUNTIF(D8:D13,"NO") -> 1
A18: Adiciones mal autorizadas: | B18: =COUNTIFS(E8:E13,"<>"&G8:G13) -> 0
A19: Valor total con irregularidades: | B19: =SUMIF(H8:H13,"<>BAJO",C8:C13) -> 94000000
A22: Hallazgos: | B22: =B17+B18 -> 1 | C22: adiciones con problemas de control
D23: =B19 -> 94000000

Sheet PT_D.3_Retiros
A1: PT D.3 - RETIROS O BAJAS SIN AUTORIZACIÓN
A2: NIA 240 - Fraude | Objetivo: Detectar retiros no autorizados que oculten ventas o robos
A4: Período: | B4: 2024
A7: Fecha | B7: Código Activo | C7: Descripción | D7: Valor Neto | E7: Motivo Baja | F7: Autorizado Por | G7: Nivel Requerido | H7: Riesgo | I7: Estado | J7: Acción
A8: 15/04/2024 | B8: AF-125 | C8: Vehículo viejo | D8: 28000000 | E8: Venta | F8: Gerente General | G8: Gerente General | H8: =IF(F8<>G8,"CRÍTICO","BAJO") -> BAJO | I8: =IF(H8="CRÍTICO","⛔ SIN AUTORIZAR","✓ CORRECTO") -> ✓ CORRECTO | J8: =IF(H8="CRÍTICO","Obtener autorización adecuada","Ninguna") -> Ninguna
A9: 22/07/2024 | B9: AF-238 | C9: Maquinaria obsoleta | D9: 0 | E9: Obsolescencia | F9: Contador | G9: Gerente General | H9: =IF(F9<>G9,"CRÍTICO","BAJO") -> CRÍTICO | I9: =IF(H9="CRÍTICO","⛔ SIN AUTORIZAR","✓ CORRECTO") -> ⛔ SIN AUTORIZAR | J9: =IF(H9="CRÍTICO","Obtener autorización adecuada","Ninguna") -> Obtener autorización adecuada
A10: 10/09/2024 | B10: AF-156 | C10: Computadores | D10: 8500000 | E10: Robo | F10: Gerente TI | G10: Gerente General | H10: =IF(F10<>G10,"CRÍTICO","BAJO") -> CRÍTICO | I10: =IF(H10="CRÍTICO","⛔ SIN AUTORIZAR","✓ CORRECTO") -> ⛔ SIN AUTORIZAR | J10: =IF(H10="CRÍTICO","Obtener autorización adecuada","Ninguna") -> Obtener autorización adecuada
A11: 18/11/2024 | B11: AF-089 | C11: Equipo dañado | D11: 15000000 | E11: Daño total | F11: Contador | G11: Junta | H11: =IF(F11<>G11,"CRÍTICO","BAJO") -> CRÍTICO | I11: =IF(H11="CRÍTICO","⛔ SIN AUTORIZAR","✓ CORRECTO") -> ⛔ SIN AUTORIZAR | J11: =IF(H11="CRÍTICO","Obtener autorización adecuada","Ninguna") -> Obtener autorización adecuada
A12: 05/12/2024 | B12: AF-201 | C12: Mobiliario | D12: 2500000 | E12: Donación | F12: Gerente Admin | G12: Gerente General | H12: =IF(F12<>G12,"CRÍTICO","BAJO") -> CRÍTICO | I12: =IF(H12="CRÍTICO","⛔ SIN AUTORIZAR","✓ CORRECTO") -> ⛔ SIN AUTORIZAR | J12: =IF(H12="CRÍTICO","Obtener autorización adecuada","Ninguna") -> Obtener autorización adecuada
A14: EVALUACIÓN DE RETIROS Y BAJAS
A15: Retiros revisados: | B15: =COUNTA(B8:B12) -> 5
A16: Retiros sin autorización adecuada: | B16: =COUNTIF(H8:H12,"CRÍTICO") -> 4 | H16: RIESGO GLOBAL: | I16: =IF(B16>0,"CRÍTICO","BAJO") -> CRÍTICO
A17: Valor en riesgo: | B17: =SUMIF(H8:H12,"CRÍTICO",D8:D12) -> 26000000
A21: Bajas sospechosas: | B21: =B16 -> 4
D22: =B17 -> 26000000

Sheet PT_D.4_Certificados
A1: PT D.4 - CERTIFICADOS DE TRADICIÓN Y LIBERTAD (INMUEBLES)
A2: Propiedad Legal | Objetivo: Verificar titularidad de inmuebles
A4: Fecha de verificación: | B4: 31/12/2024
A7: Dirección | B7: Matrícula Inmobiliaria | C7: Valor Libros | D7: Certificado Obtenido | E7: Titular Registrado | F7: Gravámenes | G7: Vigencia Certificado | H7: Riesgo | I7: Estado | J7: Acción
A8: Calle 100 #15-20 | B8: 50C-123456 | C8: 2800000000 | D8: SÍ | E8: La Empresa S.A. | F8: Hipoteca Banco A | G8: 15/11/2024 | H8: =IF(D8="NO","CRÍTICO",IF(E8<>"La Empresa S.A.","ALTO","BAJO")) -> BAJO | I8: =IF(H8="CRÍTICO","⛔ SIN CERTIFICADO",IF(H8="ALTO","🔴 TITULAR INCORRECTO","✓ OK")) -> ✓ OK | J8: =IF(D8="NO","Obtener certificado",IF(E8<>"La Empresa S.A.","Verificar propiedad","Ninguna")) -> Ninguna
A9: Av. 68 #45-10 | B9: 50N-789012 | C9: 1500000000 | D9: NO | E9: N/A | F9: N/A | G9: N/A | H9: =IF(D9="NO","CRÍTICO",IF(E9<>"La Empresa S.A.","ALTO","BAJO")) -> CRÍTICO | I9: =IF(H9="CRÍTICO","⛔ SIN CERTIFICADO",IF(H9="ALTO","🔴 TITULAR INCORRECTO","✓ OK")) -> ⛔ SIN CERTIFICADO | J9: =IF(D9="NO","Obtener certificado",IF(E9<>"La Empresa S.A.","Verificar propiedad","Ninguna")) -> Obtener certificado
A10: Carrera 7 #80-50 | B10: 50C-345678 | C10: 3200000000 | D10: SÍ | E10: La Empresa S.A. | F10: Ninguno | G10: 20/12/2024 | H10: =IF(D10="NO","CRÍTICO",IF(E10<>"La Empresa S.A.","ALTO","BAJO")) -> BAJO | I10: =IF(H10="CRÍTICO","⛔ SIN CERTIFICADO",IF(H10="ALTO","🔴 TITULAR INCORRECTO","✓ OK")) -> ✓ OK | J10: =IF(D10="NO","Obtener certificado",IF(E10<>"La Empresa S.A.","Verificar propiedad","Ninguna")) -> Ninguna
A11: Bodega Km 5 | B11: 25H-901234 | C11: 850000000 | D11: SÍ | E11: Persona Natural | F11: Ninguno | G11: 10/10/2024 | H11: =IF(D11="NO","CRÍTICO",IF(E11<>"La Empresa S.A.","ALTO","BAJO")) -> ALTO | I11: =IF(H11="CRÍTICO","⛔ SIN CERTIFICADO",IF(H11="ALTO","🔴 TITULAR INCORRECTO","✓ OK")) -> 🔴 TITULAR INCORRECTO | J11: =IF(D11="NO","Obtener certificado",IF(E11<>"La Empresa S.A.","Verificar propiedad","Ninguna")) -> Verificar propiedad
A13: VERIFICACIÓN DE TITULARIDAD
A14: Inmuebles verificados: | B14: =COUNTA(A8:A11) -> 4
A15: Sin certificado actual: | B15: =COUNTIF(D8:D11,"NO") -> 1
A16: Valor inmuebles sin verificar: | B16: =SUMIF(D8:D11,"NO",C8:C11) -> 1500000000 | H16: RIESGO GLOBAL: | I16: =IF(B15>0,"CRÍTICO",IF(COUNTIF(H8:H11,"ALTO")>0,"ALTO","BAJO")) -> CRÍTICO
A20: Inmuebles con problemas: | B20: =COUNTIF(H8:H11,"<>BAJO") -> 2
D21: =B16 -> 1500000000

Sheet PT_D.5_Depreciacion
A1: PT D.5 - DEPRECIACIÓN ACUMULADA - INCONSISTENCIAS
A2: NIC 16 - Cálculo Correcto | Objetivo: Verificar exactitud del cálculo de depreciación
A4: Año fiscal: | B4: 2024
A7: Activo | B7: Costo | C7: Vida Útil | D7: Método | E7: Depr. Calculada | F7: Depr. Registrada | G7: Diferencia | H7: % Dif | I7: Riesgo | J7: Estado | K7: Acción
A8: Vehículo A | B8: 125000000 | C8: 5 | D8: Línea recta | E8: =B8/C8 -> 25000000 | F8: 25000000 | G8: =E8-F8 -> 0 | H8: =IF(E8=0,0,ABS(G8/E8)) -> 0 | I8: =IF(H8>0.15,"ALTO",IF(H8>0.05,"MEDIO","BAJO")) -> BAJO | J8: =IF(I8="ALTO","🔴 ERROR",IF(I8="MEDIO","⚠ REVISAR","✓ OK")) -> ✓ OK | K8: =IF(I8="ALTO","Ajustar depreciación",IF(I8="MEDIO","Verificar cálculo","Ninguna")) -> Ninguna
A9: Maquinaria B | B9: 385000000 | C9: 10 | D9: Línea recta | E9: =B9/C9 -> 38500000 | F9: 38500000 | G9: =E9-F9 -> 0 | H9: =IF(E9=0,0,ABS(G9/E9)) -> 0 | I9: =IF(H9>0.15,"ALTO",IF(H9>0.05,"MEDIO","BAJO")) -> BAJO | J9: =IF(I9="ALTO","🔴 ERROR",IF(I9="MEDIO","⚠ REVISAR","✓ OK")) -> ✓ OK | K9: =IF(I9="ALTO","Ajustar depreciación",IF(I9="MEDIO","Verificar cálculo","Ninguna")) -> Ninguna
A10: Edificio C | B10: 2800000000 | C10: 40 | D10: Línea recta | E10: =B10/C10 -> 70000000 | F10: 70000000 | G10: =E10-F10 -> 0 | H10: =IF(E10=0,0,ABS(G10/E10)) -> 0 | I10: =IF(H10>0.15,"ALTO",IF(H10>0.05,"MEDIO","BAJO")) -> BAJO | J10: =IF(I10="ALTO","🔴 ERROR",IF(I10="MEDIO","⚠ REVISAR","✓ OK")) -> ✓ OK | K10: =IF(I10="ALTO","Ajustar depreciación",IF(I10="MEDIO","Verificar cálculo","Ninguna")) -> Ninguna
A11: Equipo D | B11: 95000000 | C11: 8 | D11: Línea recta | E11: =B11/C11 -> 11875000 | F11: 11875000 | G11: =E11-F11 -> 0 | H11: =IF(E11=0,0,ABS(G11/E11)) -> 0 | I11: =IF(H11>0.15,"ALTO",IF(H11>0.05,"MEDIO","BAJO")) -> BAJO | J11: =IF(I11="ALTO","🔴 ERROR",IF(I11="MEDIO","⚠ REVISAR","✓ OK")) -> ✓ OK | K11: =IF(I11="ALTO","Ajustar depreciación",IF(I11="MEDIO","Verificar cálculo","Ninguna")) -> Ninguna
A12: Mobiliario E | B12: 45000000 | C12: 10 | D12: Línea recta | E12: =B12/C12 -> 4500000 | F12: 4500000 | G12: =E12-F12 -> 0 | H12: =IF(E12=0,0,ABS(G12/E12)) -> 0 | I12: =IF(H12>0.15,"ALTO",IF(H12>0.05,"MEDIO","BAJO")) -> BAJO | J12: =IF(I12="ALTO","🔴 ERROR",IF(I12="MEDIO","⚠ REVISAR","✓ OK")) -> ✓ OK | K12: =IF(I12="ALTO","Ajustar depreciación",IF(I12="MEDIO","Verificar cálculo","Ninguna")) -> Ninguna
A13: Computadores F | B13: 85000000 | C13: 3 | D13: Línea recta | E13: =B13/C13 -> 28333333 | F13: 28333333 | G13: =E13-F13 -> 0.33333333 | H13: =IF(E13=0,0,ABS(G13/E13)) -> 1.1764706e-08 | I13: =IF(H13>0.15,"ALTO",IF(H13>0.05,"MEDIO","BAJO")) -> BAJO | J13: =IF(I13="ALTO","🔴 ERROR",IF(I13="MEDIO","⚠ REVISAR","✓ OK")) -> ✓ OK | K13: =IF(I13="ALTO","Ajustar depreciación",IF(I13="MEDIO","Verificar cálculo","Ninguna")) -> Ninguna
A15: EVALUACIÓN DE DEPRECIACIÓN
A16: Activos revisados: | B16: =COUNTA(A8:A13) -> 6
A17: Con diferencias materiales: | B17: =COUNTIF(I8:I13,"<>BAJO") -> 0 | I17: RIESGO GLOBAL: | J17: =IF(B17>2,"ALTO",IF(B17>0,"MEDIO","BAJO")) -> BAJO
A18: Diferencia total depreciación: | B18: =SUM(G8:G13) -> 0.33333333
A19: Impacto en resultado: | B19: =ABS(B18) -> 0.33333333
A24: Ajustes requeridos: | B24: =B17 -> 0
D25: =B19 -> 0.33333333

Sheet PT_D.6_Reparaciones
A1: PT D.6 - REPARACIONES CAPITALIZADAS VS GASTO
A2: Capitalización Indebida | Objetivo: Detectar gastos capitalizados incorrectamente
A4: Período: | B4: 2024
A7: Fecha | B7: Descripción | C7: Monto | D7: Activo | E7: Tratamiento | F7: Extiende Vida Útil | G7: Aumenta Capacidad | H7: Riesgo | I7: Estado | J7: Acción
A8: 15/02/2024 | B8: Repuestos vehículo | C8: 2500000 | D8: Vehículo A | E8: Capitalizado | F8: NO | G8: NO | H8: =IF(AND(E8="Capitalizado",F8="NO",G8="NO"),"ALTO","BAJO") -> ALTO | I8: =IF(H8="ALTO","🔴 MAL CAPITALIZADO","✓ CORRECTO") -> 🔴 MAL CAPITALIZADO | J8: =IF(H8="ALTO","Reclasificar a gasto","Ninguna") -> Reclasificar a gasto
A9: 20/04/2024 | B9: Mejora edificio nuevo piso | C9: 185000000 | D9: Edificio | E9: Capitalizado | F9: SÍ | G9: SÍ | H9: =IF(AND(E9="Capitalizado",F9="NO",G9="NO"),"ALTO","BAJO") -> BAJO | I9: =IF(H9="ALTO","🔴 MAL CAPITALIZADO","✓ CORRECTO") -> ✓ CORRECTO | J9: =IF(H9="ALTO","Reclasificar a gasto","Ninguna") -> Ninguna
A10: 10/06/2024 | B10: Mantenimiento maquinaria | C10: 8500000 | D10: Maquinaria B | E10: Capitalizado | F10: NO | G10: NO | H10: =IF(AND(E10="Capitalizado",F10="NO",G10="NO"),"ALTO","BAJO") -> ALTO | I10: =IF(H10="ALTO","🔴 MAL CAPITALIZADO","✓ CORRECTO") -> 🔴 MAL CAPITALIZADO | J10: =IF(H10="ALTO","Reclasificar a gasto","Ninguna") -> Reclasificar a gasto
A11: 15/08/2024 | B11: Pintura oficinas | C11: 12000000 | D11: Edificio | E11: Capitalizado | F11: NO | G11: NO | H11: =IF(AND(E11="Capitalizado",F11="NO",G11="NO"),"ALTO","BAJO") -> ALTO | I11: =IF(H11="ALTO","🔴 MAL CAPITALIZADO","✓ CORRECTO") -> 🔴 MAL CAPITALIZADO | J11: =IF(H11="ALTO","Reclasificar a gasto","Ninguna") -> Reclasificar a gasto
A12: 20/10/2024 | B12: Actualización software equipo | C12: 45000000 | D12: Equipo C | E12: Capitalizado | F12: SÍ | G12: SÍ | H12: =IF(AND(E12="Capitalizado",F12="NO",G12="NO"),"ALTO","BAJO") -> BAJO | I12: =IF(H12="ALTO","🔴 MAL CAPITALIZADO","✓ CORRECTO") -> ✓ CORRECTO | J12: =IF(H12="ALTO","Reclasificar a gasto","Ninguna") -> Ninguna
A13: 05/12/2024 | B13: Cambio llantas | C13: 3200000 | D13: Vehículo B | E13: Capitalizado | F13: NO | G13: NO | H13: =IF(AND(E13="Capitalizado",F13="NO",G13="NO"),"ALTO","BAJO") -> ALTO | I13: =IF(H13="ALTO","🔴 MAL CAPITALIZADO","✓ CORRECTO") -> 🔴 MAL CAPITALIZADO | J13: =IF(H13="ALTO","Reclasificar a gasto","Ninguna") -> Reclasificar a gasto
A15: EVALUACIÓN DE CAPITALIZACIONES
A16: Reparaciones revisadas: | B16: =COUNTA(A8:A13) -> 6 | H16: RIESGO GLOBAL: | I16: =IF(B17>2,"ALTO",IF(B17>0,"MEDIO","BAJO")) -> ALTO
A17: Mal capitalizadas: | B17: =COUNTIF(H8:H13,"ALTO") -> 4
A18: Monto a reclasificar como gasto: | B18: =SUMIF(H8:H13,"ALTO",C8:C13) -> 26200000
A19: Impacto en utilidad: | B19: =-B18 -> -26200000
A22: Ajustes requeridos: | B22: =B17 -> 4 | C22: capitalizaciones incorrectas
D23: =B18 -> 26200000

Sheet PT_D.7_TotalDepreciados
A1: PT D.7 - ACTIVOS TOTALMENTE DEPRECIADOS AÚN EN USO
A2: Vida Útil Razonable | Objetivo: Identificar vida útil subestimada
A4: Fecha de análisis: | B4: 31/12/2024
A7: Activo | B7: Costo Original | C7: Depr. Acumulada | D7: Valor Neto | E7: Años Depreciados | F7: Vida Útil Asignada | G7: Aún en Uso | H7: Riesgo | I7: Estado | J7: Acción
A8: Vehículo antiguo | B8: 85000000 | C8: 85000000 | D8: =B8-C8 -> 0 | E8: 5 | F8: 5 | G8: SÍ | H8: =IF(AND(D8=0,G8="SÍ"),"MEDIO","BAJO") -> MEDIO | I8: =IF(H8="MEDIO","⚠ REVISAR VIDA","✓ OK") -> ⚠ REVISAR VIDA | J8: =IF(H8="MEDIO","Reevaluar vida útil","Ninguna") -> Reevaluar vida útil
A9: Maquinaria A | B9: 385000000 | C9: 385000000 | D9: =B9-C9 -> 0 | E9: 10 | F9: 10 | G9: SÍ | H9: =IF(AND(D9=0,G9="SÍ"),"MEDIO","BAJO") -> MEDIO | I9: =IF(H9="MEDIO","⚠ REVISAR VIDA","✓ OK") -> ⚠ REVISAR VIDA | J9: =IF(H9="MEDIO","Reevaluar vida útil","Ninguna") -> Reevaluar vida útil
A10: Computadores viejos | B10: 45000000 | C10: 45000000 | D10: =B10-C10 -> 0 | E10: 3 | F10: 3 | G10: NO | H10: =IF(AND(D10=0,G10="SÍ"),"MEDIO","BAJO") -> BAJO | I10: =IF(H10="MEDIO","⚠ REVISAR VIDA","✓ OK") -> ✓ OK | J10: =IF(H10="MEDIO","Reevaluar vida útil","Ninguna") -> Ninguna
A11: Equipo producción | B11: 125000000 | C11: 125000000 | D11: =B11-C11 -> 0 | E11: 8 | F11: 8 | G11: SÍ | H11: =IF(AND(D11=0,G11="SÍ"),"MEDIO","BAJO") -> MEDIO | I11: =IF(H11="MEDIO","⚠ REVISAR VIDA","✓ OK") -> ⚠ REVISAR VIDA | J11: =IF(H11="MEDIO","Reevaluar vida útil","Ninguna") -> Reevaluar vida útil
A12: Mobiliario | B12: 28000000 | C12: 28000000 | D12: =B12-C12 -> 0 | E12: 10 | F12: 10 | G12: SÍ | H12: =IF(AND(D12=0,G12="SÍ"),"MEDIO","BAJO") -> MEDIO | I12: =IF(H12="MEDIO","⚠ REVISAR VIDA","✓ OK") -> ⚠ REVISAR VIDA | J12: =IF(H12="MEDIO","Reevaluar vida útil","Ninguna") -> Reevaluar vida útil
A14: ANÁLISIS DE VIDA ÚTIL
A15: Activos totalmente depreciados: | B15: =COUNTIF(D8:D12,0) -> 5
A16: Totalmente depreciados y en uso: | B16: =COUNTIFS(D8:D12,0,G8:G12,"SÍ") -> 4 | H16: RIESGO GLOBAL: | I16: =IF(B16/B15>0.6,"MEDIO","BAJO") -> MEDIO
A17: Valor original activos en uso: | B17: =SUMIFS(B8:B12,D8:D12,0,G8:G12,"SÍ") -> 623000000
A21: Activos que requieren revisión: | B21: =B16 -> 4
D22: =B17 -> 623000000

Sheet PT_D.8_Revaluaciones
A1: PT D.8 - REVALUACIONES Y RAZONABILIDAD
A2: NIC 16 - Valor Razonable | Objetivo: Verificar razonabilidad de revaluaciones
A4: Período: | B4: 2024
A7: Activo | B7: Valor Anterior | C7: Revaluación | D7: Valor Revaluado | E7: % Cambio | F7: Avalúo Profesional | G7: Fecha Avalúo | H7: Riesgo | I7: Estado | J7: Acción
A8: Edificio Sede | B8: 2800000000 | C8: 420000000 | D8: =B8+C8 -> 3220000000 | E8: =C8/B8 -> 0.15 | F8: SÍ | G8: 15/11/2024 | H8: =IF(F8="NO","CRÍTICO",IF(E8>0.3,"ALTO","BAJO")) -> BAJO | I8: =IF(H8="CRÍTICO","⛔ SIN AVALÚO",IF(H8="ALTO","🔴 REVISAR","✓ RAZONABLE")) -> ✓ RAZONABLE | J8: =IF(F8="NO","Obtener avalúo profesional",IF(E8>0.3,"Verificar valor mercado","Ninguna")) -> Ninguna
A9: Terreno Bodega | B9: 850000000 | C9: 510000000 | D9: =B9+C9 -> 1360000000 | E9: =C9/B9 -> 0.6 | F9: NO | G9: N/A | H9: =IF(F9="NO","CRÍTICO",IF(E9>0.3,"ALTO","BAJO")) -> CRÍTICO | I9: =IF(H9="CRÍTICO","⛔ SIN AVALÚO",IF(H9="ALTO","🔴 REVISAR","✓ RAZONABLE")) -> ⛔ SIN AVALÚO | J9: =IF(F9="NO","Obtener avalúo profesional",IF(E9>0.3,"Verificar valor mercado","Ninguna")) -> Obtener avalúo profesional
A10: Propiedad Norte | B10: 1200000000 | C10: 240000000 | D10: =B10+C10 -> 1440000000 | E10: =C10/B10 -> 0.2 | F10: SÍ | G10: 20/10/2024 | H10: =IF(F10="NO","CRÍTICO",IF(E10>0.3,"ALTO","BAJO")) -> BAJO | I10: =IF(H10="CRÍTICO","⛔ SIN AVALÚO",IF(H10="ALTO","🔴 REVISAR","✓ RAZONABLE")) -> ✓ RAZONABLE | J10: =IF(F10="NO","Obtener avalúo profesional",IF(E10>0.3,"Verificar valor mercado","Ninguna")) -> Ninguna
A11: Terreno Planta | B11: 650000000 | C11: 455000000 | D11: =B11+C11 -> 1105000000 | E11: =C11/B11 -> 0.7 | F11: NO | G11: N/A | H11: =IF(F11="NO","CRÍTICO",IF(E11>0.3,"ALTO","BAJO")) -> CRÍTICO | I11: =IF(H11="CRÍTICO","⛔ SIN AVALÚO",IF(H11="ALTO","🔴 REVISAR","✓ RAZONABLE")) -> ⛔ SIN AVALÚO | J11: =IF(F11="NO","Obtener avalúo profesional",IF(E11>0.3,"Verificar valor mercado","Ninguna")) -> Obtener avalúo profesional
A13: EVALUACIÓN DE REVALUACIONES
A14: Revaluaciones realizadas: | B14: =COUNTA(A8:A11) -> 4
A15: Sin avalúo profesional: | B15: =COUNTIF(F8:F11,"NO") -> 2
A16: Monto revaluado sin soporte: | B16: =SUMIF(F8:F11,"NO",C8:C11) -> 965000000 | H16: RIESGO GLOBAL: | I16: =IF(B15>0,"CRÍTICO","BAJO") -> CRÍTICO
A21: Revaluaciones sin soporte: | B21: =B15 -> 2
D22: =B16 -> 965000000

Sheet PT_D.9_Arrendados
A1: PT D.9 - ACTIVOS ARRENDADOS CONTABILIZADOS COMO PROPIOS
A2: NIIF 16 - Clasificación | Objetivo: Detectar arrendamientos clasificados como PPE
A4: Fecha de análisis: | B4: 31/12/2024
A7: Activo | B7: Valor Registrado | C7: Contrato | D7: Opción Compra | E7: Transfiere Propiedad | F7: Tipo Real | G7: Registrado Como | H7: Riesgo | I7: Estado | J7: Acción
A8: Vehículo Operativo | B8: 125000000 | C8: Arrend. Operativo | D8: NO | E8: NO | F8: Arrendamiento | G8: PPE | H8: =IF(AND(F8="Arrendamiento",G8="PPE"),"CRÍTICO","BAJO") -> CRÍTICO | I8: =IF(H8="CRÍTICO","⛔ MAL CLASIFICADO","✓ CORRECTO") -> ⛔ MAL CLASIFICADO | J8: =IF(H8="CRÍTICO","Reclasificar a NIIF 16","Ninguna") -> Reclasificar a NIIF 16
A9: Edificio Propio | B9: 2800000000 | C9: Propiedad | D9: N/A | E9: SÍ | F9: PPE | G9: PPE | H9: =IF(AND(F9="Arrendamiento",G9="PPE"),"CRÍTICO","BAJO") -> BAJO | I9: =IF(H9="CRÍTICO","⛔ MAL CLASIFICADO","✓ CORRECTO") -> ✓ CORRECTO | J9: =IF(H9="CRÍTICO","Reclasificar a NIIF 16","Ninguna") -> Ninguna
A10: Equipo Leasing | B10: 385000000 | C10: Leasing Financiero | D10: SÍ | E10: SÍ | F10: PPE | G10: PPE | H10: =IF(AND(F10="Arrendamiento",G10="PPE"),"CRÍTICO","BAJO") -> BAJO | I10: =IF(H10="CRÍTICO","⛔ MAL CLASIFICADO","✓ CORRECTO") -> ✓ CORRECTO | J10: =IF(H10="CRÍTICO","Reclasificar a NIIF 16","Ninguna") -> Ninguna
A11: Oficinas Arrendadas | B11: 0 | C11: Arrend. Operativo | D11: NO | E11: NO | F11: Arrendamiento | G11: PPE | H11: =IF(AND(F11="Arrendamiento",G11="PPE"),"CRÍTICO","BAJO") -> CRÍTICO | I11: =IF(H11="CRÍTICO","⛔ MAL CLASIFICADO","✓ CORRECTO") -> ⛔ MAL CLASIFICADO | J11: =IF(H11="CRÍTICO","Reclasificar a NIIF 16","Ninguna") -> Reclasificar a NIIF 16
A12: Maquinaria Propia | B12: 520000000 | C12: Propiedad | D12: N/A | E12: SÍ | F12: PPE | G12: PPE | H12: =IF(AND(F12="Arrendamiento",G12="PPE"),"CRÍTICO","BAJO") -> BAJO | I12: =IF(H12="CRÍTICO","⛔ MAL CLASIFICADO","✓ CORRECTO") -> ✓ CORRECTO | J12: =IF(H12="CRÍTICO","Reclasificar a NIIF 16","Ninguna") -> Ninguna
A14: CLASIFICACIÓN DE ACTIVOS
A15: Activos revisados: | B15: =COUNTA(A8:A12) -> 5
A16: Arrendamientos mal clasificados: | B16: =COUNTIF(H8:H12,"CRÍTICO") -> 2 | H16: RIESGO GLOBAL: | I16: =IF(B16>0,"CRÍTICO","BAJO") -> CRÍTICO
A17: Valor a reclasificar: | B17: =SUMIF(H8:H12,"CRÍTICO",B8:B12) -> 125000000
A21: Reclasificaciones requeridas: | B21: =B16 -> 2
D22: =B17 -> 125000000

Sheet PT_D.10_Politicas
A1: PT D.10 - POLÍTICAS DE DEPRECIACIÓN VS INDUSTRIA
A2: Razonabilidad de Políticas | Objetivo: Comparar vida útil con estándares de industria
A4: Industria de referencia: | B4: Manufactura
A7: Categoría | B7: Vida Útil Empresa | C7: Vida Útil Industria | D7: Método Empresa | E7: Método Industria | F7: Diferencia Años | G7: % Dif | H7: Riesgo | I7: Estado | J7: Impacto | K7: Acción
A8: Edificios | B8: 40 | C8: 50 | D8: Línea recta | E8: Línea recta | F8: =B8-C8 -> -10 | G8: =IF(C8=0,0,F8/C8) -> -0.2 | H8: =IF(ABS(G8)>0.3,"ALTO",IF(ABS(G8)>0.15,"MEDIO","BAJO")) -> MEDIO | I8: =IF(H8="ALTO",IF(F8<0,"🔴 MUY ACELERADA","⚠ CONSERVADORA"),IF(H8="MEDIO","⚠ REVISAR","✓ RAZONABLE")) -> ⚠ REVISAR | J8: =IF(F8<0,"Mayor gasto","Menor gasto") -> Mayor gasto | K8: =IF(ABS(G8)>0.3,"Revisar política","Ninguna") -> Ninguna
A9: Vehículos | B9: 5 | C9: 5 | D9: Línea recta | E9: Línea recta | F9: =B9-C9 -> 0 | G9: =IF(C9=0,0,F9/C9) -> 0 | H9: =IF(ABS(G9)>0.3,"ALTO",IF(ABS(G9)>0.15,"MEDIO","BAJO")) -> BAJO | I9: =IF(H9="ALTO",IF(F9<0,"🔴 MUY ACELERADA","⚠ CONSERVADORA"),IF(H9="MEDIO","⚠ REVISAR","✓ RAZONABLE")) -> ✓ RAZONABLE | J9: =IF(F9<0,"Mayor gasto","Menor gasto") -> Menor gasto | K9: =IF(ABS(G9)>0.3,"Revisar política","Ninguna") -> Ninguna
A10: Maquinaria | B10: 8 | C10: 12 | D10: Línea recta | E10: Línea recta | F10: =B10-C10 -> -4 | G10: =IF(C10=0,0,F10/C10) -> -0.33333333 | H10: =IF(ABS(G10)>0.3,"ALTO",IF(ABS(G10)>0.15,"MEDIO","BAJO")) -> ALTO | I10: =IF(H10="ALTO",IF(F10<0,"🔴 MUY ACELERADA","⚠ CONSERVADORA"),IF(H10="MEDIO","⚠ REVISAR","✓ RAZONABLE")) -> 🔴 MUY ACELERADA | J10: =IF(F10<0,"Mayor gasto","Menor gasto") -> Mayor gasto | K10: =IF(ABS(G10)>0.3,"Revisar política","Ninguna") -> Revisar política
A11: Computadores | B11: 3 | C11: 3 | D11: Línea recta | E11: Línea recta | F11: =B11-C11 -> 0 | G11: =IF(C11=0,0,F11/C11) -> 0 | H11: =IF(ABS(G11)>0.3,"ALTO",IF(ABS(G11)>0.15,"MEDIO","BAJO")) -> BAJO | I11: =IF(H11="ALTO",IF(F11<0,"🔴 MUY ACELERADA","⚠ CONSERVADORA"),IF(H11="MEDIO","⚠ REVISAR","✓ RAZONABLE")) -> ✓ RAZONABLE | J11: =IF(F11<0,"Mayor gasto","Menor gasto") -> Menor gasto | K11: =IF(ABS(G11)>0.3,"Revisar política","Ninguna") -> Ninguna
A12: Mobiliario | B12: 10 | C12: 10 | D12: Línea recta | E12: Línea recta | F12: =B12-C12 -> 0 | G12: =IF(C12=0,0,F12/C12) -> 0 | H12: =IF(ABS(G12)>0.3,"ALTO",IF(ABS(G12)>0.15,"MEDIO","BAJO")) -> BAJO | I12: =IF(H12="ALTO",IF(F12<0,"🔴 MUY ACELERADA","⚠ CONSERVADORA"),IF(H12="MEDIO","⚠ REVISAR","✓ RAZONABLE")) -> ✓ RAZONABLE | J12: =IF(F12<0,"Mayor gasto","Menor gasto") -> Menor gasto | K12: =IF(ABS(G12)>0.3,"Revisar política","Ninguna") -> Ninguna
A13: Equipo Prod. | B13: 5 | C13: 10 | D13: Línea recta | E13: Línea recta | F13: =B13-C13 -> -5 | G13: =IF(C13=0,0,F13/C13) -> -0.5 | H13: =IF(ABS(G13)>0.3,"ALTO",IF(ABS(G13)>0.15,"MEDIO","BAJO")) -> ALTO | I13: =IF(H13="ALTO",IF(F13<0,"🔴 MUY ACELERADA","⚠ CONSERVADORA"),IF(H13="MEDIO","⚠ REVISAR","✓ RAZONABLE")) -> 🔴 MUY ACELERADA | J13: =IF(F13<0,"Mayor gasto","Menor gasto") -> Mayor gasto | K13: =IF(ABS(G13)>0.3,"Revisar política","Ninguna") -> Revisar política
A15: ANÁLISIS COMPARATIVO
A16: Categorías revisadas: | B16: =COUNTA(A8:A13) -> 6
A17: Con diferencias significativas: | B17: =COUNTIF(H8:H13,"<>BAJO") -> 3 | I17: RIESGO GLOBAL: | J17: =IF(B18>1,"ALTO",IF(B17>2,"MEDIO","BAJO")) -> ALTO
A18: Políticas muy aceleradas: | B18: =COUNTIFS(F8:F13,"<0",H8:H13,"ALTO") -> 2
A23: Políticas que requieren revisión: | B23: =B17 -> 3
D24: Impacto: Posible sobreestimación del gasto

Sheet PT_D.11_Ventas
A1: PT D.11 - GANANCIAS/PÉRDIDAS EN VENTA DE ACTIVOS
A2: Cálculo Correcto | Objetivo: Verificar cálculo de utilidad/pérdida en venta de activos
A4: Período: | B4: 2024
A7: Fecha | B7: Activo | C7: Costo Original | D7: Depr. Acumulada | E7: Valor Neto | F7: Precio Venta | G7: Resultado Calculado | H7: Resultado Registrado | I7: Diferencia | J7: Riesgo | K7: Estado
A8: 15/03/2024 | B8: Vehículo A | C8: 125000000 | D8: 75000000 | E8: =C8-D8 -> 50000000 | F8: 62000000 | G8: =F8-E8 -> 12000000 | H8: 12000000 | I8: =G8-H8 -> 0 | J8: =IF(ABS(I8)>E8*0.1,"ALTO",IF(I8<>0,"MEDIO","BAJO")) -> BAJO | K8: =IF(J8="ALTO","🔴 ERROR",IF(J8="MEDIO","⚠ REVISAR","✓ CORRECTO")) -> ✓ CORRECTO
A9: 22/06/2024 | B9: Maquinaria B | C9: 385000000 | D9: 230000000 | E9: =C9-D9 -> 155000000 | F9: 178000000 | G9: =F9-E9 -> 23000000 | H9: 23000000 | I9: =G9-H9 -> 0 | J9: =IF(ABS(I9)>E9*0.1,"ALTO",IF(I9<>0,"MEDIO","BAJO")) -> BAJO | K9: =IF(J9="ALTO","🔴 ERROR",IF(J9="MEDIO","⚠ REVISAR","✓ CORRECTO")) -> ✓ CORRECTO
A10: 10/09/2024 | B10: Equipo C | C10: 95000000 | D10: 85000000 | E10: =C10-D10 -> 10000000 | F10: 15000000 | G10: =F10-E10 -> 5000000 | H10: 5000000 | I10: =G10-H10 -> 0 | J10: =IF(ABS(I10)>E10*0.1,"ALTO",IF(I10<>0,"MEDIO","BAJO")) -> BAJO | K10: =IF(J10="ALTO","🔴 ERROR",IF(J10="MEDIO","⚠ REVISAR","✓ CORRECTO")) -> ✓ CORRECTO
A11: 18/11/2024 | B11: Computadores | C11: 45000000 | D11: 40000000 | E11: =C11-D11 -> 5000000 | F11: 8000000 | G11: =F11-E11 -> 3000000 | H11: 3000000 | I11: =G11-H11 -> 0 | J11: =IF(ABS(I11)>E11*0.1,"ALTO",IF(I11<>0,"MEDIO","BAJO")) -> BAJO | K11: =IF(J11="ALTO","🔴 ERROR",IF(J11="MEDIO","⚠ REVISAR","✓ CORRECTO")) -> ✓ CORRECTO
A13: EVALUACIÓN DE RESULTADOS EN VENTAS
A14: Ventas revisadas: | B14: =COUNTA(A8:A11) -> 4
A15: Con diferencias: | B15: =COUNTIF(I8:I11,"<>0") -> 0
A16: Diferencia total: | B16: =SUM(I8:I11) -> 0
A17: Impacto en utilidad: | B17: =B16 -> 0 | I17: RIESGO GLOBAL: | J17: =IF(COUNTIF(J8:J11,"ALTO")>0,"ALTO",IF(B15>0,"MEDIO","BAJO")) -> BAJO
A23: Ajustes requeridos: | B23: =B15 -> 0
D24: =ABS(B16) -> 0

Sheet PT_D.12_Ficticios
A1: PT D.12 - ACTIVOS INEXISTENTES O FICTICIOS
A2: NIA 240 - Existencia | Objetivo: Detectar activos ficticios que inflan el balance
A4: Fecha de verificación: | B4: 31/12/2024
A7: Código | B7: Descripción | C7: Valor Libros | D7: Factura Disponible | E7: Ubicación Física | F7: Placa Visible | G7: En Uso Activo | H7: Riesgo | I7: Estado | J7: Acción
A8: AF-501 | B8: Maquinaria CNC 2020 | C8: 385000000 | D8: SÍ | E8: NO | F8: NO | G8: NO | H8: =IF(OR(D8="NO",AND(E8="NO",G8="NO")),"CRÍTICO","BAJO") -> CRÍTICO | I8: =IF(H8="CRÍTICO","⛔ FICTICIO","✓ EXISTE") -> ⛔ FICTICIO | J8: =IF(H8="CRÍTICO","Dar de baja inmediata","Ninguna") -> Dar de baja inmediata
A9: AF-502 | B9: Vehículo Toyota 2022 | C9: 125000000 | D9: SÍ | E9: SÍ | F9: SÍ | G9: SÍ | H9: =IF(OR(D9="NO",AND(E9="NO",G9="NO")),"CRÍTICO","BAJO") -> BAJO | I9: =IF(H9="CRÍTICO","⛔ FICTICIO","✓ EXISTE") -> ✓ EXISTE | J9: =IF(H9="CRÍTICO","Dar de baja inmediata","Ninguna") -> Ninguna
A10: AF-503 | B10: Equipo Especializado | C10: 520000000 | D10: NO | E10: NO | F10: NO | G10: NO | H10: =IF(OR(D10="NO",AND(E10="NO",G10="NO")),"CRÍTICO","BAJO") -> CRÍTICO | I10: =IF(H10="CRÍTICO","⛔ FICTICIO","✓ EXISTE") -> ⛔ FICTICIO | J10: =IF(H10="CRÍTICO","Dar de baja inmediata","Ninguna") -> Dar de baja inmediata
A11: AF-504 | B11: Edificio Norte | C11: 2800000000 | D11: SÍ | E11: SÍ | F11: N/A | G11: SÍ | H11: =IF(OR(D11="NO",AND(E11="NO",G11="NO")),"CRÍTICO","BAJO") -> BAJO | I11: =IF(H11="CRÍTICO","⛔ FICTICIO","✓ EXISTE") -> ✓ EXISTE | J11: =IF(H11="CRÍTICO","Dar de baja inmediata","Ninguna") -> Ninguna
A12: AF-505 | B12: Computadores 50 Und | C12: 185000000 | D12: SÍ | E12: SÍ | F12: SÍ | G12: SÍ | H12: =IF(OR(D12="NO",AND(E12="NO",G12="NO")),"CRÍTICO","BAJO") -> BAJO | I12: =IF(H12="CRÍTICO","⛔ FICTICIO","✓ EXISTE") -> ✓ EXISTE | J12: =IF(H12="CRÍTICO","Dar de baja inmediata","Ninguna") -> Ninguna
A14: DETECCIÓN DE ACTIVOS FICTICIOS
A15: Activos verificados: | B15: =COUNTA(A8:A12) -> 5
A16: Activos ficticios detectados: | B16: =COUNTIF(H8:H12,"CRÍTICO") -> 2 | H16: RIESGO GLOBAL: | I16: =IF(B16>0,"CRÍTICO","BAJO") -> CRÍTICO
A17: Valor de activos ficticios: | B17: =SUMIF(H8:H12,"CRÍTICO",C8:C12) -> 905000000
A21: Bajas requeridas: | B21: =B16 -> 2 | C21: activos ficticios
D22: =B17 -> 905000000
